Workbook

Sheet README
A1: Liquid Alchemy Content Database v1
A2: Repo-ready workbook with normalized content sheets plus App_JSON_Export compatibility layer.
A3: Use the source tabs as canonical content. Use export/normalization sheets to generate current-app JSON.
A4: Do not treat App_JSON_Export as the source of truth; it is an app compatibility target.
A5: Images are referenced by path/status only; do not embed images.
A6: User state is excluded from canonical content.
A7: Zero-proof ABV must be calculated from ingredients[] only, never riffs/notes/lore.

Sheet Packs
A1: pack_id | B1: pack_name | C1: pack_version | D1: status | E1: recipe_count | F1: source_file | G1: created_at | H1: notes
A2: pack_000_import_20260603_2145 | B2: Imported Snapshot 2026-06-03 21:45 | C2: 1 | D2: imported_needs_review | E2: 108 | F2: 20260603_2145.json | G2: 2026-06-06 | H2: Initial import from current app JSON.
A3: pack_001_zero_proof_atk | B3: Zero-Proof ATK Spritzers & Refreshers | C3: 1 | D3: draft_needs_review | E3: 4 | F3: User-provided ATK/Claude extraction | G3: 2026-06-06 | H3: Adds four zero-proof drinks recovered from pre-Cursor/sandbox period.
A4: pack_002_attaboy_bug_family | B4: Attaboy Bug Cocktail Family | C4: 1 | D4: draft_needs_review | E4: 4 | F4: liquid_alchemy_attaboy_bug_cocktails.txt | G4: 2026-06-04 | H4: Attaboy Bug Cocktail family: Mosquito, Praying Mantis, Maverick, Lantern Fly.

Sheet Recipes
A1: recipe_id | B1: name | C1: family_id | D1: family | E1: subfamily_id | F1: subfamily | G1: base_spirit | H1: glass_id | I1: glass | J1: serve_style | K1: difficulty | L1: occasion | M1: season | N1: tags | O1: rating | P1: source_added_at | Q1: boozy | R1: sweet | S1: sour | T1: bitter | U1: fruity | V1: herbal | W1: smoky | X1: spicy | Y1: rich | Z1: pack_id | AA1: content_version | AB1: status | AC1: curiosity_hook | AD1: why_it_matters | AE1: related_recipe_ids | AF1: publish_ready | AG1: aka | AH1: obscura | AI1: craftLinks | AJ1: sourceUrl
A2: dame_blanche_au_poire | B2: Dame Blanche au Poire | C2: sour | D2: Sour | E2: daisy | F2: Daisy | G2: Gin | H2: coupe | I2: Coupe | J2: Up | K2: Easy | L2: Aperitivo | M2: Year-Round | N2: Sour/Tart, Fruity, Herbal/Botanical, Light/Refreshing, Elegant | O2: 0 | P2: 1780281499931 | Q2: 6 | R2: 4 | S2: 6 | T2: 1 | U2: 5 | V2: 0 | W2: 0 | X2: 0 | Y2: 1 | Z2: pack_000_import_20260603_2145 | AA2: 1 | AB2: imported_needs_review | AF2: FALSE | AH2: FALSE | AI2: []
A3: old_fashioned_classic | B3: Old Fashioned | C3: old_fashioned | D3: Old Fashioned | E3: core_old_fashioned | F3: Core Old Fashioned | G3: Bourbon | H3: rocks_old_fashioned | I3: Rocks/Old Fashioned | J3: On the Rocks | K3: Easy | L3: Nightcap | M3: Year-Round | N3: Boozy, Sweet, Bitter, Rich | O3: 0 | P3: 1780281499931 | Q3: 9 | R3: 4 | S3: 0 | T3: 6 | U3: 2 | V3: 0 | W3: 0 | X3: 1 | Y3: 5 | Z3: pack_000_import_20260603_2145 | AA3: 1 | AB3: imported_needs_review | AF3: FALSE | AH3: FALSE | AI3: []
A4: rosemary_fizz | B4: Rosemary Fizz | C4: sour | D4: Sour | E4: fizz | F4: Fizz | G4: Vodka | H4: coupe | I4: Coupe | J4: Up | K4: Medium | L4: Aperitivo | M4: Summer | N4: Floral, Herbal/Botanical, Fruity, Sour/Tart, Sparkling, Elegant | O4: 0 | P4: 1780270791298 | Q4: 5 | R4: 4 | S4: 4 | T4: 0 | U4: 3 | V4: 5 | W4: 0 | X4: 0 | Y4: 3 | Z4: pack_000_import_20260603_2145 | AA4: 1 | AB4: imported_needs_review | AF4: FALSE | AH4: FALSE | AI4: []
A5: first_class_pass | B5: First Class Pass | C5: highball | D5: Highball | E5: core_highball | F5: Core Highball | G5: Whiskey | H5: collins_highball | I5: Collins/Highball | J5: On the Rocks | K5: Easy | L5: Aperitivo | M5: Summer | N5: Herbal/Botanical, Floral, Light/Refreshing, Fruity, Elegant | O5: 0 | P5: 1780270198088 | Q5: 4 | R5: 3 | S5: 2 | T5: 0 | U5: 2 | V5: 5 | W5: 0 | X5: 0 | Y5: 1 | Z5: pack_000_import_20260603_2145 | AA5: 1 | AB5: imported_needs_review | AF5: FALSE | AH5: FALSE | AI5: []
A6: cold_fashioned | B6: Cold Fashioned | C6: old_fashioned | D6: Old Fashioned | E6: core_old_fashioned | F6: Core Old Fashioned | G6: Bourbon | H6: rocks_old_fashioned | I6: Rocks/Old Fashioned | J6: Frozen | K6: Medium | L6: Party | M6: Summer | N6: Boozy, Sweet, Bitter, Rich, Sour/Tart | O6: 0 | P6: 1780269740325 | Q6: 7 | R6: 4 | S6: 3 | T6: 4 | U6: 2 | V6: 0 | W6: 0 | X6: 1 | Y6: 4 | Z6: pack_000_import_20260603_2145 | AA6: 1 | AB6: imported_needs_review | AF6: FALSE | AH6: FALSE | AI6: []
A7: classic_margarita | B7: Classic Margarita | C7: sour | D7: Sour | E7: daisy | F7: Daisy | G7: Tequila | H7: other | I7: Other | J7: On the Rocks | K7: Easy | L7: Party/Batch | M7: Summer | N7: Sour/Tart, Fruity, Light/Refreshing, Sweet | O7: 0 | P7: 1780198574911 | Q7: 6 | R7: 4 | S7: 8 | T7: 1 | U7: 3 | V7: 1 | W7: 0 | X7: 0 | Y7: 1 | Z7: pack_000_import_20260603_2145 | AA7: 1 | AB7: imported_needs_review | AF7: FALSE | AH7: FALSE | AI7: []
A8: french_007 | B8: French 007 | C8: sour | D8: Sour | E8: fizz | F8: Fizz | G8: Champagne/Prosecco | H8: champagne_flute | I8: Champagne Flute | J8: Up | K8: Easy | L8: Aperitivo | M8: Year-Round | N8: Fruity, Sparkling, Sweet, Light/Refreshing, Elegant | O8: 0 | P8: 1780198575011 | Q8: 3 | R8: 5 | S8: 1 | T8: 0 | U8: 7 | V8: 0 | W8: 0 | X8: 0 | Y8: 2 | Z8: pack_000_import_20260603_2145 | AA8: 1 | AB8: imported_needs_review | AF8: FALSE | AH8: FALSE | AI8: []
A9: classic_martini | B9: Classic Martini | C9: martini_and_manhattan | D9: Martini & Manhattan | E9: martini_style | F9: Martini Style | G9: Gin | H9: martini | I9: Martini | J9: Up | K9: Medium | L9: Aperitivo | M9: Year-Round | N9: Boozy, Herbal/Botanical, Elegant, Light/Refreshing | O9: 0 | P9: 1780198574511 | Q9: 9 | R9: 1 | S9: 0 | T9: 2 | U9: 0 | V9: 7 | W9: 0 | X9: 0 | Y9: 1 | Z9: pack_000_import_20260603_2145 | AA9: 1 | AB9: imported_needs_review | AF9: FALSE | AH9: FALSE | AI9: []
A10: classic_manhattan | B10: Manhattan | C10: martini_and_manhattan | D10: Martini & Manhattan | E10: manhattan_style | F10: Manhattan Style | G10: Whiskey | H10: coupe | I10: Coupe | J10: Up | K10: Easy | L10: Nightcap | M10: Fall | N10: Boozy, Bitter, Rich, Sweet, Elegant | O10: 0 | P10: 1780198574531 | Q10: 9 | R10: 4 | S10: 0 | T10: 5 | U10: 2 | V10: 3 | W10: 0 | X10: 2 | Y10: 6 | Z10: pack_000_import_20260603_2145 | AA10: 1 | AB10: imported_needs_review | AF10: FALSE | AH10: FALSE | AI10: []
A11: classic_daiquiri | B11: Classic Daiquiri | C11: sour | D11: Sour | E11: core_sour | F11: Core Sour | G11: Rum | H11: coupe | I11: Coupe | J11: Up | K11: Easy | L11: Aperitivo | M11: Summer | N11: Sour/Tart, Light/Refreshing, Sweet, Fruity | O11: 0 | P11: 1780198574551 | Q11: 6 | R11: 4 | S11: 7 | T11: 0 | U11: 3 | V11: 0 | W11: 0 | X11: 0 | Y11: 1 | Z11: pack_000_import_20260603_2145 | AA11: 1 | AB11: imported_needs_review | AF11: FALSE | AH11: FALSE | AI11: []
A12: classic_negroni | B12: Negroni | C12: negroni | D12: Negroni | E12: unknown | G12: Gin | H12: rocks_old_fashioned | I12: Rocks/Old Fashioned | J12: On the Rocks | K12: Easy | L12: Aperitivo | M12: Year-Round | N12: Bitter, Herbal/Botanical, Boozy, Sweet, Elegant | O12: 0 | P12: 1780198574571 | Q12: 7 | R12: 4 | S12: 0 | T12: 8 | U12: 1 | V12: 6 | W12: 0 | X12: 1 | Y12: 3 | Z12: pack_000_import_20260603_2145 | AA12: 1 | AB12: imported_needs_review | AF12: FALSE | AH12: FALSE | AI12: []
A13: classic_whiskey_sour | B13: Whiskey Sour | C13: sour | D13: Sour | E13: egg_white_sour | F13: Egg White Sour | G13: Bourbon | H13: rocks_old_fashioned | I13: Rocks/Old Fashioned | J13: On the Rocks | K13: Easy | L13: Anytime | M13: Year-Round | N13: Sour/Tart, Sweet, Fruity, Creamy/Rich | O13: 0 | P13: 1780198574591 | Q13: 6 | R13: 5 | S13: 7 | T13: 1 | U13: 2 | V13: 0 | W13: 0 | X13: 1 | Y13: 4 | Z13: pack_000_import_20260603_2145 | AA13: 1 | AB13: imported_needs_review | AF13: FALSE | AH13: FALSE | AI13: []
A14: moscow_mule | B14: Moscow Mule | C14: highball | D14: Highball | E14: ginger_highball_buck | F14: Ginger Highball / Buck | G14: Vodka | H14: copper_mug | I14: Copper Mug | J14: On the Rocks | K14: Easy | L14: Party/Batch | M14: Summer | N14: Light/Refreshing, Spicy, Sparkling | O14: 0 | P14: 1780198574611 | Q14: 4 | R14: 2 | S14: 3 | T14: 0 | U14: 1 | V14: 0 | W14: 0 | X14: 5 | Y14: 0 | Z14: pack_000_import_20260603_2145 | AA14: 1 | AB14: imported_needs_review | AF14: FALSE | AH14: FALSE | AI14: []
A15: classic_cosmopolitan | B15: Cosmopolitan | C15: sour | D15: Sour | E15: daisy | F15: Daisy | G15: Vodka | H15: martini | I15: Martini | J15: Up | K15: Easy | L15: Party/Batch | M15: Year-Round | N15: Fruity, Sour/Tart, Light/Refreshing, Elegant | O15: 0 | P15: 1780198574631 | Q15: 5 | R15: 4 | S15: 6 | T15: 0 | U15: 7 | V15: 0 | W15: 0 | X15: 0 | Y15: 1 | Z15: pack_000_import_20260603_2145 | AA15: 1 | AB15: imported_needs_review | AF15: FALSE | AH15: FALSE | AI15: []
A16: aperol_spritz | B16: Aperol Spritz | C16: spritz_and_aperitivo | D16: Spritz & Aperitivo | E16: classic_spritz | F16: Classic Spritz | G16: Aperol | H16: wine_glass | I16: Wine Glass | J16: On the Rocks | K16: Easy | L16: Aperitivo | M16: Summer | N16: Light/Refreshing, Sparkling, Bitter, Fruity, Elegant | O16: 0 | P16: 1780198574651 | Q16: 2 | R16: 4 | S16: 1 | T16: 5 | U16: 4 | V16: 2 | W16: 0 | X16: 0 | Y16: 1 | Z16: pack_000_import_20260603_2145 | AA16: 1 | AB16: imported_needs_review | AF16: FALSE | AH16: FALSE | AI16: []
A17: french_75 | B17: French 75 | C17: sour | D17: Sour | E17: fizz | F17: Fizz | G17: Gin | H17: champagne_flute | I17: Champagne Flute | J17: Up | K17: Easy | L17: Aperitivo | M17: Spring | N17: Sparkling, Sour/Tart, Elegant, Light/Refreshing, Boozy | O17: 0 | P17: 1780198574671 | Q17: 6 | R17: 3 | S17: 5 | T17: 0 | U17: 1 | V17: 3 | W17: 0 | X17: 0 | Y17: 1 | Z17: pack_000_import_20260603_2145 | AA17: 1 | AB17: imported_needs_review | AF17: FALSE | AH17: FALSE | AI17: []
A18: classic_sidecar | B18: Sidecar | C18: sour | D18: Sour | E18: daisy | F18: Daisy | G18: Cognac | H18: coupe | I18: Coupe | J18: Up | K18: Easy | L18: After Dinner | M18: Fall | N18: Sour/Tart, Boozy, Sweet, Elegant | O18: 0 | P18: 1780198573511 | Q18: 7 | R18: 4 | S18: 6 | T18: 1 | U18: 2 | V18: 0 | W18: 0 | X18: 0 | Y18: 3 | Z18: pack_000_import_20260603_2145 | AA18: 1 | AB18: imported_needs_review | AF18: FALSE | AH18: FALSE | AI18: []
A19: pisco_sour | B19: Pisco Sour | C19: sour | D19: Sour | E19: egg_white_sour | F19: Egg White Sour | G19: Pisco | H19: coupe | I19: Coupe | J19: Up | K19: Medium | L19: Aperitivo | M19: Year-Round | N19: Sour/Tart, Fruity, Creamy/Rich, Light/Refreshing | O19: 0 | P19: 1780198573531 | Q19: 6 | R19: 4 | S19: 7 | T19: 2 | U19: 3 | V19: 0 | W19: 0 | X19: 0 | Y19: 4 | Z19: pack_000_import_20260603_2145 | AA19: 1 | AB19: imported_needs_review | AF19: FALSE | AH19: FALSE | AI19: []
A20: bees_knees | B20: Bee's Knees | C20: sour | D20: Sour | E20: core_sour | F20: Core Sour | G20: Gin | H20: coupe | I20: Coupe | J20: Up | K20: Easy | L20: Aperitivo | M20: Spring | N20: Sour/Tart, Herbal/Botanical, Sweet, Light/Refreshing, Elegant | O20: 0 | P20: 1780198573551 | Q20: 6 | R20: 5 | S20: 6 | T20: 1 | U20: 1 | V20: 5 | W20: 0 | X20: 0 | Y20: 2 | Z20: pack_000_import_20260603_2145 | AA20: 1 | AB20: imported_needs_review | AF20: FALSE | AH20: FALSE | AI20: []
A21: classic_gimlet | B21: Gimlet | C21: sour | D21: Sour | E21: core_sour | F21: Core Sour | G21: Gin | H21: coupe | I21: Coupe | J21: Up | K21: Easy | L21: Aperitivo | M21: Spring | N21: Sour/Tart, Herbal/Botanical, Light/Refreshing, Sweet | O21: 0 | P21: 1780198573571 | Q21: 6 | R21: 4 | S21: 7 | T21: 1 | U21: 2 | V21: 5 | W21: 0 | X21: 0 | Y21: 1 | Z21: pack_000_import_20260603_2145 | AA21: 1 | AB21: imported_needs_review | AF21: FALSE | AH21: FALSE | AI21: []
A22: southside | B22: Southside | C22: sour | D22: Sour | E22: core_sour | F22: Core Sour | G22: Gin | H22: coupe | I22: Coupe | J22: Up | K22: Easy | L22: Aperitivo | M22: Summer | N22: Sour/Tart, Herbal/Botanical, Light/Refreshing, Fruity | O22: 0 | P22: 1780198573591 | Q22: 6 | R22: 4 | S22: 6 | T22: 1 | U22: 2 | V22: 6 | W22: 0 | X22: 0 | Y22: 1 | Z22: pack_000_import_20260603_2145 | AA22: 1 | AB22: imported_needs_review | AF22: FALSE | AH22: FALSE | AI22: []
A23: clover_club | B23: Clover Club | C23: sour | D23: Sour | E23: egg_white_sour | F23: Egg White Sour | G23: Gin | H23: coupe | I23: Coupe | J23: Up | K23: Medium | L23: Aperitivo | M23: Spring | N23: Fruity, Sour/Tart, Creamy/Rich, Elegant, Floral | O23: 0 | P23: 1780198573611 | Q23: 5 | R23: 4 | S23: 5 | T23: 1 | U23: 5 | V23: 3 | W23: 0 | X23: 0 | Y23: 4 | Z23: pack_000_import_20260603_2145 | AA23: 1 | AB23: imported_needs_review | AF23: FALSE | AH23: FALSE | AI23: []
A24: rob_roy | B24: Rob Roy | C24: martini_and_manhattan | D24: Martini & Manhattan | E24: manhattan_style | F24: Manhattan Style | G24: Scotch | H24: coupe | I24: Coupe | J24: Up | K24: Easy | L24: Nightcap | M24: Winter | N24: Boozy, Bitter, Rich, Sweet, Elegant, Smoky | O24: 0 | P24: 1780198573631 | Q24: 9 | R24: 3 | S24: 0 | T24: 5 | U24: 1 | V24: 2 | W24: 4 | X24: 2 | Y24: 5 | Z24: pack_000_import_20260603_2145 | AA24: 1 | AB24: imported_needs_review | AF24: FALSE | AH24: FALSE | AI24: []
... A109: sicilian_sojourn | B109: Sicilian Sojourn | C109: highball | D109: Highball | E109: spritz | F109: Spritz | G109: Non-alcoholic | H109: collins_highball | I109: Collins/Highball | J109: On the Rocks | K109: Easy | L109: Aperitivo | M109: Winter | N109: Light/Refreshing, Sparkling, Herbal/Botanical, Fruity, Elegant | O109: 0 | P109: 1780281499905 | Q109: 0 | R109: 3 | S109: 5 | T109: 2 | U109: 7 | V109: 5 | W109: 0 | X109: 0 | Y109: 1 | Z109: pack_000_import_20260603_2145 | AA109: 1 | AB109: imported_needs_review | AF109: FALSE | AH109: FALSE | AI109: []
A110: pomegranate_spritzer | B110: Pomegranate Spritzer | C110: highball | D110: Highball | E110: spritz | F110: Spritz | G110: Non-alcoholic | H110: collins_highball | I110: Collins/Highball | J110: On the Rocks | K110: Easy | L110: Anytime | M110: Fall | N110: Light/Refreshing, Sparkling, Fruity, Bitter, Elegant | O110: 0 | P110: 1780281501000 | Q110: 0 | R110: 3 | S110: 4 | T110: 3 | U110: 7 | V110: 0 | W110: 0 | X110: 0 | Y110: 0 | Z110: pack_001_zero_proof_atk | AA110: 1 | AB110: draft_needs_review | AD110: Zero-proof base recipe. Optional alcoholic riffs must not affect ABV. | AF110: FALSE | AH110: FALSE | AI110: []
A111: hibiscus_guava_agua_fresca | B111: Hibiscus Guava Agua Fresca | C111: zero_proof | D111: Zero Proof | E111: agua_fresca | F111: Agua Fresca | G111: Non-alcoholic | H111: collins_highball | I111: Collins/Highball | J111: On the Rocks | K111: Easy | L111: Brunch | M111: Summer | N111: Light/Refreshing, Fruity, Floral, Herbal/Botanical, Sour/Tart | O111: 0 | P111: 1780281502000 | Q111: 0 | R111: 3 | S111: 5 | T111: 2 | U111: 8 | V111: 4 | W111: 0 | X111: 0 | Y111: 0 | Z111: pack_001_zero_proof_atk | AA111: 1 | AB111: draft_needs_review | AD111: Zero-proof base recipe. Optional alcoholic riffs must not affect ABV. | AF111: FALSE | AH111: FALSE | AI111: []
A112: raspberry_lime_rickey | B112: Raspberry Lime Rickey | C112: highball | D112: Highball | E112: rickey | F112: Rickey | G112: Non-alcoholic | H112: collins_highball | I112: Collins/Highball | J112: On the Rocks | K112: Medium | L112: Warm Weather | M112: Summer | N112: Light/Refreshing, Sparkling, Fruity, Sour/Tart, Elegant | O112: 0 | P112: 1780281503000 | Q112: 0 | R112: 3 | S112: 6 | T112: 0 | U112: 7 | V112: 0 | W112: 0 | X112: 0 | Y112: 0 | Z112: pack_001_zero_proof_atk | AA112: 1 | AB112: draft_needs_review | AD112: Zero-proof base recipe. Optional alcoholic riffs must not affect ABV. | AF112: FALSE | AH112: FALSE | AI112: []
A113: cantaloupe_fresno_chile_spritzer | B113: Cantaloupe and Fresno Chile Spritzer | C113: highball | D113: Highball | E113: spritz | F113: Spritz | G113: Non-alcoholic | H113: collins_highball | I113: Collins/Highball | J113: On the Rocks | K113: Easy | L113: Warm Weather | M113: Summer | N113: Light/Refreshing, Sparkling, Fruity, Spicy, Elegant | O113: 0 | P113: 1780281504000 | Q113: 0 | R113: 2 | S113: 1 | T113: 0 | U113: 8 | V113: 0 | W113: 0 | X113: 4 | Y113: 0 | Z113: pack_001_zero_proof_atk | AA113: 1 | AB113: draft_needs_review | AD113: Zero-proof base recipe. Optional alcoholic riffs must not affect ABV. | AF113: FALSE | AH113: FALSE | AI113: []
A114: mosquito | B114: Mosquito | C114: sour | D114: Sour | E114: daisy_equal_parts | F114: Daisy — Equal Parts | G114: Mezcal | H114: coupe | I114: Coupe | J114: Up | K114: Easy | L114: After Dinner | M114: Year-Round | N114: Sour/Tart, Bitter, Smoky, Spicy, Boozy | O114: 0 | P114: 1780281600000 | Q114: 6 | R114: 3 | S114: 6 | T114: 7 | U114: 2 | V114: 2 | W114: 6 | X114: 5 | Y114: 1 | Z114: pack_002_attaboy_bug_family | AA114: 1 | AB114: draft_needs_review | AC114: Sam Ross has described the equal-parts format as a balancing discipline: every component must earn its quarter of the glass. There is nowhere to hide. A weak spirit, a stale citrus, an under-sweetened ginger juice — the format exposes all of it. This is the equal-parts lesson: simplicity is the hardest standard to meet. | AD114: The Mosquito is the seed of a creative system — a template remixed from a template, now producing its own family of drinks at one of the most influential bars in contemporary craft cocktail culture. The equal-parts format, descended from the Last Word through the Paper Plane, is one of the most generative structures in modern mixology. | AE114: paper_plane,last_word | AF114: FALSE | AH114: FALSE | AI114: ["sweetened-ginger-juice"] | AJ114: https://punchdrink.com/articles/attaboy-equal-parts-cocktail-recipes/
A115: praying_mantis | B115: Praying Mantis | C115: sour | D115: Sour | E115: daisy_equal_parts | F115: Daisy — Equal Parts | G115: Scotch | H115: coupe | I115: Coupe | J115: Up | K115: Medium | L115: After Dinner | M115: Year-Round | N115: Sour/Tart, Bitter, Smoky, Boozy, Herbal/Botanical | O115: 0 | P115: 1780281600001 | Q115: 7 | R115: 2 | S115: 6 | T115: 8 | U115: 1 | V115: 5 | W115: 7 | X115: 3 | Y115: 1 | Z115: pack_002_attaboy_bug_family | AA115: 1 | AB115: draft_needs_review | AC115: Gran Classico and Campari occupy similar roles — bitter liqueur, similar color, similar ABV — but produce meaningfully different drinks. Understanding the functional differences between bitter liqueurs (sweetness level, herbal character, proof, finish) is essential to working intelligently with the Daisy template. Swapping one bitter for another is not a neutral substitution. | AD115: The most complex and demanding drink in the Bug family — a demonstration that the equal-parts template can carry serious weight when the ingredients are chosen with precision. Islay Scotch in a shaken equal-parts sour is an unusual move that works. | AE115: mosquito,paper_plane,last_word | AF115: FALSE | AH115: FALSE | AI115: ["sweetened-ginger-juice"] | AJ115: https://punchdrink.com/articles/attaboy-equal-parts-cocktail-recipes/
A116: maverick | B116: Maverick | C116: sour | D116: Sour | E116: daisy_equal_parts | F116: Daisy — Equal Parts | G116: Gin | H116: coupe | I116: Coupe | J116: Up | K116: Easy | L116: Aperitivo | M116: Year-Round | N116: Sour/Tart, Herbal/Botanical, Light/Refreshing, Fruity, Elegant | O116: 0 | P116: 1780281600002 | Q116: 5 | R116: 4 | S116: 6 | T116: 4 | U116: 2 | V116: 6 | W116: 0 | X116: 3 | Y116: 1 | Z116: pack_002_attaboy_bug_family | AA116: 1 | AB116: draft_needs_review | AC116: Shaking mint rather than muddling it is a technique choice with real consequences. Muddling ruptures the cell walls and releases chlorophyll along with the aromatics — producing a greener, more aggressive, sometimes bitter mint character. Shaking whole leaves extracts aromatics more gently. Neither is wrong; they produce different results. This drink needs the gentle version. | AD116: The Maverick closes the circle — a gin drink descended from a gin drink, routed through bourbon and mezcal along the way. The most approachable entry point into the Bug family, and a demonstration that the equal-parts template is as comfortable with lightness as with complexity. | AE116: mosquito,last_word,paper_plane | AF116: FALSE | AH116: FALSE | AI116: ["sweetened-ginger-juice"] | AJ116: https://punchdrink.com/articles/attaboy-equal-parts-cocktail-recipes/
A117: lantern_fly | B117: Lantern Fly | C117: sour | D117: Sour | E117: daisy_equal_parts | F117: Daisy — Equal Parts | G117: Rum | H117: coupe | I117: Coupe | J117: Up | K117: Medium | L117: After Dinner | M117: Year-Round | N117: Sour/Tart, Bitter, Fruity, Boozy, Spicy | O117: 0 | P117: 1780281600003 | Q117: 6 | R117: 3 | S117: 6 | T117: 7 | U117: 5 | V117: 4 | W117: 0 | X117: 4 | Y117: 2 | Z117: pack_002_attaboy_bug_family | AA117: 1 | AB117: draft_needs_review | AC117: Amargo-Vallet is a case study in how a drink's bitter component determines its character as much as the base spirit does. Swap Amargo-Vallet for Campari in this recipe and you have a different drink — same structure, same proportions, genuinely different experience. The bitter element in an equal-parts Daisy is not interchangeable. Choose it as carefully as you choose the spirit. | AD117: The most ingredient-specific drink in the Bug family, and the one most likely to reward the curious drinker who seeks it out. Amargo-Vallet is genuinely obscure outside of cocktail enthusiast circles; Jamaican pot still rum is underappreciated even among rum drinkers. The Lantern Fly puts both in a context where they cannot hide. | AE117: mosquito,paper_plane,last_word | AF117: FALSE | AH117: FALSE | AI117: ["sweetened-ginger-juice"] | AJ117: https://punchdrink.com/articles/attaboy-equal-parts-cocktail-recipes/

Sheet Ingredients
A1: ingredient_id | B1: name | C1: style | D1: flavor_notes | E1: category | F1: status
A2: absinthe | B2: Absinthe | F2: imported_needs_review
A3: agave_nectar | B3: Agave nectar | F3: imported_needs_review
A4: agave_syrup | B4: Agave syrup | F4: imported_needs_review
A5: agave_syrup_1_1 | B5: Agave syrup (1:1) | F5: imported_needs_review
A6: aged_apple_brandy_clear_creek_8_year | B6: Aged apple brandy (Clear Creek 8-year) | F6: imported_needs_review
A7: aged_rum | B7: Aged rum | F7: imported_needs_review
A8: allspice_dram | B8: Allspice dram | F8: imported_needs_review
A9: amaretto | B9: Amaretto | F9: imported_needs_review
A10: amaro | B10: Amaro | F10: imported_needs_review
A11: amaro_averna | B11: Amaro Averna | F11: imported_needs_review
A12: amaro_montenegro | B12: Amaro Montenegro | F12: imported_needs_review
A13: amaro_nonino | B13: Amaro Nonino | F13: imported_needs_review
... A224: zucca_rabarbaro | B224: Zucca Rabarbaro | F224: imported_needs_review
A225: pomegranate_juice_unsweetened | B225: Unsweetened 100% pomegranate juice | E225: juice | F225: draft_needs_review
A226: simple_syrup | B226: Simple syrup | E226: syrup | F226: draft_needs_review
A227: nonalcoholic_old_fashioned_bitters | B227: Nonalcoholic old-fashioned bitters | E227: mixer | F227: draft_needs_review
A228: seltzer_chilled | B228: Seltzer, chilled | E228: mixer | F228: draft_needs_review
A229: pomegranate_seeds | B229: Pomegranate seeds | E229: produce | F229: draft_needs_review
A230: hibiscus_tea_bags | B230: Hibiscus tea bags | E230: mixer | F230: draft_needs_review
A231: water_room_temperature | B231: Water, room temperature | E231: mixer | F231: draft_needs_review
A232: guava_nectar_chilled | B232: Guava nectar, chilled | E232: juice | F232: draft_needs_review
A233: mint_herb_syrup | B233: Mint Herb Syrup ✨ | E233: syrup | F233: draft_needs_review
A234: fresh_lemon_juice | B234: Fresh lemon juice | E234: juice | F234: draft_needs_review
A235: fresh_mint_leaves | B235: Fresh mint leaves | E235: produce | F235: draft_needs_review
A236: lemon_slices | B236: Lemon slices | E236: produce | F236: draft_needs_review
... A242: fresno_chile | B242: Fresno chile | E242: produce | F242: draft_needs_review
A243: sweetened_ginger_juice | B243: Sweetened ginger juice | D243: House Attaboy prep; see craft item sweetened-ginger-juice. | E243: juice | F243: draft_needs_review
A244: islay_scotch | B244: Islay Scotch | E244: spirit | F244: draft_needs_review
A245: gran_classico | B245: Gran Classico | E245: liqueur | F245: draft_needs_review
A246: amargo_vallet | B246: Amargo-Vallet amaro | E246: amaro | F246: draft_needs_review
A247: doctor_bird_jamaican_pot_still_rum | B247: Jamaican pot still rum (Doctor Bird recommended) | E247: spirit | F247: draft_needs_review
A248: candied_ginger | B248: Candied ginger | E248: garnish | F248: draft_needs_review

Sheet Recipe_Ingredients
A1: recipe_id | B1: sort_order | C1: ingredient_id | D1: ingredient_name_source | E1: amount | F1: unit | G1: prep | H1: note | I1: optional | J1: substitution_note
A2: dame_blanche_au_poire | B2: 1 | C2: gin_citadelle_recommended | D2: Gin (Citadelle recommended) | E2: 1.5 | F2: oz | I2: FALSE
A3: dame_blanche_au_poire | B3: 2 | C3: pear_liqueur | D3: Pear liqueur | E3: 1 | F3: oz | I3: FALSE
A4: dame_blanche_au_poire | B4: 3 | C4: fresh_lemon_juice | D4: Fresh lemon juice | E4: 0.75 | F4: oz | I4: FALSE
A5: dame_blanche_au_poire | B5: 4 | C5: citrus_peel | D5: Citrus peel | E5: 1 | F5: whole | I5: FALSE
A6: old_fashioned_classic | B6: 1 | C6: bourbon | D6: Bourbon | E6: 2 | F6: oz | I6: FALSE
A7: old_fashioned_classic | B7: 2 | C7: simple_syrup | D7: Simple syrup | E7: 0.67 | F7: oz | I7: FALSE
A8: old_fashioned_classic | B8: 3 | C8: angostura_aromatic_bitters | D8: Angostura Aromatic Bitters | E8: 5 | F8: dash | I8: FALSE
A9: old_fashioned_classic | B9: 4 | C9: angostura_orange_bitters | D9: Angostura Orange Bitters | E9: 5 | F9: dash | I9: FALSE
A10: old_fashioned_classic | B10: 5 | C10: cocktail_cherry_juice | D10: Cocktail cherry juice | E10: 1 | F10: tbsp | I10: FALSE
A11: old_fashioned_classic | B11: 6 | C11: orange_peel | D11: Orange peel | E11: 1 | F11: whole | I11: FALSE
A12: old_fashioned_classic | B12: 7 | C12: cocktail_cherry | D12: Cocktail cherry | E12: 1 | F12: whole | I12: FALSE
A13: rosemary_fizz | B13: 1 | C13: vodka_titos | D13: Vodka (Titos) | E13: 2 | F13: oz | I13: FALSE
... A522: sicilian_sojourn | B522: 6 | C522: tarragon_sprig | D522: Tarragon sprig | E522: 1 | F522: whole | I522: FALSE
A523: pomegranate_spritzer | B523: 1 | C523: pomegranate_juice_unsweetened | D523: Unsweetened 100% pomegranate juice | E523: 4 | F523: oz | I523: FALSE
A524: pomegranate_spritzer | B524: 2 | C524: simple_syrup | D524: Simple syrup | E524: 0.5 | F524: oz | I524: FALSE
A525: pomegranate_spritzer | B525: 3 | C525: nonalcoholic_old_fashioned_bitters | D525: Nonalcoholic old-fashioned bitters | E525: 0.25 | F525: tsp | H525: Traditional Angostura bitters also work but are not zero-proof. | I525: FALSE
A526: pomegranate_spritzer | B526: 4 | C526: seltzer_chilled | D526: Seltzer, chilled | E526: 4 | F526: oz | I526: FALSE
A527: pomegranate_spritzer | B527: 5 | C527: pomegranate_seeds | D527: Pomegranate seeds | E527: 1 | F527: whole | G527: garnish | I527: FALSE
A528: hibiscus_guava_agua_fresca | B528: 1 | C528: hibiscus_tea_bags | D528: Hibiscus tea bags | E528: 10 | F528: whole | G528: 100% hibiscus preferred | I528: FALSE
A529: hibiscus_guava_agua_fresca | B529: 2 | C529: water_room_temperature | D529: Water, room temperature | E529: 28 | F529: oz | I529: FALSE
A530: hibiscus_guava_agua_fresca | B530: 3 | C530: guava_nectar_chilled | D530: Guava nectar, chilled | E530: 14 | F530: oz | H530: Substitute pineapple or mango juice. | I530: FALSE
A531: hibiscus_guava_agua_fresca | B531: 4 | C531: mint_herb_syrup | D531: Mint Herb Syrup ✨ | E531: 4 | F531: oz | I531: FALSE
A532: hibiscus_guava_agua_fresca | B532: 5 | C532: fresh_lemon_juice | D532: Fresh lemon juice | E532: 2 | F532: oz | I532: FALSE
A533: hibiscus_guava_agua_fresca | B533: 6 | C533: fresh_mint_leaves | D533: Fresh mint leaves | E533: 0.25 | F533: cup | I533: FALSE
A534: hibiscus_guava_agua_fresca | B534: 7 | C534: lemon_slices | D534: Lemon slices | E534: 8 | F534: whole | G534: garnish | I534: FALSE
A535: raspberry_lime_rickey | B535: 1 | C535: sous_vide_raspberry_syrup | D535: Sous Vide Raspberry Syrup ✨ | E535: 0.75 | F535: cup | I535: FALSE
A536: raspberry_lime_rickey | B536: 2 | C536: fresh_lime_juice | D536: Fresh lime juice | E536: 0.25 | F536: cup | G536: about 2 limes | I536: FALSE
A537: raspberry_lime_rickey | B537: 3 | C537: seltzer_or_club_soda | D537: Seltzer or club soda | E537: 3 | F537: cup | I537: FALSE
A538: raspberry_lime_rickey | B538: 4 | C538: lime_slices | D538: Lime slices | E538: 4 | F538: whole | G538: garnish | I538: FALSE
A539: cantaloupe_fresno_chile_spritzer | B539: 1 | C539: cantaloupe_pieces | D539: Cantaloupe pieces | E539: 2 | F539: cup | G539: 1-inch pieces | I539: FALSE
A540: cantaloupe_fresno_chile_spritzer | B540: 2 | C540: fresno_chile | D540: Fresno chile | E540: 0.5 | F540: whole | G540: stemmed, seeded, and chopped | I540: FALSE
A541: cantaloupe_fresno_chile_spritzer | B541: 3 | C541: seltzer_chilled | D541: Seltzer, chilled | E541: 3 | F541: cup | I541: FALSE
A542: mosquito | B542: 1 | C542: mezcal | D542: Mezcal | E542: 0.75 | F542: oz | I542: FALSE
A543: mosquito | B543: 2 | C543: fresh_lemon_juice | D543: Fresh lemon juice | E543: 0.75 | F543: oz | I543: FALSE
A544: mosquito | B544: 3 | C544: sweetened_ginger_juice | D544: Sweetened ginger juice | E544: 0.75 | F544: oz | I544: FALSE
A545: mosquito | B545: 4 | C545: campari | D545: Campari | E545: 0.75 | F545: oz | I545: FALSE
A546: praying_mantis | B546: 1 | C546: islay_scotch | D546: Islay Scotch | E546: 0.75 | F546: oz | I546: FALSE
A547: praying_mantis | B547: 2 | C547: fresh_lemon_juice | D547: Fresh lemon juice | E547: 0.75 | F547: oz | I547: FALSE
A548: praying_mantis | B548: 3 | C548: sweetened_ginger_juice | D548: Sweetened ginger juice | E548: 0.75 | F548: oz | I548: FALSE
A549: praying_mantis | B549: 4 | C549: gran_classico | D549: Gran Classico | E549: 0.75 | F549: oz | I549: FALSE
A550: maverick | B550: 1 | C550: london_dry_gin | D550: London dry gin | E550: 0.75 | F550: oz | I550: FALSE
A551: maverick | B551: 2 | C551: fresh_lemon_juice | D551: Fresh lemon juice | E551: 0.75 | F551: oz | I551: FALSE
A552: maverick | B552: 3 | C552: sweetened_ginger_juice | D552: Sweetened ginger juice | E552: 0.75 | F552: oz | I552: FALSE
A553: maverick | B553: 4 | C553: aperol | D553: Aperol | E553: 0.75 | F553: oz | I553: FALSE
A554: maverick | B554: 5 | C554: fresh_mint_leaves | D554: Fresh mint leaves | E554: 7 | F554: whole | H554: 6–8 leaves; shaken in, not muddled | I554: FALSE
A555: lantern_fly | B555: 1 | C555: doctor_bird_jamaican_pot_still_rum | D555: Jamaican pot still rum (Doctor Bird recommended) | E555: 0.75 | F555: oz | I555: FALSE
A556: lantern_fly | B556: 2 | C556: fresh_lemon_juice | D556: Fresh lemon juice | E556: 0.75 | F556: oz | I556: FALSE
A557: lantern_fly | B557: 3 | C557: sweetened_ginger_juice | D557: Sweetened ginger juice | E557: 0.75 | F557: oz | I557: FALSE
A558: lantern_fly | B558: 4 | C558: amargo_vallet | D558: Amargo-Vallet amaro | E558: 0.75 | F558: oz | I558: FALSE

Sheet Steps
A1: recipe_id | B1: step_number | C1: instruction | D1: source_note
A2: dame_blanche_au_poire | B2: 1 | C2: Place the gin, pear liqueur, and lemon juice in a cocktail shaker. Cover with ice and shake vigorously until well-chilled, about 15 seconds. Strain into a chilled coupe or small tulip glass. Garnish with a citrus peel. | D2: imported_full_instruction
A3: old_fashioned_classic | B3: 1 | C3: Place a large ice cube in a rocks glass. Add the bourbon, simple syrup, both bitters, and cherry juice. Stir with a cocktail mixing spoon for a full 30 seconds until well chilled and properly diluted. Express an orange peel over the glass, run it around the rim, and drop it in. Garnish with a cocktail cherry. | D3: imported_full_instruction
A4: rosemary_fizz | B4: 1 | C4: Add strawberries and one and a half rosemary sprigs to a shaker with simple syrup and muddle. Add egg white, vodka, and lemon juice. Dry shake without ice for at least 15 seconds to build the foam. Add ice and St-Germain and shake again for 15 more seconds. Double strain into a coupe or rocks glass over fresh ice. Top with Prosecco. Garnish with a rosemary sprig. | D4: imported_full_instruction
A5: first_class_pass | B5: 1 | C5: Add cucumber slices and mint leaves to a shaker and muddle gently — bruise the cucumber and press the mint just enough to release the oils without shredding. Add Irish whiskey, elderflower liqueur, vodka, honey syrup, and lime juice. Add ice and shake well. Double strain through a fine strainer into an ice-filled highball glass. Top with chilled yuzu soda. Garnish with a lime wheel and mint sprig. | D5: imported_full_instruction
A6: cold_fashioned | B6: 1 | C6: Add all ingredients to a blender and blend until smooth. Serve in a rocks glass. Garnish with a brulee sugar crisp. For the Old Fashioned mix: combine 150ml black tea, 150g sugar, and 14 dashes aromatic bitters. Stir until sugar dissolves. For the citrus blend: combine 2 parts fresh lemon juice, 1 part fresh orange juice, 1 part fresh grapefruit juice. For the brulee sugar crisp: cut the end off an orange and place it upside down on a jigger. Spread 1 barspoon sugar over the center, add 8-10 drops aromatic bitters, then caramelize with a kitchen torch until fully browned and bubbling. Add a pinch of flaky sea salt as it cools. | D6: imported_full_instruction
A7: classic_margarita | B7: 1 | C7: Prepare a margarita glass with a salted rim. Add tequila, Cointreau, lime juice, and agave syrup to a shaker tin. Add ice and shake hard for 15 seconds. Strain over fresh ice into the prepared glass. Garnish with a lime wheel. | D7: imported_full_instruction
A8: french_007 | B8: 1 | C8: Add the pear and pomegranate liqueurs to a chilled champagne flute. Top with dry champagne or sparkling wine. No stirring needed — the bubbles will do the work. | D8: imported_full_instruction
A9: classic_martini | B9: 1 | C9: Stir gin, vermouth, and bitters with ice for 30-40 seconds until well chilled and properly diluted. Strain into a chilled martini or coupe glass. Express a lemon peel over the surface and either drop it in or perch it on the rim. | D9: imported_full_instruction
A10: classic_manhattan | B10: 1 | C10: Combine whiskey, vermouth, and bitters in a mixing glass with ice. Stir for 30 seconds until well chilled. Strain into a chilled coupe or Nick & Nora glass. Garnish with a cocktail cherry. | D10: imported_full_instruction
A11: classic_daiquiri | B11: 1 | C11: Combine all ingredients in a shaker with ice. Shake hard for 15 seconds. Double strain into a chilled coupe. | D11: imported_full_instruction
A12: classic_negroni | B12: 1 | C12: Combine gin, Campari, and sweet vermouth in a mixing glass with ice. Stir for 30 seconds. Strain over a large ice cube in a rocks glass. Express an orange peel over the surface and drop it in. | D12: imported_full_instruction
A13: classic_whiskey_sour | B13: 1 | C13: Dry shake all ingredients without ice for 15 seconds to emulsify the egg white. Add ice and shake hard for another 15 seconds. Strain into a rocks glass over ice. Dash bitters on the foam and drag a toothpick through for a decorative pattern. | D13: imported_full_instruction
... A106: lantern_fly | B106: 1 | C106: Combine all ingredients in a cocktail shaker with ice. Shake until well chilled. Strain into a chilled coupe. Garnish with candied ginger. | D106: attaboy_bug_family_import

Sheet Garnishes
A1: recipe_id | B1: sort_order | C1: garnish | D1: prep | E1: placement | F1: source_note
A2: dame_blanche_au_poire | B2: 1 | C2: Citrus peel | F2: imported_from_ingredients
A3: old_fashioned_classic | B3: 1 | C3: Cocktail cherry juice | F3: imported_from_ingredients
A4: old_fashioned_classic | B4: 2 | C4: Orange peel | F4: imported_from_ingredients
A5: old_fashioned_classic | B5: 3 | C5: Cocktail cherry | F5: imported_from_ingredients
A6: rosemary_fizz | B6: 1 | C6: Fresh rosemary sprigs | F6: imported_from_ingredients
A7: first_class_pass | B7: 1 | C7: Fresh cucumber slices | F7: imported_from_ingredients
A8: first_class_pass | B8: 2 | C8: Fresh mint leaves | F8: imported_from_ingredients
A9: classic_margarita | B9: 1 | C9: Lime wheel | F9: imported_from_ingredients
A10: classic_martini | B10: 1 | C10: Lemon peel | F10: imported_from_ingredients
A11: classic_manhattan | B11: 1 | C11: Cocktail cherry | F11: imported_from_ingredients
A12: classic_negroni | B12: 1 | C12: Orange peel | F12: imported_from_ingredients
A13: moscow_mule | B13: 1 | C13: Lime wheel | F13: imported_from_ingredients
... A50: sicilian_sojourn | B50: 1 | C50: Tarragon sprig | F50: imported_from_ingredients
A51: mosquito | B51: 1 | C51: Candied ginger | E51: coupe rim or pick | F51: attaboy_bug_family_import
A52: praying_mantis | B52: 1 | C52: Candied ginger | E52: coupe rim or pick | F52: attaboy_bug_family_import
A53: maverick | B53: 1 | C53: Candied ginger | E53: coupe rim or pick | F53: attaboy_bug_family_import
A54: lantern_fly | B54: 1 | C54: Candied ginger | E54: coupe rim or pick | F54: attaboy_bug_family_import

Sheet Lore
A1: recipe_id | B1: story | C1: origin | D1: why_it_works | E1: curiosity_hook | F1: notes | G1: riffs | H1: tasting_notes | I1: creator_id | J1: source_urls | K1: source_notes | L1: review_status
A2: dame_blanche_au_poire | B2: The Dame Blanche is a classic gin sour from the golden age of cocktails, named after the Belgian legend of a white-robed spirit said to haunt mountain passes. Structurally it belongs to the Sour family — spirit, citrus, sweetener — here elevated with pear liqueur for a delicate floral character. | F2: Recipe by @bridget7487049 via ReciMe. Citadelle gin is recommended but any quality London Dry works well. | I2: bridget7487049_via_recime | L2: needs_review
A3: old_fashioned_classic | B3: The Old Fashioned is the oldest known cocktail, dating to the early 1800s — originally called simply a 'cocktail': a spirit, sugar, water, and bitters. The name came later when drinkers began requesting it 'the old-fashioned way' as bartenders started adding juices and liqueurs. It is the template from which nearly all stirred, spirit-forward cocktails descend. | F3: The 30-second stir is non-negotiable — it's what makes the texture silky. Use a good bourbon with some proof (100+) since the dilution will soften it. | L3: needs_review
A4: rosemary_fizz | B4: Created by Damon Williams at Baytowne Provisions in South Walton, Florida — a beachside bar on the Gulf Coast that is not famous and does not need to be. The lineage is what matters here: an egg white sour with elderflower and a sparkling wine top, muddled rosemary and strawberry as the aromatic foundation. The thread runs from the classic Fizz template through the St-Germain era of modern American craft bartending all the way to a bar on the Emerald Coast. Every cocktail has a lineage. This one traces from Paris to New York to the Florida Panhandle, and it is a very good drink. | F4: The St-Germain is added with the ice in the second shake rather than the first — a deliberate choice to protect its delicate floral aromatics from the aggressive friction of the dry shake. It is a small detail that makes a difference. Dry shake for the full 15 seconds; the foam needs the time. Two small strawberries rather than one large one gives better muddling coverage. | G4: Substitute gin for vodka for a more botanical result that leans into the rosemary and elderflower. Omit the Prosecco and serve straight up as a Royale variation. Blackberries in place of strawberries for an autumn version. | L4: needs_review
A5: first_class_pass | B5: An evolution of an original recipe by Jack McGarry, managing partner of The Irish Exit in New York City — the sister bar to The Dead Rabbit, one of the most celebrated cocktail bars in the world. The drink matches cucumber and mint against the floral, herbal character of Irish whiskey, a pairing so natural it is surprising it is not more common. The elderflower liqueur ties both together. The yuzu soda adds a citrus brightness that keeps the whole thing from becoming heavy despite the multiple flavor elements at play. | F5: Fever-Tree Lime and Yuzu is the house soda at The Irish Exit — it is worth tracking down. In a pinch, any yuzu-forward soda or a combination of yuzu juice and plain soda water will work. Double strain to remove mint fragments and cucumber seeds. The small amounts of vodka and lime are balancers rather than primary flavors — do not skip them. Honey syrup is 1:1 honey to warm water, stirred until dissolved. | G5: Substitute gin for Irish whiskey for a more botanical result. Add a barspoon of St-Germain in place of the elderflower liqueur for a slightly richer floral note. | L5: needs_review
A6: cold_fashioned | B6: A house cocktail from Still Austin Whiskey Co., the first whiskey distillery in Austin city limits since Prohibition. Still Austin is a grain-to-glass operation — milling, mashing, fermenting, distilling, barreling, and bottling entirely in-house — and The Musician bourbon, their flagship, is what the drink is built around. The Cold Fashioned is served at their distillery bar on the east side of Austin, alongside tours, live music, and a seafood food truck on the patio. The recipe was popularized online by Austin-based mixologist Reid Nelson (@reidbetweenthelimes), who recreated the Still Austin version at home with characteristic attention to technique and garnish detail. The brulee sugar crisp is the signature detail: sugar, aromatic bitters, and flaky sea salt caramelized on an orange slice with a kitchen torch. The xanthan gum note is worth heeding — a quarter teaspoon is the difference between a smooth frozen cocktail and a separated one. | F6: Xanthan gum is optional but recommended for texture — it prevents the blend from separating and gives the drink a smoother, more uniform consistency. A small amount goes a long way. Pre-made old fashioned mix and sour mix can substitute for the house-made versions but the scratch version is dramatically better. The brulee sugar crisp can be made ahead and stored briefly. | G6: Scale down to a single serving: 1.5oz bourbon, 0.75oz old fashioned mix, 2oz citrus blend, small pinch of xanthan gum, 4oz pebble ice. Substitute rye for a spicier result. | L6: needs_review
A7: classic_margarita | B7: The Margarita is technically a Daisy — a sour cocktail made with a base spirit, citrus, and an orange liqueur, served in a salt-rimmed glass. In fact, margarita is Spanish for daisy. It belongs to the same family as the Sidecar and Cosmopolitan, and is one of the most ordered cocktails in the world. Its precise origin is disputed, with several bartenders and socialites from the 1930s-50s claiming credit. | F7: Use the best blanco tequila you can — it makes an enormous difference. Agave syrup at 1:1 (agave:water) keeps the sweetness clean and true to the spirit. | G7: Tommy Margarita: agave nectar instead of triple sec, on the rocks. Mezcal Margarita: substitute mezcal for tequila for a smoky version. Spicy Margarita: add jalapeno-infused tequila or muddle fresh chile. | L7: needs_review
A8: french_007 | B8: The French 007 is a champagne cocktail in the Kir Royale tradition — a style dating to post-war Burgundy, where Canon Félix Kir popularized the combination of crème de cassis and white wine. By substituting fruit liqueurs for cassis and using champagne, the format becomes endlessly riffable. The name nods to its Franco-elegant character — shaken, not stirred optional. | F8: The Mathilde Poire and Pama create a beautiful rose-gold color in the glass. Use a genuinely dry champagne or crémant to keep it from tipping too sweet. | G8: Substitute rye for bourbon for a spicier, drier result. Add a barspoon of honey syrup for a Gold Rush variation. | L8: needs_review
A9: classic_martini | B9: The Martini is arguably the most iconic cocktail in existence, its origins disputed between New York and San Francisco in the 1880s. It belongs to no family — it IS a family, the template from which the Manhattan, the Negroni, and countless others descend. Churchill famously chilled his gin by glancing at the vermouth bottle. James Bond's insistence on shaking it is, to purists, a cardinal sin. | F9: The ratio is everything — 5:1 is bone dry, 3:1 is classic, 2:1 is a wet martini. Chill your glass in the freezer. Never shake unless specifically asked — it bruises the gin and clouds the drink. | G9: Gibson: substitute a cocktail onion garnish for the olive. Dirty Martini: add a barspoon of olive brine. Vesper: add 0.5 oz Lillet Blanc and substitute vodka for half the gin. | L9: needs_review
A10: classic_manhattan | B10: The Manhattan was born in New York City in the 1870s, with the Manhattan Club claiming credit. It is the oldest known stirred whiskey cocktail and the direct ancestor of the Rob Roy (Scotch), the Black Manhattan (Averna), and the Toronto (Fernet). Along with the Old Fashioned and Martini it forms the holy trinity of classic American cocktails. | F10: Rye gives a spicier, drier result; bourbon gives a softer, sweeter one. Use a quality sweet vermouth — Carpano Antica is the gold standard. The cherry matters — use a Luxardo, not a maraschino. | G10: Rob Roy: substitute Scotch for rye. Black Manhattan: substitute Averna amaro for sweet vermouth. Perfect Manhattan: split sweet and dry vermouth equally. | L10: needs_review
A11: classic_daiquiri | B11: The Daiquiri was born in the mining town of Daiquirí, Cuba around 1900, popularized by American engineer Jennings Cox. It belongs to the Sour family — spirit, citrus, sweetener — and is considered the purist's test of a bartender's skill. Hemingway famously drank them by the pitcher at El Floridita in Havana, though he requested his without sugar — the Papa Doble. | F11: The Daiquiri is a bartender's benchmark — deceptively simple, ruthlessly revealing of technique and ingredient quality. Use fresh lime juice only. The ratio of sweet to sour is the whole game — taste and adjust before shaking. | G11: Hemingway Daiquiri: add grapefruit juice and maraschino, no sugar. Banana Daiquiri: add banana liqueur. Strawberry Daiquiri: blend with fresh strawberries. | L11: needs_review
A12: classic_negroni | B12: The Negroni was born in Florence in 1919 when Count Camillo Negroni asked bartender Fosco Scarselli to strengthen his Americano by replacing the soda water with gin. It belongs to the equal-parts family and is the gateway drug to the world of bitter, amaro-driven cocktails. The Sbagliato (with prosecco), Boulevardier (with bourbon), and Mezcal Negroni are its most celebrated variations. | F12: Equal parts is the rule — resist the urge to increase the gin. The Negroni rewards patience; stir it longer than you think necessary. Substituting bourbon for gin gives you a Boulevardier. | G12: Boulevardier: substitute bourbon for gin. Mezcal Negroni: substitute mezcal for gin. Sbagliato: substitute Prosecco for gin. White Negroni: substitute Suze and Lillet Blanc. | L12: needs_review
A13: classic_whiskey_sour | B13: The Whiskey Sour dates to at least 1862, appearing in Jerry Thomas's seminal bartending guide. It represents the entire Sour family — spirit, citrus, sweetener — which is the most important template in cocktail making. The addition of egg white elevates it to a Fizz or Boston Sour. Nearly every fruit-forward modern cocktail traces its lineage to this template. | F13: The egg white is optional but transforms the texture — silky and luxurious. The dry shake first is essential to build the foam. For a Boston Sour, serve up in a coupe. | G13: New York Sour: float red wine on top. Boston Sour: add egg white. Add a dash of Angostura bitters for more structure. | L13: needs_review
A14: moscow_mule | B14: The Moscow Mule was invented in 1941 at the Cock 'n' Bull pub in Los Angeles as a marketing collaboration between Smirnoff vodka and a ginger beer company. Its signature copper mug was a stroke of branding genius. It represents the Highball family — spirit, mixer, ice — the simplest and most refreshing cocktail template, and the one responsible for popularizing vodka in America. | F14: The copper mug is traditional and does keep the drink colder longer. Use a spicy, full-flavored ginger beer — Fever-Tree or Bundaberg work well. Substituting dark rum gives you a Dark & Stormy. | G14: Dark and Stormy: substitute dark rum for vodka. Kentucky Mule: substitute bourbon. Mexican Mule: substitute tequila. | L14: needs_review
A15: classic_cosmopolitan | B15: The Cosmopolitan was popularized by bartender Toby Cecchini at The Odeon in New York in 1988, though earlier versions existed in Florida and Provincetown. It became a cultural phenomenon through Sex and the City in the late 1990s, making it one of the most recognizable cocktails in the world. Technically a Daisy — spirit, citrus, orange liqueur — it shares its DNA with the Margarita and Sidecar. | F15: Use just enough cranberry juice to give the drink its signature blush — more than half an ounce and it tips too sweet. Citrus vodka is traditional but a clean neutral vodka works equally well. | G15: Add a float of Cointreau for extra orange richness. Substitute blood orange juice for regular cranberry for a seasonal variation. | L15: needs_review
... A43: dangerous_passion | B43: Created at a beachside bar in Aruba, the Dangerous Passion — El Azarosa Passionato in its original Spanish-Italian — is a masterclass in the seductive tension between tropical sweetness and slow-building heat. The passion fruit opens bright and floral, the ginger adds warmth, and the Ancho Reyes delivers a long, smoky chile finish. The flamed garnish is theatre as much as technique — the scorched habanero releases capsaicin aromatics that prime the palate before the first sip. A cocktail that lives up to its name. | F43: The flamed garnish is essential to the experience — the scorched habanero and toasted cardamom transform the aromatic profile entirely. Fresh passion fruit juice is strongly preferred; bottled works but loses the floral brightness. Teremana Reposado brings a gentle oak and vanilla quality that bridges the fruit and heat beautifully. | G43: Substitute gin for vodka for a more botanical version. Add a barspoon of grenadine for a deeper, richer color. | L43: needs_review
A44: monte_cassino | F44: From Steve the Bartender's Top 10 list. | G44: Substitute Yellow Chartreuse for Green for a softer, less assertive variation. | L44: needs_review
A45: flor_de_jerez | F45: From Steve the Bartender's Top 10 list. | G45: Substitute fino sherry for manzanilla for a nuttier, more oxidized character. | L45: needs_review
A46: bicycle_thief | F46: From Steve the Bartender's Top 10 list. | G46: Add a barspoon of grenadine for a fruitier, deeper result. | L46: needs_review
A47: kentucky_buck | F47: By @BartenderAtLarge. From Steve the Bartender's Top 10 list. | G47: Moscow Mule: substitute vodka for bourbon. Mexican Mule: substitute tequila. | L47: needs_review
A48: bitter_giuseppe | F48: Original specs from Steve the Bartender's Top 10 list. | G48: Add a barspoon of Fernet-Branca for an intensely bitter, digestif-style variation. | L48: needs_review
A49: siesta | F49: From Steve the Bartender's Top 10 list. | G49: Substitute Aperol for Campari for a softer, less bitter result. | L49: needs_review
A50: monella_sour | F50: From Steve the Bartender's Top 10 list. | G50: Substitute mezcal for the base spirit for a smoky variation. | L50: needs_review
A51: shakedown_street | F51: From Steve the Bartender's Top 10 list. | G51: Substitute bourbon for rye for a sweeter, rounder result. | L51: needs_review
A52: black_prince | F52: From Steve the Bartender's Top 10 list. | G52: Add a barspoon of blackberry liqueur for a fruitier, deeper result. | L52: needs_review
A53: muddled_mission | F53: From Steve the Bartender's Top 10 list. | G53: Substitute gin for vodka for a more botanical variation. | L53: needs_review
A54: bad_birdy_sangria | B54: Created by mixologist Bad Birdy, this elevated Sangria riff layers citrus, warm spice, and tropical fruit over a medium-bodied red wine base, with brandy adding depth and a splash of Coke lifting the whole thing with a whisper of sweetness and fizz. It drinks like a party in a glass. | F54: Created by mixologist Bad Birdy. Garnish with a mint sprig and lime wheel. | G54: Adjust the fruit selection seasonally — stone fruit in summer, citrus in winter. | L54: needs_review
A55: rattlesnake | B55: Created by Natasha David in New York City. David herself admits she is not a huge fan of egg whites or absinthe — yet finds the Rattlesnake unexpectedly balanced. As she puts it: ingredients in the right proportions create harmony, even if they are not always up your alley. A frothy, absinthe-spiked Whiskey Sour that earns its name. | F55: Garnish: Angostura bitters swirl. | G55: Omit the absinthe rinse for a more straightforward whiskey sour. The Corpse Reviver No. 2 shares the absinthe rinse technique. | L55: needs_review
A56: fresh_fruit_citronade | B56: Started life as an Applebee's menu item — proof that chain restaurants occasionally stumble onto something worth stealing. Re-specced for Alchemy with fresh lemon, Solerno, and an extra crack of pepper. A dirty pour keeps the muddled fruit and broken ice in the glass, layering the flavor from first sip to last. Sorry, Applebee's. | F56: The dirty pour keeps the muddled fruit in the glass, creating layered flavor as you drink. The black pepper is the secret — do not skip it. Solerno bridges the citrus and strawberry beautifully; Cointreau works as a substitute. | G56: The original Applebee's spec that started this: 1.5 oz citron vodka, 2 fresh strawberries, 3 basil leaves, pinch of black pepper, good quality lemonade, seltzer. Build in glass — muddle strawberries, pepper, and basil gently, add vodka and ice and stir, top with lemonade and seltzer, then gently lift and stir to combine. The current Alchemy spec is a proper cocktail rebuild of that same spirit. | L56: needs_review
A57: berry_gin_fizz | B57: Discovered on a German cocktail website, this is a modern riff on the classic Gin Fizz — one of the most enduring cocktail families of the 1920s. The addition of fresh berries gives it a playful, summery character that feels entirely contemporary. The Fizz family template — spirit, citrus, sweetener, soda — is one of the most riff-able in the cocktail canon. | F57: The recipe calls for The Great Eight Gin, an Austrian craft dry gin from the Peter Affenzeller distillery in Upper Austria, named for its eight botanicals. Any quality dry gin works beautifully. Use raspberries for tartness, blueberries for a deeper, earthier note, or a mix of both. | L57: needs_review
A58: rosemary_gin_smash | B58: The Smash is one of cocktailing oldest templates — spirit, herb, sugar, and seasonal fruit, dating to at least 1862. The modern gin-and-herb interpretation was pioneered by German bartender Jorg Meyer, whose Gin Basil Smash (created in 2008 at Le Lion in Hamburg) inspired a generation of herb-forward riffs. This rosemary version follows that lineage: clean, aromatic, and deeply refreshing. Found on a German cocktail website featuring The Great Eight Gin, an Austrian craft dry gin from the Peter Affenzeller distillery. | F58: Built in the glass with no shaking — try it as written first for comparison, then try shaking for more dilution and a colder result. The Great Eight Gin is an Austrian craft dry gin from the Peter Affenzeller distillery in Upper Austria. Any quality dry gin with botanical character works well here. | G58: The direct ancestor of this drink is the Gin Basil Smash, created by German bartender Jorg Meyer at Le Lion in Hamburg in 2008 — same template, basil instead of rosemary. Worth making both back to back. | L58: needs_review
A59: morgenthaler_amaretto_sour | B59: In 2012, Jeffrey Morgenthaler published a post titled I Make the Best Amaretto Sour in the World. The craft cocktail world had spent a decade treating the Amaretto Sour as a punchline. Morgenthaler disagreed. His revamped version adds overproof bourbon for backbone and egg white for texture, transforming a drink everyone had written off into something genuinely elegant. It is now considered a modern classic and a defining moment of the cocktail revival — proof that rehabilitation is possible. Search Morgenthaler to find all three of his recipes in the collection. | F59: The overproof bourbon is non-negotiable — it provides the backbone that makes this drink work. Without it, the amaretto overwhelms. Overproof means 100 proof (50% ABV) or higher; the higher the better. Morgenthaler recommends Bookers (typically 120-130 proof, uncut and unfiltered straight from the barrel), and he also recommends Old Grand-Dad 114 as an excellent, more accessible option. Any cask-strength bourbon in the 110-130 proof range will work beautifully. Dry shake first to build the foam, then shake with ice. Fine strain to keep it clean. Luxardo amaretto is also recommended. | L59: needs_review
A60: tia_mia | B60: In the mid-2000s, Ivy Mix had a habit of floating a splash of mezcal on cocktails she liked — including the Mai Tai. Around 2010, working at Lani Kai in New York, she committed to a full ounce and the Tia Mia was born. A mezcal-and-Jamaican-rum riff on Trader Vic 1944 original, it quickly earned a following among New York bartenders and drinkers and is now considered a modern tropical classic. Mix went on to co-found Leyenda in Brooklyn, a pan-Latin cocktail bar ranked among the world best, and to write Spirits of Latin America — a book that treats Latin spirits as cultural history, travel, and place, not just bottles on a backbar. | Search Ivy Mix to find more of her recipes. | F60: The name is a play on Mai Tai — swap the letters. Tia Mia is also Spanish for my aunt, the name Mix gave to a regular she knew in Guatemala. Use a smoky, expressive mezcal — Del Maguey Vida is the classic choice. Jamaican rum brings funk and depth; any full-bodied aged Jamaican rum works. Crushed ice is part of the identity. | G60: The Mai Tai is the direct ancestor — substitute curacao for orgeat and lime for the base. | L60: needs_review
A61: negroni_sbagliato | B61: Sbagliato means mistaken in Italian. At Bar Basso in Milan sometime in the 1970s, bartender Mirko Stocchetto was making a Negroni during a busy service and accidentally reached for a bottle of Prosecco instead of gin. Rather than discard it, he served it. The guest loved it. It became a house specialty and eventually a global classic. In 2022 a viral TikTok interview with House of the Dragon actress Olivia Cooke — in which she ordered a Negroni Sbagliato with Prosecco in a particular tone of voice — made it briefly the most Googled cocktail in the world. The happy accident has never looked back. | F61: Do not shake. Do not over-stir. The Prosecco is delicate and the bubbles are part of the drink. Use a good Prosecco — it is a third of the cocktail. Cava works beautifully as a slightly drier alternative. | G61: The classic Negroni: substitute gin for Prosecco. Large-Batch version: equal bottles of each ingredient in a punch bowl. | L61: needs_review
A62: americano_cocktail | B62: The Americano traces directly to the Milano Torino — equal parts Campari and sweet vermouth — which had been popular in Italy since the 1860s. When American soldiers arrived in Italy during World War I, many found the Mi-To too bitter and too strong. Italian bartenders began adding soda water to lengthen and lighten it for their American guests. The name stuck. It is one of the oldest drinks in the Campari lineage and the direct precursor to the Negroni — Count Camillo Negroni simply asked his bartender to replace the soda with gin. | F62: The Americano is the ancestor of the Negroni — substitute gin for the soda water and you have one. Lower-ABV, endlessly refreshing, and the perfect introduction to the bitter aperitivo style. James Bond orders one in the first chapter of Casino Royale — his very first drink in the entire canon. | G62: Negroni: add gin. Sbagliato: substitute Prosecco for soda. | L62: needs_review
A63: french_blonde | B63: The French Blonde is gin, Lillet Blanc, fresh grapefruit, and St-Germain elderflower — a drink that sits somewhere between a Greyhound and a White Negroni, floral and citrus-bright and unmistakably French in character. It came to widespread attention when US Weekly reported it as Taylor Swift favorite cocktail during the Eras Tour era — and if the Eras Tour can boost the global economy, a Swift endorsement was always going to move bottles of Lillet. Bartenders everywhere had better know how to make it. The good news: it deserves the attention entirely on its own merits. | F63: Use fresh grapefruit juice — not bottled. Oro Blanco (white grapefruit) gives the palest, most elegant color. Pink grapefruit works just as well and adds a peachy hue. A London dry gin is traditional but a citrus-forward gin elevates the floral notes beautifully. | L63: needs_review
A64: caipirinha | B64: The national cocktail of Brazil and one of the great three-ingredient drinks in the world. Cachaca, lime, sugar — that is all. The name means little country girl in Portuguese, and the drink most likely originated in Sao Paulo, though its precise history is contested. One persistent theory holds that an early version was created as a folk remedy during the Spanish Flu pandemic of 1918 — cachaca, lime, honey, and garlic — and that the garlic was eventually dropped as the drink moved from medicine cabinet to bar. In 2003 the Brazilian government officially declared it the national cocktail. In 2024 it ranked third in the world on TasteAtlas. Cachaca is not rum — both come from sugarcane, but cachaca is distilled from fresh-pressed cane juice while rum is made from molasses. That difference is everything. | F64: The white pith is the enemy — remove it before muddling or it will add bitterness. Press on the flesh, not the skin. Brazilian tradition says stirred, never shaken. Use 2 teaspoons of sugar as a starting point and adjust to your lime and preference. Leblon and Novo Fogo are excellent cachacas for the Caipirinha. | G64: Strawberry Caipirinha: muddle 3-4 hulled strawberries with the lime and sugar before adding cachaca. Passionfruit Caipirinha: add 1 oz fresh passionfruit pulp. Caipiroska: substitute vodka for cachaca. Caipirissima: substitute white rum for cachaca. | L64: needs_review
A65: strawberry_caipirinha | B65: The Strawberry Caipirinha is the most popular variation of Brazil national cocktail — and the one most likely to convert someone who thinks they do not like cachaca. The fruit softens the spirit forward edge of the classic while the lime keeps the brightness. It follows the same logic as the classic: muddle, spirit, ice. The template is unchanged. Only the fruit has moved. | F65: Use ripe, in-season strawberries — underripe strawberries are mostly water and will produce a flat, pink drink rather than a vibrant one. Taste before adding more sugar as ripe strawberries bring their own sweetness. Crushed ice gives a better result than cubed here. | G65: Add a few fresh basil leaves to the muddle for an herbal variation. A splash of fresh orange juice adds brightness. For a sparkling version, top with a splash of soda water. | L65: needs_review
A66: white_lady | B66: Harry Craddock created the White Lady at the American Bar at the Savoy in London in 1930, publishing it in The Savoy Cocktail Book the same year — one of the most important bartending reference books ever written. It is a Daisy in its purest form: gin, orange liqueur, citrus, served up. The egg white was Craddock addition, lifting a clean three-ingredient Sour into something more refined. The Savoy Cocktail Book codified an entire era of classic cocktail making during Prohibition, when American bartenders fled to London and brought their craft with them. The White Lady is one of its finest results. | F66: The egg white is optional but highly recommended — it gives the drink a silky texture and a beautiful white foam that explains the name. Dry shake first, then shake with ice. Cointreau specifically, not generic triple sec — the quality of the orange liqueur matters here. A good London dry gin is the right choice. | G66: Omit the egg white for a sharper, more citrus-forward version. Add a dash of orange bitters for depth. Some bartenders add a barspoon of simple syrup for a rounder finish. | L66: needs_review
A67: singapore_sling | B67: Created sometime between 1899 and 1915 by Ngiam Tong Boon, a Hainanese-Chinese bartender at the Long Bar in Raffles Hotel, Singapore. The original recipe was never formally recorded — the closest thing to a primary source is a recipe hastily scrawled on a bar chit in 1936 by a visitor who thought to ask a waiter how it was made. The drink was conceived as a workaround. In colonial Singapore, women were not permitted to consume alcohol in public — but fruit juice was perfectly acceptable. The Singapore Sling's pink color and tropical sweetness gave women plausible deniability, a cocktail disguised as something respectable. Ngiam Tong Boon built the subversion right into the recipe. The Long Bar where it was born did not survive the war intact. Japanese forces occupied Raffles in 1942, using it as a prisoner of war transit camp, and whatever records existed were lost. The version served today is reconstructed from the memories of former bartenders and that lone 1936 chit. The hotel was later restored to its colonial-era splendor, and the Long Bar now serves thousands of Singapore Slings a day — guests still encouraged, as they always were, to throw their peanut shells on the floor. | F67: Cherry Heering specifically — not generic cherry brandy. The Benedictine is the secret weapon and should not be omitted; it adds a herbal depth that is hard to identify but impossible to miss when absent. Fresh pineapple juice makes a significant difference over canned. The grenadine provides color as much as sweetness — housemade grenadine gives a far better result than commercial. | G67: Reduce grenadine and pineapple for a drier, more spirit-forward version. Add a float of dark rum for a richer tropical character. | L67: needs_review
A68: morgenthaler_sbagliato | B68: Jeffrey Morgenthaler is known for barrel-aging cocktails and pioneering the bottled cocktail movement in the United States. But when he throws a party, he makes this. Three bottles, a punch bowl, and ice — the entire prep takes five minutes. The genius is in the equal-parts simplicity: one bottle of each, combined without measuring. Morgenthaler approach to the Sbagliato strips away any pretension and reveals what it always was — an aperitivo for a crowd, lightly bitter, endlessly refreshing, and almost impossible to mess up. Search Morgenthaler to find all three of his recipes in the collection. | F68: Everything must be well chilled before combining — this preserves the Prosecco bubbles. Do not shake. Stir once, gently. Cinzano specifically is Morgenthaler preference for this recipe. Scale down by using equal parts of each spirit: 1 oz Campari, 1 oz sweet vermouth, 1 oz Prosecco per serving. | G68: Scale to a single serving: 1 oz each Campari, sweet vermouth, Prosecco, built over ice. | L68: needs_review
A69: gin_basil_smash | B69: Created by German bartender Jorg Meyer at Le Lion — Bar de Paris in Hamburg in 2008. Meyer spent an afternoon experimenting with a bunch of basil and a bottle of gin and produced one of the most important cocktails of the modern era. The Gin Basil Smash single-handedly rehabilitated the Smash template, launched a thousand herb-forward riffs, and proved that a great cocktail can come from anywhere — including a quiet afternoon in a Hamburg bar. It is now considered a modern classic and is one of the most influential drinks of the craft cocktail revival. Search Jorg Meyer to find more of his recipes. | F69: Gentle muddling is everything — overworked basil turns bitter and dark. Bruise, do not destroy. Double straining produces a cleaner, brighter green drink. A London Dry gin is the classic choice; a botanical gin with herbal notes also works beautifully. | G69: Genovese Smash: substitute fresh lime juice for lemon, use Genovese basil specifically, serve up in a coupe or martini glass with a slapped basil leaf float. The lime gives a sharper, more tropical acidity — balance with a slightly richer syrup. | L69: needs_review
A70: genovese_smash | B70: A lime-forward riff on Jorg Meyer 2008 Gin Basil Smash, substituting lime for lemon and Genovese basil for common sweet basil. The shift from lemon to lime gives the drink a sharper, more tropical edge — brighter on the nose, more assertive on the finish. Often called a Basil Gin Martini because it is served in a coupe or martini glass, but the Smash is what it is and what it has always been. The glass is presentation. The template is everything. | F70: Genovese basil specifically — it has a sweeter, more floral character than common sweet basil, with less of the anise note. The lime creates a sharper, brighter acidity than the classic lemon version, so a 2:1 rich simple syrup softens it without adding sweetness. Gentle muddling is non-negotiable. The slapped basil float garnish is essential — it perfumes every sip. This drink is often called a Basil Gin Martini because of the glass — a naming habit that dates to the 1990s cocktail boom, when anything served in a V-shaped glass got called a martini regardless of its ingredients. A true Martini is spirit plus vermouth, stirred, spirit-forward. This drink is spirit, citrus, and sweetener, shaken — a Smash. The glass is presentation. The family is everything. | G70: Use lemon instead of lime and you are making Jorg Meyer original Gin Basil Smash. Try Thai basil for an anise-forward variation. Muddle a single strawberry with the basil for a summer riff. | L70: needs_review
A71: chestnut_cup | B71: Created at the Chestnut Club in Santa Monica, California. The drink sits at a fascinating intersection — it has the citrus-sweetener backbone of a Sour, the bitter complexity of a Campari build, and the nutty richness of a Tiki-adjacent orgeat ingredient, all in one glass. It should not work as well as it does. The name has nothing to do with chestnuts — it comes from the bar that made it, whose name comes from the street it sits on. | F71: The single ice cube technique is deliberate — it chills and combines the drink without the full dilution of a full shake. The orgeat bridges the bitter Campari and bright lemon beautifully; do not skip it or substitute simple syrup. A botanical gin works particularly well here. House-made orgeat makes a noticeable difference. | G71: Substitute Aperol for Campari for a softer, less bitter version. Gran Classico Bitter gives a more herbal, complex result. Add a dash of Angostura bitters for extra depth. | L71: needs_review
A72: springs_first_bloom | B72: Created by Charlotte Voisey, one of the most decorated bartenders of the modern era — William Grant and Sons brand ambassador, Tales of the Cocktail Foundation board member, and a driving force in bringing craft bartending into the mainstream consciousness. Spring First Bloom is a showcase for what a thoughtfully constructed Egg White Sour can be: Hendricks cucumber botanicals, St-Germain elderflower, lemongrass, lavender bitters, and egg white foam, all working in concert. Published in Liquor.com. The name is apt — this is what spring tastes like. | F72: Hendricks is specified and should not be substituted — its cucumber and botanical notes are structural to the drink, not incidental. The lemongrass syrup takes time but is worth making; it also works beautifully in a Daiquiri or Gimlet. Lavender bitters are essential — Fee Brothers and Scrappy both make excellent versions. The microgreen garnish is elegant and intentional. | G72: The lemongrass syrup works in almost any floral sour. Try it in a Gimlet or a Bees Knees riff. | L72: needs_review
A73: irish_maid | B73: The Maid family of cocktails begins with the Kentucky Maid, created by Sam Ross — the same bartender who created the Paper Plane. The Irish Maid is an adaptation credited to Jack McGarry at The Dead Rabbit in New York City, one of the most decorated cocktail bars in the world. The logic is simple: Irish whiskey, lighter and more floral than bourbon, is a natural partner for elderflower and cucumber. The result is a whiskey sour that does not taste like one — bright, garden-fresh, and deeply refreshing. It is a modern classic in the making. | F73: Use a smooth Irish whiskey — Redbreast 12 is exceptional here, Jameson is the reliable standard. Mash the cucumber, do not pulverize it — juice, not puree. The elderflower should be present but not dominant; St-Germain at 0.5 oz keeps it in its lane. Fine straining removes all cucumber pulp and gives a clean, bright drink. | G73: The Kentucky Maid substitutes bourbon and lime for the Irish whiskey and lemon — Sam Ross original. A Scotch Maid with a peated whisky adds a smoky counterpoint to the floral elderflower. | L73: needs_review
A74: guardian_angel | B74: Created by Erick Castro for an Amaro Montenegro showcase event — a brief meant to highlight the Italian amaro in a cocktail context. Castro reached for Jamaican overproof rum for funk and depth, orgeat and lime for the sour backbone, and rosewater for a subtle floral lift. The combination is a deliberate nod to the classic Infante cocktail, which shares the orgeat-lime-rosewater structure, but Amaro Montenegro as the base gives it a significantly more complex, herbal character. The Educated Barfly featured it on their YouTube channel in 2020, calling it a crazy delicious drink that looks wrong on paper and right in the glass. Castro is a San Diego bartender and hospitality industry advocate who opened Raised by Wolves and Polite Provisions, two of the most celebrated bars on the West Coast. | F74: Wray and Nephew is specified — the overproof funk is structural to the drink, not optional. Amaro Montenegro is the right amaro here; it is lighter and more floral than many amari, which allows the rosewater and cucumber to come through. Rosewater is measured in drops — 3 is the sweet spot, more and it dominates. Double straining produces a clean, elegant drink. | G74: Try Campari in place of Amaro Montenegro for a more bitter, less floral result. | L74: needs_review
A75: infante | B75: Created in 2009 by Giuseppe Gonzalez at Dutch Kills bar in Long Island City, New York — the bar opened by Sam Ross and Richard Boccato, two of the most important figures of the craft cocktail revival. Gonzalez replaced the Margarita orange liqueur with orgeat, a substitution that sounds simple and lands like a revelation. The almond lends body to tequila mid-palate; the orange flower water adds a perfumed warmth on the finish. Named after Pedro Infante Cruz, the beloved Mexican actor and singer who appeared in over 60 films and recorded more than 350 songs before his death in 1957. The Infante is the structural ancestor of Erick Castro Guardian Angel — swap the tequila for Amaro Montenegro and overproof rum and you have one of the most interesting cocktails of the modern era. | F75: Reposado brings welcome oak and vanilla that deepens the orgeat. Blanco is brighter and more refreshing. Orange flower water is measured in drops — it perfumes the drink without dominating. Fresh nutmeg on the garnish is non-negotiable; it adds a warm, spicy finish that pulls everything together. Fortaleza and Siete Leguas are exceptional here. Liber and Co. orgeat is the obvious choice. | G75: Substitute rosewater for orange flower water for a more floral, delicate result — the version that inspired Erick Castro Guardian Angel. The Casper is a reposado variation with hazelnut orgeat and a rose water spritz. | L75: needs_review
... A104: thou_shall_not_be_named | B104: Created by Alicia Perry at Polite Provisions in San Diego — the James Beard-nominated bar owned by Erick Castro, who is already in this collection via the Guardian Angel. Perry describes the drink simply as stirred and direct, which is exactly right. Working from the Boulevardier framework, she swaps whiskey for a reposado-mezcal split and replaces Campari with Amaro Sfumato Rabarbaro, a smoky rhubarb amaro that changes the character of the drink entirely. It retains the Negroni family structure while going somewhere whiskey could never take it. First published in PUNCH in 2022. | F104: Amaro Sfumato Rabarbaro is the key ingredient — a smoky rhubarb-root amaro from Cappelletti that is dark, bitter, and deeply complex. It pulls out the bitter orange notes from the Torino vermouth while the mezcal adds a layer of smoke. El Tesoro reposado and Del Maguey Vida mezcal are the original choices but any quality equivalents work. Stir, do not shake — this is a stirred spirit-forward drink. | G104: Substitute Campari for the Sfumato for a more approachable but less distinctive version. A full ounce of mezcal makes it significantly smokier. | L104: needs_review
A105: triple_crown | B105: The Triple Crown comes from Jay Zimmerman of ba'sik in Williamsburg, Brooklyn, and was featured in Brooklyn Bartender by Carey Jones. The name earns its place three times over: three equal parts anchor the recipe; bourbon is the sport of Kentucky and horse racing royalty; and the combination of pamplemousse, lemon, and Montenegro Amaro represents a hat trick of complexity that takes a classic whiskey sour template and transforms it into something more layered and surprising. It is, as Jones writes, a complex whiskey sour packed full of flavor. | F105: A complex whiskey sour that rewards good ingredients. Eagle Rare single-barrel bourbon brings depth and vanilla backbone. Combier's Pamplemousse Rose is the preferred pamplemousse — the citrusy grapefruit richness ties the Montenegro's herbal bitterness to the lemon beautifully. The equal three-quarter measure of pamplemousse, lemon, and amaro is the architecture of the drink — don't adjust without considering what you're changing. | L105: needs_review
A106: new_brunswick | B106: A variation on the classic Brunswick cocktail, created by Ehren Ashkenazi of The Modern in New York City — the restaurant inside MoMA. The Brunswick template trades the Sour's usual sweetener for a fortified wine component, which adds complexity without adding sugar. Ashkenazi's use of Lillet Rouge rather than sweet vermouth gives it a lighter, more wine-forward character that suits the pink grapefruit beautifully. Published in Serious Eats. | F106: Ashkenazi uses Rittenhouse Rye specifically — its 100-proof backbone holds up against the assertive grapefruit without getting lost. Lillet Rouge is the house spec; substitute Carpano Antica sweet vermouth for a richer, more herbal result. Structurally this is a Sour built long — grapefruit as primary citrus, lemon as accent, served in a highball. It sits at the intersection of the Sour and Collins families, which is part of what makes it interesting. | G106: Substitute Campari for Lillet Rouge for a more bitter, Negroni-adjacent result. Try Aperol for a softer, lower-ABV finish. | L106: needs_review
A107: pineapple_makrut_buck | B107: Created by Camila Chaparro and published in Cocktails Illustrated by America's Test Kitchen (October 2025). Five five-star reviews. This is what a genuinely good zero-proof cocktail looks like — not a juice with bubbles, but a fully considered drink where every element has a structural role. The ginger-makrut syrup, cream of coconut, and fresh lime work together the way spirit, sweetener, and acid do in a classic Buck. The result is frothy, tropical, and complex in a way that earns its place in any collection. | F107: The ✨ next to the syrup means the recipe lives in the Craft section. The 5-second shake is deliberate — long enough to chill and combine without destroying the cream of coconut's body. Cream of coconut is not coconut cream or coconut milk: Coco Lopez or Goya are the reliable supermarket brands. If you cannot find makrut lime leaves, substitute 3 strips of lime zest and 3 strips of lemon zest. Structurally this is a zero-proof Buck — the same family as the Moscow Mule — built on pineapple and coconut rather than spirit. It drinks like a cocktail because the syrup, acid, and carbonation are doing the same structural work that spirit would do. | G107: Add 1–1.5 oz of white rum or coconut rum to make it a proper Buck. A float of ginger beer over the seltzer adds more heat. | L107: needs_review
A108: grapefruit_rosemary_spritzer | B108: Created by Lawman Johnson and published in Cook's Illustrated (January/February 2021), then included in How to Cocktail and Cocktails Illustrated by America's Test Kitchen. 4.5 stars across 38 ratings. Johnson describes it as simple but sophisticated and not-too-sweet — which is exactly right. The rosemary syrup is the move: it adds a savory, herbal dimension that grapefruit juice alone cannot produce, and it is what separates this from every other grapefruit soda on the table. | F108: The ✨ next to the syrup means the recipe lives in the Craft section. Fresh grapefruit is preferred — yellow, pink, or red all work, each with a slightly different profile. The rosemary syrup is doing specific structural work here: it tempers the tartness and adds a savory piney backbone that makes the drink feel like more than juice with bubbles. ATK's headnote gives you the spirit path: add 1 oz of blanco tequila, vodka, or London dry gin to turn it into a proper spritz. | G108: Add 1 oz blanco tequila for a Paloma-adjacent spritz. Add 1 oz London dry gin for something closer to a Gin & Tonic riff. Substitute thyme syrup and orange juice for a warmer, more autumnal variation. | L108: needs_review
A109: sicilian_sojourn | B109: Created by Camila Chaparro and published in How to Cocktail and Cocktails Illustrated by America's Test Kitchen (November 2020). 4.5 stars across 14 ratings. Blood oranges originated in the southern Mediterranean and feature prominently in Sicilian cuisine — the name earns itself. The tarragon is the move: its anise-licorice quality forms a classic Mediterranean pairing with citrus that turns a beautiful juice into something genuinely complex. This is zero-proof cocktail making at its most considered. | F109: Double-straining is essential here — it removes all tarragon leaf fragments and produces the clean, jewel-bright magenta color that makes this drink as beautiful as it tastes. The 5-second shake is deliberate; longer dilutes the vivid color and softens the tarragon. Blood oranges are a winter fruit — peak season is December through March. Out of season, navel oranges work but the color and raspberry-bitter complexity of the blood orange won't be there. Fresh basil is a documented substitute for tarragon if you prefer a sweeter, more floral herbal note. | G109: Add 1 oz of Aperol for a low-ABV spritz with complementary bitter orange notes. Add 1 oz of gin for a more botanical, spirit-forward build. Substitute fresh basil for tarragon for a sweeter, less anise-forward variation. | L109: needs_review
A110: pomegranate_spritzer | B110: Published by America's Test Kitchen in Cocktails Illustrated (October 2025). This is a compact zero-proof spritz built around pomegranate's tart, tannic backbone rather than imitation spirits. | D110: Zero-proof drink structured like a cocktail rather than a soft drink. | E110: Zero-proof but still cocktail-shaped: acid, sweetness, aroma, texture, and bubbles all have a job. | F110: Use unsweetened 100% pomegranate juice. The bitters add structure and make the drink read as a cocktail rather than juice with bubbles. Nonalcoholic old-fashioned bitters preserve zero-proof status; traditional Angostura works if trace alcohol is acceptable. | G110: Traditional Angostura bitters may be substituted if strict zero-proof status is not required. A rosemary or orange peel garnish would push it more aperitivo. | J110: https://www.americastestkitchen.com/recipes/17277-pomegranate-spritzer | K110: America's Test Kitchen — Cocktails Illustrated, Oct 2025. Makes 1. | L110: needs_review
A111: hibiscus_guava_agua_fresca | B111: Created by Sara Mayer for America's Test Kitchen / Cocktails Illustrated (November 2020). A highly rated zero-proof batch drink that turns agua fresca into something layered enough for cocktail service. | D111: Zero-proof drink structured like a cocktail rather than a soft drink. | E111: Zero-proof but still cocktail-shaped: acid, sweetness, aroma, texture, and bubbles all have a job. | F111: Batch drink. The long room-temperature steep extracts hibiscus color and tartness without boiling bitterness. Guava gives body and tropical perfume; pineapple or mango juice can substitute. | G111: Substitute pineapple or mango juice for guava nectar. For a sharper version, increase lemon slightly just before serving. | K111: Sara Mayer, America's Test Kitchen — Cocktails Illustrated, Nov 2020. Makes 8. Source rating noted by user/Claude: 5 stars / 63 ratings. | L111: needs_review
A112: raspberry_lime_rickey | B112: Published by America's Test Kitchen in Sous Vide for Everybody (June 2018). This is a zero-proof Rickey that keeps the template's crisp lime-and-bubbles structure while using raspberry syrup for color, aroma, and seasonal fruit depth. | D112: Zero-proof drink structured like a cocktail rather than a soft drink. | E112: Zero-proof but still cocktail-shaped: acid, sweetness, aroma, texture, and bubbles all have a job. | F112: The syrup is the real craft item here. ATK's sous vide method holds fruit at 140°F / 60°C for 2–3 hours, producing a vivid raspberry syrup; frozen raspberries yield especially vibrant color. | G112: Use club soda for a sharper mineral profile or seltzer for a cleaner fruit-forward version. The raspberry-lime mixture can be batched ahead and topped with bubbles to order. | K112: America's Test Kitchen — Sous Vide for Everybody, June 2018. Makes 4. | L112: needs_review
A113: cantaloupe_fresno_chile_spritzer | B113: Created by Hannah Fenton for America's Test Kitchen (November 2022). The recipe is almost audaciously simple — three ingredients — but the Fresno chile gives ripe cantaloupe enough tension to read like a composed zero-proof cocktail. | D113: Zero-proof drink structured like a cocktail rather than a soft drink. | E113: Zero-proof but still cocktail-shaped: acid, sweetness, aroma, texture, and bubbles all have a job. | F113: The puree can be refrigerated up to 2 days. This is intentionally austere: ripe melon, fresh chile heat, and bubbles. Use good cantaloupe or the drink has nowhere to hide. | G113: Try basil or mint as an aromatic garnish. For more heat, let the chile sit briefly in the strained puree before adding seltzer, then strain again. | K113: Hannah Fenton, America's Test Kitchen, Nov 2022. Serves 4. | L113: needs_review
A114: mosquito | B114: Sam Ross created the Paper Plane in 2007 for the opening menu of Chicago's Violet Hour, drawing on the Last Word — the pre-Prohibition equal-parts classic of gin, green Chartreuse, maraschino, and lime — as his structural template. Equal parts, shaken, citrus-forward, bitter element. The Paper Plane went on to become one of the most widely traveled modern classics in the craft cocktail canon. Ten years later, Ross revisited his own creation. At Attaboy — the celebrated bar he launched on Manhattan's Lower East Side in 2012 with partner Michael McIlroy — he assembled a new equal-parts drink called the Mosquito: mezcal, lemon, sweetened ginger juice, Campari. The architecture is the same as the Paper Plane. The personality is entirely different — smokier, spicier, more bitter, with ginger replacing Amaro Nonino's herbal sweetness and Campari sharpening the finish where Aperol had softened it. The Mosquito became the progenitor of what Attaboy staff have dubbed the Bug Cocktail family: a growing library of equal-parts originals, now numbering more than eight, each keeping the lemon and ginger components intact while swapping the spirit and bitter element. It is, in miniature, the same creative logic that produced the Mosquito from the Paper Plane — a template passed forward, remixed, extended. Attaboy operates without written menus, relying on bartender's choice, which means these drinks exist in the bar's institutional memory as much as on any page. Publishing them is an act of preservation as much as documentation. | C114: Sam Ross, Attaboy, New York City, 2017 | D114: The Mosquito is the seed of a creative system — a template remixed from a template, now producing its own family of drinks at one of the most influential bars in contemporary craft cocktail culture. The equal-parts format, descended from the Last Word through the Paper Plane, is one of the most generative structures in modern mixology. | E114: Sam Ross has described the equal-parts format as a balancing discipline: every component must earn its quarter of the glass. There is nowhere to hide. A weak spirit, a stale citrus, an under-sweetened ginger juice — the format exposes all of it. This is the equal-parts lesson: simplicity is the hardest standard to meet. | F114: Creator's spec per Punch, January 2025. The ginger juice is the heart of this drink and every drink in the Bug family — it must be made fresh. The sweetening ratio (4:3 juice to sugar by weight) is precise and intentional; adjust and the balance collapses. Campari's bitterness is what reins in the ginger's natural sweetness — they are calibrated against each other. Mezcal with genuine smoke presence is necessary; a neutral-tasting mezcal loses the tension that makes the drink interesting. | G114: The Paper Plane (Sam Ross, 2007) is the direct ancestor: bourbon, Aperol, Amaro Nonino, lemon, equal parts. The Last Word (pre-Prohibition) is the architectural grandfather: gin, green Chartreuse, maraschino, lime, equal parts. The three Bug Cocktails below are all Mosquito variations following the same equal-parts ginger-lemon template with different spirit and bitter pairings. | I114: sam_ross_attaboy | J114: https://punchdrink.com/recipes/mosquito/ https://punchdrink.com/articles/attaboy-equal-parts-cocktail-recipes/ | K114: Documented Attaboy specs via Punch (January 2025). Liquid Alchemy editorial framing; creator attribution preserved. | L114: needs_review
A115: praying_mantis | B115: Brandon Bramhall created the Praying Mantis at Attaboy's Nashville outpost, working within the equal-parts ginger-lemon template that Sam Ross established with the Mosquito. The formula is consistent across the Bug family: a base spirit, lemon juice, sweetened ginger juice, and a bitter liqueur or amaro, all in equal proportion, all shaken and served up in a coupe. What changes is the pairing — and the pairing is everything. Bramhall's choice of Islay Scotch and Gran Classico is the most austere and complex variation in the Bug family. Islay Scotch brings peat smoke, maritime salt, and iodine — a flavor profile that has no equivalent in any other spirit and that pairs with bitterness in ways that require careful calibration. Gran Classico, the Swiss bitter liqueur made from a nineteenth-century recipe with twenty-five herbs and roots, sits between Campari and Aperol in sweetness but carries a complexity that neither achieves. The combination produces a drink that is simultaneously more smoky, more bitter, and more herbal than the Mosquito — and considerably more demanding of the drinker. The name is well-chosen. The praying mantis is a patient, precise, and formidable creature. So is this drink. | C115: Brandon Bramhall, Attaboy, Nashville | D115: The most complex and demanding drink in the Bug family — a demonstration that the equal-parts template can carry serious weight when the ingredients are chosen with precision. Islay Scotch in a shaken equal-parts sour is an unusual move that works. | E115: Gran Classico and Campari occupy similar roles — bitter liqueur, similar color, similar ABV — but produce meaningfully different drinks. Understanding the functional differences between bitter liqueurs (sweetness level, herbal character, proof, finish) is essential to working intelligently with the Daisy template. Swapping one bitter for another is not a neutral substitution. | F115: Creator's spec per Punch, January 2025. Islay Scotch is not interchangeable with blended or Highland Scotch here — the peat is structural, not decorative. Laphroaig 10, Ardbeg 10, or Caol Ila 12 are all appropriate choices at different smoke intensities. Gran Classico is available in well-stocked craft spirits retailers; Contratto Bitter or Tempus Fugit Gran Classico are the same product. Do not substitute Campari — the bitterness profile is different enough to produce a meaningfully different drink. | G115: Substitute blended Scotch for Islay to soften the smoke and produce a more approachable version at some cost to complexity. Campari in place of Gran Classico sharpens the bitterness and reduces the herbal depth — closer to a Scotch Mosquito than a distinct drink. For a lower-proof version, substitute a peated Scotch-style whisky liqueur (Drambuie adds honey sweetness that changes the balance significantly — account for it by reducing the ginger juice). | I115: brandon_bramhall_attaboy | J115: https://punchdrink.com/articles/attaboy-equal-parts-cocktail-recipes/ | K115: Documented Attaboy specs via Punch (January 2025). Liquid Alchemy editorial framing; creator attribution preserved. | L115: needs_review
A116: maverick | B116: Mike McCollum of Attaboy Nashville brought two things to the Bug family that none of the other drinks in the series have: gin as the base spirit, and fresh mint shaken directly into the cocktail. The gin choice is interesting. The Last Word — the great-grandparent of this entire family — is a gin drink. The Paper Plane moved to bourbon. The Mosquito moved to mezcal. The Maverick returns to gin, completing a kind of circle, and pairs it with Aperol rather than Campari or Gran Classico. The result is the lightest, most herbaceous, and most approachable drink in the Bug family — Aperol's lower bitterness and higher sweetness softening the ginger's heat, gin's botanicals amplified by the mint, lemon keeping everything bright and clean. The mint technique is the detail worth noting. Rather than muddled in the shaker or used as a garnish, the leaves are shaken whole with the other ingredients and caught by the strainer. This produces a gentler mint character than muddling — more aromatic than aggressive, woven into the drink rather than dominating it. | C116: Mike McCollum, Attaboy, Nashville | D116: The Maverick closes the circle — a gin drink descended from a gin drink, routed through bourbon and mezcal along the way. The most approachable entry point into the Bug family, and a demonstration that the equal-parts template is as comfortable with lightness as with complexity. | E116: Shaking mint rather than muddling it is a technique choice with real consequences. Muddling ruptures the cell walls and releases chlorophyll along with the aromatics — producing a greener, more aggressive, sometimes bitter mint character. Shaking whole leaves extracts aromatics more gently. Neither is wrong; they produce different results. This drink needs the gentle version. | F116: Creator's spec per Punch, January 2025. A botanical gin with genuine herbal presence works better here than a neutral or citrus-forward gin — the mint needs something to harmonize with. Beefeater, Tanqueray, or Sipsmith are appropriate. The double-strain or tightly gated Hawthorne is important — mint leaf fragments in a coupe are not pleasant. Aperol's lower proof (11% ABV) means this is the lowest-alcohol drink in the Bug family; factor that in if you are building a round. | G116: Substitute Campari for Aperol for a significantly more bitter, less sweet version — closer to a gin Mosquito. Add a half ounce of green Chartreuse and reduce Aperol to 0.5 oz to push the drink back toward its Last Word ancestor. Basil shaken in place of mint produces a more savory, anise-adjacent variation worth trying. | I116: mike_mccollum_attaboy | J116: https://punchdrink.com/articles/attaboy-equal-parts-cocktail-recipes/ | K116: Documented Attaboy specs via Punch (January 2025). Liquid Alchemy editorial framing; creator attribution preserved. | L116: needs_review
A117: lantern_fly | B117: Jojo Colona created the Lantern Fly at Attaboy's New York location, working with two ingredients that are unusual choices within the Bug family and that produce, together, the most distinctly funky drink in the series. Jamaican pot still rum is not a background ingredient. Made in traditional pot stills rather than the continuous column stills that produce lighter Caribbean rums, pot still Jamaican rum carries an intense, funky, almost overripe fruit quality — esters and congeners that make themselves known in any drink they inhabit. Doctor Bird, the rum Punch specifies for this recipe, is a Worthy Park expression named for the Jamaican national bird, made entirely from pot still distillate. It is not a subtle rum. Amargo-Vallet is equally specific. The Mexican digestif amaro, made since 1881 in Mexico City and named for its French founder Adolphe Vallet, is built on a base of angostura bark — making it a relative of Angostura bitters in botanical character, with the flavor profile of a bitter liqueur rather than a concentrate. It is drier, more herbal, and less sweet than Campari, and its angostura-forward bitterness creates a different kind of tension with the ginger than Campari's more fruit-and-citrus bitterness. The combination — funky pot still rum, angostura-forward amaro, ginger heat, lemon acid — is aggressive and layered in a way that rewards attention. | C117: Jojo Colona, Attaboy, New York City | D117: The most ingredient-specific drink in the Bug family, and the one most likely to reward the curious drinker who seeks it out. Amargo-Vallet is genuinely obscure outside of cocktail enthusiast circles; Jamaican pot still rum is underappreciated even among rum drinkers. The Lantern Fly puts both in a context where they cannot hide. | E117: Amargo-Vallet is a case study in how a drink's bitter component determines its character as much as the base spirit does. Swap Amargo-Vallet for Campari in this recipe and you have a different drink — same structure, same proportions, genuinely different experience. The bitter element in an equal-parts Daisy is not interchangeable. Choose it as carefully as you choose the spirit. | F117: Creator's spec per Punch, January 2025. Jamaican pot still rum is not interchangeable with standard Jamaican rum or blended Caribbean rum — the funk is structural. Worthy Park, Hampden, or Doctor Bird are the appropriate choices. Amargo-Vallet has limited distribution; check specialty spirits retailers. In a pinch, Angostura bitters at 0.5 oz plus 0.25 oz Campari approximates the botanical character at some cost to the amaro's depth and sweetness contribution — adjust the ginger juice accordingly. | G117: Substitute Campari for Amargo-Vallet for a sweeter, more familiar bitter profile that tames the funk of the pot still rum rather than amplifying it. Smith & Cross, the Navy-strength Jamaican pot still rum, in place of Doctor Bird increases the proof significantly and pushes the funk further — the drink becomes considerably more demanding. Combine equal parts pot still rum and aged agricole rhum for a split-base variation with additional grassy, vegetal complexity. | I117: jojo_colona_attaboy | J117: https://punchdrink.com/recipes/lantern-fly/ https://punchdrink.com/articles/attaboy-equal-parts-cocktail-recipes/ | K117: Documented Attaboy specs via Punch (January 2025). Liquid Alchemy editorial framing; creator attribution preserved. | L117: needs_review

Sheet Images
A1: recipe_id | B1: image_type | C1: asset_path | D1: status | E1: source_reference | F1: prompt | G1: alt_text | H1: version | I1: notes
A2: dame_blanche_au_poire | B2: thumbnail | C2: assets/cocktails/dame_blanche_au_poire/thumbnail.png | D2: embedded_base64_in_source_needs_asset_export | E2: 20260603_2145.json:_thumb | H2: 1
A3: old_fashioned_classic | B3: hero | C3: assets/cocktails/old_fashioned_classic/hero.png | D3: embedded_base64_in_source_needs_asset_export | E3: 20260603_2145.json:imageUrl | H3: 1
A4: old_fashioned_classic | B4: thumbnail | C4: assets/cocktails/old_fashioned_classic/thumbnail.png | D4: embedded_base64_in_source_needs_asset_export | E4: 20260603_2145.json:_thumb | H4: 1
A5: classic_margarita | B5: hero | C5: assets/cocktails/classic_margarita/hero.png | D5: embedded_base64_in_source_needs_asset_export | E5: 20260603_2145.json:imageUrl | H5: 1
A6: classic_margarita | B6: thumbnail | C6: assets/cocktails/classic_margarita/thumbnail.png | D6: embedded_base64_in_source_needs_asset_export | E6: 20260603_2145.json:_thumb | H6: 1
A7: french_007 | B7: hero | C7: assets/cocktails/french_007/hero.png | D7: embedded_base64_in_source_needs_asset_export | E7: 20260603_2145.json:imageUrl | H7: 1
A8: french_007 | B8: thumbnail | C8: assets/cocktails/french_007/thumbnail.png | D8: embedded_base64_in_source_needs_asset_export | E8: 20260603_2145.json:_thumb | H8: 1
A9: classic_whiskey_sour | B9: hero | C9: assets/cocktails/classic_whiskey_sour/hero.png | D9: embedded_base64_in_source_needs_asset_export | E9: 20260603_2145.json:imageUrl | H9: 1
A10: classic_whiskey_sour | B10: thumbnail | C10: assets/cocktails/classic_whiskey_sour/thumbnail.png | D10: embedded_base64_in_source_needs_asset_export | E10: 20260603_2145.json:_thumb | H10: 1
A11: classic_cosmopolitan | B11: hero | C11: assets/cocktails/classic_cosmopolitan/hero.png | D11: embedded_base64_in_source_needs_asset_export | E11: 20260603_2145.json:imageUrl | H11: 1
A12: classic_cosmopolitan | B12: thumbnail | C12: assets/cocktails/classic_cosmopolitan/thumbnail.png | D12: embedded_base64_in_source_needs_asset_export | E12: 20260603_2145.json:_thumb | H12: 1
A13: aperol_spritz | B13: hero | C13: assets/cocktails/aperol_spritz/hero.png | D13: embedded_base64_in_source_needs_asset_export | E13: 20260603_2145.json:imageUrl | H13: 1
... A23: shakedown_street | B23: thumbnail | C23: assets/cocktails/shakedown_street/thumbnail.png | D23: embedded_base64_in_source_needs_asset_export | E23: 20260603_2145.json:_thumb | H23: 1

Sheet Creators
A1: creator_id | B1: name | C1: bio | D1: source_urls | E1: status
A2: bridget7487049_via_recime | B2: @bridget7487049 via ReciMe | E2: imported_needs_review
A3: sam_ross_attaboy | B3: Sam Ross, Attaboy, New York City | C3: Sam Ross created the Mosquito at Attaboy (New York City) in 2017. | D3: https://punchdrink.com/articles/attaboy-equal-parts-cocktail-recipes/ | E3: draft_needs_review
A4: brandon_bramhall_attaboy | B4: Brandon Bramhall, Attaboy, Nashville | C4: Brandon Bramhall created the Praying Mantis at Attaboy Nashville. | D4: https://punchdrink.com/articles/attaboy-equal-parts-cocktail-recipes/ | E4: draft_needs_review
A5: mike_mccollum_attaboy | B5: Mike McCollum, Attaboy, Nashville | C5: Mike McCollum created the Maverick at Attaboy Nashville. | D5: https://punchdrink.com/articles/attaboy-equal-parts-cocktail-recipes/ | E5: draft_needs_review
A6: jojo_colona_attaboy | B6: Jojo Colona, Attaboy, New York City | C6: Jojo Colona created the Lantern Fly at Attaboy New York City. | D6: https://punchdrink.com/articles/attaboy-equal-parts-cocktail-recipes/ | E6: draft_needs_review

Sheet Families
A1: family_id | B1: name | C1: type | D1: parent_family_id | E1: status
A2: flip_nog_and_creamy | B2: Flip, Nog & Creamy | C2: family | E2: imported_needs_review
A3: cream_cocktail | B3: Cream Cocktail | C3: subfamily | D3: flip_nog_and_creamy | E3: imported_needs_review
A4: flip | B4: Flip | C4: subfamily | D4: flip_nog_and_creamy | E4: imported_needs_review
A5: highball | B5: Highball | C5: family | E5: imported_needs_review
A6: core_highball | B6: Core Highball | C6: subfamily | D6: highball | E6: imported_needs_review
A7: ginger_highball_buck | B7: Ginger Highball / Buck | C7: subfamily | D7: highball | E7: imported_needs_review
A8: spritz | B8: Spritz | C8: subfamily | D8: highball | E8: imported_needs_review
A9: tonic_highball | B9: Tonic Highball | C9: subfamily | D9: highball | E9: imported_needs_review
A10: julep | B10: Julep | C10: family | E10: imported_needs_review
A11: core_julep | B11: Core Julep | C11: subfamily | D11: julep | E11: imported_needs_review
A12: martini_and_manhattan | B12: Martini & Manhattan | C12: family | E12: imported_needs_review
A13: manhattan_style | B13: Manhattan Style | C13: subfamily | D13: martini_and_manhattan | E13: imported_needs_review
A14: martini_style | B14: Martini Style | C14: subfamily | D14: martini_and_manhattan | E14: imported_needs_review
A15: negroni | B15: Negroni | C15: family | E15: imported_needs_review
A16: americano_style | B16: Americano Style | C16: subfamily | D16: negroni | E16: imported_needs_review
A17: classic_negroni | B17: Classic Negroni | C17: subfamily | D17: negroni | E17: imported_needs_review
A18: dry_negroni | B18: Dry Negroni | C18: subfamily | D18: negroni | E18: imported_needs_review
A19: sbagliato_style | B19: Sbagliato Style | C19: subfamily | D19: negroni | E19: imported_needs_review
A20: unknown | C20: subfamily | D20: negroni | E20: imported_needs_review
A21: old_fashioned | B21: Old Fashioned | C21: family | E21: imported_needs_review
A22: bittered_spirit | B22: Bittered Spirit | C22: subfamily | D22: old_fashioned | E22: imported_needs_review
A23: core_old_fashioned | B23: Core Old Fashioned | C23: subfamily | D23: old_fashioned | E23: imported_needs_review
A24: sour | B24: Sour | C24: family | E24: imported_needs_review
A25: collins | B25: Collins | C25: subfamily | D25: sour | E25: imported_needs_review
A26: core_sour | B26: Core Sour | C26: subfamily | D26: sour | E26: imported_needs_review
A27: daisy | B27: Daisy | C27: subfamily | D27: sour | E27: imported_needs_review
A28: egg_white_sour | B28: Egg White Sour | C28: subfamily | D28: sour | E28: imported_needs_review
A29: fizz | B29: Fizz | C29: subfamily | D29: sour | E29: imported_needs_review
A30: royale | B30: Royale | C30: subfamily | D30: sour | E30: imported_needs_review
A31: smash | B31: Smash | C31: subfamily | D31: sour | E31: imported_needs_review
A32: whiskey_sour | B32: Whiskey Sour | C32: subfamily | D32: sour | E32: imported_needs_review
A33: spritz_and_aperitivo | B33: Spritz & Aperitivo | C33: family | E33: imported_needs_review
A34: americano_style | B34: Americano Style | C34: subfamily | D34: spritz_and_aperitivo | E34: imported_needs_review
A35: classic_spritz | B35: Classic Spritz | C35: subfamily | D35: spritz_and_aperitivo | E35: imported_needs_review
A36: sbagliato_style | B36: Sbagliato Style | C36: subfamily | D36: spritz_and_aperitivo | E36: imported_needs_review
A37: wine_spritz | B37: Wine Spritz | C37: subfamily | D37: spritz_and_aperitivo | E37: imported_needs_review
A38: tiki_and_tropical | B38: Tiki & Tropical | C38: family | E38: imported_needs_review
A39: grog | B39: Grog | C39: subfamily | D39: tiki_and_tropical | E39: imported_needs_review
A40: mai_tai_style | B40: Mai Tai Style | C40: subfamily | D40: tiki_and_tropical | E40: imported_needs_review
A41: tropical_sour | B41: Tropical Sour | C41: subfamily | D41: tiki_and_tropical | E41: imported_needs_review
A42: daisy_equal_parts | B42: Daisy — Equal Parts | C42: subfamily | D42: sour | E42: draft_needs_review

Sheet Glassware
A1: glassware_id | B1: name | C1: description | D1: status
A2: champagne_flute | B2: Champagne Flute | D2: imported_needs_review
A3: collins | B3: Collins | D3: imported_needs_review
A4: collins_highball | B4: Collins/Highball | D4: imported_needs_review
A5: copper_mug | B5: Copper Mug | D5: imported_needs_review
A6: coupe | B6: Coupe | D6: imported_needs_review
A7: highball | B7: Highball | D7: imported_needs_review
A8: julep_cup | B8: Julep Cup | D8: imported_needs_review
A9: martini | B9: Martini | D9: imported_needs_review
A10: nick_and_nora | B10: Nick & Nora | D10: imported_needs_review
A11: other | B11: Other | D11: imported_needs_review
A12: rocks_old_fashioned | B12: Rocks/Old Fashioned | D12: imported_needs_review
A13: snifter | B13: Snifter | D13: imported_needs_review
... A15: wine_glass | B15: Wine Glass | D15: imported_needs_review

Sheet Techniques
A1: technique_id | B1: name | C1: description | D1: status

Sheet AI_Metadata
A1: recipe_id | B1: field_name | C1: source_type | D1: model_or_tool | E1: human_review_status | F1: fact_check_status | G1: confidence | H1: source_status | I1: source_file | J1: imported_at
A2: dame_blanche_au_poire | B2: all_imported_fields | C2: source_json_import | D2: unknown | E2: needs_human_review | F2: needs_fact_check | G2: unknown | H2: unknown | I2: 20260603_2145.json | J2: 2026-06-06
A3: old_fashioned_classic | B3: all_imported_fields | C3: source_json_import | D3: unknown | E3: needs_human_review | F3: needs_fact_check | G3: unknown | H3: unknown | I3: 20260603_2145.json | J3: 2026-06-06
A4: rosemary_fizz | B4: all_imported_fields | C4: source_json_import | D4: unknown | E4: needs_human_review | F4: needs_fact_check | G4: unknown | H4: unknown | I4: 20260603_2145.json | J4: 2026-06-06
A5: first_class_pass | B5: all_imported_fields | C5: source_json_import | D5: unknown | E5: needs_human_review | F5: needs_fact_check | G5: unknown | H5: unknown | I5: 20260603_2145.json | J5: 2026-06-06
A6: cold_fashioned | B6: all_imported_fields | C6: source_json_import | D6: unknown | E6: needs_human_review | F6: needs_fact_check | G6: unknown | H6: unknown | I6: 20260603_2145.json | J6: 2026-06-06
A7: classic_margarita | B7: all_imported_fields | C7: source_json_import | D7: unknown | E7: needs_human_review | F7: needs_fact_check | G7: unknown | H7: unknown | I7: 20260603_2145.json | J7: 2026-06-06
A8: french_007 | B8: all_imported_fields | C8: source_json_import | D8: unknown | E8: needs_human_review | F8: needs_fact_check | G8: unknown | H8: unknown | I8: 20260603_2145.json | J8: 2026-06-06
A9: classic_martini | B9: all_imported_fields | C9: source_json_import | D9: unknown | E9: needs_human_review | F9: needs_fact_check | G9: unknown | H9: unknown | I9: 20260603_2145.json | J9: 2026-06-06
A10: classic_manhattan | B10: all_imported_fields | C10: source_json_import | D10: unknown | E10: needs_human_review | F10: needs_fact_check | G10: unknown | H10: unknown | I10: 20260603_2145.json | J10: 2026-06-06
A11: classic_daiquiri | B11: all_imported_fields | C11: source_json_import | D11: unknown | E11: needs_human_review | F11: needs_fact_check | G11: unknown | H11: unknown | I11: 20260603_2145.json | J11: 2026-06-06
A12: classic_negroni | B12: all_imported_fields | C12: source_json_import | D12: unknown | E12: needs_human_review | F12: needs_fact_check | G12: unknown | H12: unknown | I12: 20260603_2145.json | J12: 2026-06-06
... A113: cantaloupe_fresno_chile_spritzer | B113: full_record | C113: user_provided_extraction | D113: Claude + ART cleanup | E113: needs_human_review | F113: needs_source_check | G113: medium | H113: source_text_provided_by_user | I113: chat_20260606 | J113: 2026-06-06

Sheet JSON_Mapping
A1: source/workbook path | B1: export target | C1: workbook field/sheet | D1: notes
A2: Recipes / normalized tabs | B2: App_JSON_Export | C2: id | D2: Current app import id should be stable kebab-case.
A3: Recipes.name | B3: cocktails[].name | C3: App_JSON_Export.name | D3: Display name.
A4: Recipes.family/subfamily | B4: cocktails[].family/subFamily | C4: App_JSON_Export.family/subFamily | D4: Use current app labels.
A5: Recipes.base_spirit/glass/occasion/season/difficulty/serve_style | B5: matching current app fields | C5: App_JSON_Export | D5: Use allowed enum values.
A6: Recipes.tags | B6: cocktails[].tags | C6: App_JSON_Export.tags | D6: Stored as JSON text array in workbook export layer.
A7: Recipes slider columns | B7: cocktails[].sliders | C7: slider_boozy through slider_rich | D7: Exporter nests into sliders object with 9 keys.
A8: Recipe_Ingredients | B8: cocktails[].ingredients | C8: App_JSON_Export.ingredients | D8: Stored as JSON text array of {name, amount, unit}.
A9: Steps | B9: cocktails[].instructions | C9: App_JSON_Export.instructions | D9: Current app uses one string; future pipeline can retain ordered steps.
A10: Lore.notes/story/riffs/tasting_notes | B10: cocktails[].notes/lore/riffs/tastingNotes | C10: App_JSON_Export | D10: Needs review before publish.
A11: Images | B11: cocktails[].imageUrl/myPhoto | C11: App_JSON_Export.imageUrl/myPhoto | D11: Blank for v1 bulk import; asset pipeline later.
A12: Craft_Items | B12: not currently exported | C12: Craft_Items | D12: Current app import/export does not include Craft.

Sheet Validation
A1: Validation Area | B1: Check | C1: Rule | D1: Severity | E1: Status
A2: IDs | B2: Recipe ids are immutable | C2: No id changes after publish; export kebab-case. | D2: Critical | E2: Open
A3: Enums | B3: Current app enum values | C3: Use Enum_Normalization before JSON export. | D3: High | E3: Open
A4: Tags | B4: Current app tag values | C4: Use Tag_Normalization before JSON export. | D4: High | E4: Open
A5: Zero-proof | B5: Optional alcoholic ingredients | C5: Do not export optional alcoholic ingredients into base zero-proof ingredients[]. | D5: Critical | E5: Open
A6: User state | B6: Personal fields | C6: Exclude favorite, wantToTry, tried, myPhoto, personal tastingNotes; rating=0. | D6: Critical | E6: Open
A7: Craft links | B7: craftLinks ids | C7: Validate ids exist in current app craft library before export. | D7: Medium | E7: Open
A8: Images | B8: Image data | C8: No embedded/base64 images in workbook or canon JSON; asset paths only. | D8: Medium | E8: Open
A9: Export | B9: Pipeline metadata | C9: Strip pack_id/status/export_ready/export_notes from final app JSON. | D9: High | E9: Open
A10: Source of Truth | B10: Obscura sync | C10: App_JSON_Export.obscura must derive from Recipes.obscura via formula/transform. | D10: Critical | E10: Fixed in v1.1

Sheet Architecture_Notes
A1: Liquid Alchemy Content Pipeline v1
A3: Core Principles
A4: - Reward Curiosity
A5: - Content is king
A6: - Recipes, lore, craft, images, and relationships are content, not code
A7: - One master workbook acts as the content source of truth
A8: - App-ready JSON is generated from workbook data
A10: Current App Compatibility
A11: - The app currently imports JSON shaped as { cocktails: [...], inventory: [] }
A12: - Import replaces matching cocktail ids and appends new ids
A13: - Current app import supports cocktails, not Craft
A14: - App_JSON_Export is the flat export layer for the current app
... A69: - Zero-proof base recipes must calculate ABV from ingredients only; alcoholic variations belong in riffs/notes.

Sheet App_JSON_Export
A1: id | B1: name | C1: family | D1: subFamily | E1: baseSpirit | F1: glass | G1: occasion | H1: season | I1: difficulty | J1: serveStyle | K1: tags | L1: slider_boozy | M1: slider_sweet | N1: slider_sour | O1: slider_bitter | P1: slider_fruity | Q1: slider_herbal | R1: slider_smoky | S1: slider_spicy | T1: slider_rich | U1: ingredients | V1: instructions | W1: notes | X1: lore | Y1: riffs | Z1: tastingNotes | AA1: rating | AB1: addedAt | AC1: obscura | AD1: craftLinks | AE1: sourceUrl | AF1: imageUrl | AG1: myPhoto | AH1: pack_id | AI1: status | AJ1: export_ready | AK1: export_notes
A2: dame-blanche-au-poire | B2: Dame Blanche au Poire | C2: Sour | D2: Daisy | E2: Gin | F2: Coupe | G2: Aperitivo | H2: Year-Round | I2: Easy | J2: Up | K2: ["Sour/Tart","Fruity","Herbal/Botanical","Light/Refreshing","Elegant"] | L2: 6 | M2: 4 | N2: 6 | O2: 1 | P2: 5 | Q2: 0 | R2: 0 | S2: 0 | T2: 1 | U2: [{"name":"Gin (Citadelle recommended)","amount":"1.5","unit":"oz"},{"name":"Pear liqueur","amount":"1","unit":"oz"},{"name":"Fresh lemon juice","amount":"0.75","unit":"oz"},{"name":"Citrus peel","amount":"1","unit":"whole"}] | V2: Place the gin, pear liqueur, and lemon juice in a cocktail shaker. Cover with ice and shake vigorously until well-chilled, about 15 seconds. Strain into a chilled coupe or small tulip glass. Garnish with a citrus peel. | W2: Recipe by @bridget7487049 via ReciMe. Citadelle gin is recommended but any quality London Dry works well. | X2: The Dame Blanche is a classic gin sour from the golden age of cocktails, named after the Belgian legend of a white-robed spirit said to haunt mountain passes. Structurally it belongs to the Sour family — spirit, citrus, sweetener — here elevated with pear liqueur for a delicate floral character. | AA2: 0 | AB2: 1780281499931 | AC2: =IFERROR(XLOOKUP(SUBSTITUTE(A2,"-","_"),Recipes!$A:$A,Recipes!$AH:$AH,FALSE),FALSE) | AD2: [] | AH2: pack_000_import_20260603_2145 | AI2: imported_needs_review | AJ2: YES | AK2: Images intentionally blank for current app bulk import; use asset pipeline later.
A3: old-fashioned-classic | B3: Old Fashioned | C3: Old Fashioned | D3: Core Old Fashioned | E3: Bourbon | F3: Rocks/Old Fashioned | G3: Nightcap | H3: Year-Round | I3: Easy | J3: On the Rocks | K3: ["Boozy","Sweet","Bitter","Rich"] | L3: 9 | M3: 4 | N3: 0 | O3: 6 | P3: 2 | Q3: 0 | R3: 0 | S3: 1 | T3: 5 | U3: [{"name":"Bourbon","amount":"2","unit":"oz"},{"name":"Simple syrup","amount":"0.67","unit":"oz"},{"name":"Angostura Aromatic Bitters","amount":"5","unit":"dash"},{"name":"Angostura Orange Bitters","amount":"5","unit":"dash"},{"name":"Cocktail cherry juice","amount":"1","unit":"tbsp"},{"name":"Orange peel","amount":"1","unit":"whole"},{"name":"Cocktail cherry","amount":"1","unit":"whole"}] | V3: Place a large ice cube in a rocks glass. Add the bourbon, simple syrup, both bitters, and cherry juice. Stir with a cocktail mixing spoon for a full 30 seconds until well chilled and properly diluted. Express an orange peel over the glass, run it around the rim, and drop it in. Garnish with a cocktail cherry. | W3: The 30-second stir is non-negotiable — it's what makes the texture silky. Use a good bourbon with some proof (100+) since the dilution will soften it. | X3: The Old Fashioned is the oldest known cocktail, dating to the early 1800s — originally called simply a 'cocktail': a spirit, sugar, water, and bitters. The name came later when drinkers began requesting it 'the old-fashioned way' as bartenders started adding juices and liqueurs. It is the template from which nearly all stirred, spirit-forward cocktails descend. | AA3: 0 | AB3: 1780281499931 | AC3: =IFERROR(XLOOKUP(SUBSTITUTE(A3,"-","_"),Recipes!$A:$A,Recipes!$AH:$AH,FALSE),FALSE) | AD3: [] | AH3: pack_000_import_20260603_2145 | AI3: imported_needs_review | AJ3: YES | AK3: Images intentionally blank for current app bulk import; use asset pipeline later.
A4: rosemary-fizz | B4: Rosemary Fizz | C4: Sour | D4: Fizz | E4: Vodka | F4: Coupe | G4: Aperitivo | H4: Summer | I4: Medium | J4: Up | K4: ["Floral","Herbal/Botanical","Fruity","Sour/Tart","Sparkling","Elegant"] | L4: 5 | M4: 4 | N4: 4 | O4: 0 | P4: 3 | Q4: 5 | R4: 0 | S4: 0 | T4: 3 | U4: [{"name":"Vodka (Titos)","amount":"2","unit":"oz"},{"name":"St-Germain elderflower","amount":"1","unit":"oz"},{"name":"Fresh lemon juice","amount":"1","unit":"oz"},{"name":"Simple syrup","amount":"0.75","unit":"oz"},{"name":"Egg white","amount":"1","unit":"whole"},{"name":"Fresh strawberries","amount":"2","unit":"whole"},{"name":"Fresh rosemary sprigs","amount":"1.5","unit":"whole"},{"name":"Prosecco","amount":"2","unit":"oz"}] | V4: Add strawberries and one and a half rosemary sprigs to a shaker with simple syrup and muddle. Add egg white, vodka, and lemon juice. Dry shake without ice for at least 15 seconds to build the foam. Add ice and St-Germain and shake again for 15 more seconds. Double strain into a coupe or rocks glass over fresh ice. Top with Prosecco. Garnish with a rosemary sprig. | W4: The St-Germain is added with the ice in the second shake rather than the first — a deliberate choice to protect its delicate floral aromatics from the aggressive friction of the dry shake. It is a small detail that makes a difference. Dry shake for the full 15 seconds; the foam needs the time. Two small strawberries rather than one large one gives better muddling coverage. | X4: Created by Damon Williams at Baytowne Provisions in South Walton, Florida — a beachside bar on the Gulf Coast that is not famous and does not need to be. The lineage is what matters here: an egg white sour with elderflower and a sparkling wine top, muddled rosemary and strawberry as the aromatic foundation. The thread runs from the classic Fizz template through the St-Germain era of modern American craft bartending all the way to a bar on the Emerald Coast. Every cocktail has a lineage. This one traces from Paris to New York to the Florida Panhandle, and it is a very good drink. | Y4: Substitute gin for vodka for a more botanical result that leans into the rosemary and elderflower. Omit the Prosecco and serve straight up as a Royale variation. Blackberries in place of strawberries for an autumn version. | AA4: 0 | AB4: 1780270791298 | AC4: =IFERROR(XLOOKUP(SUBSTITUTE(A4,"-","_"),Recipes!$A:$A,Recipes!$AH:$AH,FALSE),FALSE) | AD4: [] | AH4: pack_000_import_20260603_2145 | AI4: imported_needs_review | AJ4: YES | AK4: Images intentionally blank for current app bulk import; use asset pipeline later.
A5: first-class-pass | B5: First Class Pass | C5: Highball | D5: Core Highball | E5: Whiskey | F5: Collins/Highball | G5: Aperitivo | H5: Summer | I5: Easy | J5: On the Rocks | K5: ["Herbal/Botanical","Floral","Light/Refreshing","Fruity","Elegant"] | L5: 4 | M5: 3 | N5: 2 | O5: 0 | P5: 2 | Q5: 5 | R5: 0 | S5: 0 | T5: 1 | U5: [{"name":"Irish whiskey","amount":"1.5","unit":"oz"},{"name":"Elderflower liqueur","amount":"0.25","unit":"oz"},{"name":"Vodka","amount":"0.25","unit":"oz"},{"name":"Honey syrup (1:1)","amount":"0.25","unit":"oz"},{"name":"Fresh lime juice","amount":"0.25","unit":"oz"},{"name":"Fresh cucumber slices","amount":"2","unit":"whole"},{"name":"Fresh mint leaves","amount":"5","unit":"whole"},{"name":"Yuzu soda, chilled","amount":"2","unit":"oz"}] | V5: Add cucumber slices and mint leaves to a shaker and muddle gently — bruise the cucumber and press the mint just enough to release the oils without shredding. Add Irish whiskey, elderflower liqueur, vodka, honey syrup, and lime juice. Add ice and shake well. Double strain through a fine strainer into an ice-filled highball glass. Top with chilled yuzu soda. Garnish with a lime wheel and mint sprig. | W5: Fever-Tree Lime and Yuzu is the house soda at The Irish Exit — it is worth tracking down. In a pinch, any yuzu-forward soda or a combination of yuzu juice and plain soda water will work. Double strain to remove mint fragments and cucumber seeds. The small amounts of vodka and lime are balancers rather than primary flavors — do not skip them. Honey syrup is 1:1 honey to warm water, stirred until dissolved. | X5: An evolution of an original recipe by Jack McGarry, managing partner of The Irish Exit in New York City — the sister bar to The Dead Rabbit, one of the most celebrated cocktail bars in the world. The drink matches cucumber and mint against the floral, herbal character of Irish whiskey, a pairing so natural it is surprising it is not more common. The elderflower liqueur ties both together. The yuzu soda adds a citrus brightness that keeps the whole thing from becoming heavy despite the multiple flavor elements at play. | Y5: Substitute gin for Irish whiskey for a more botanical result. Add a barspoon of St-Germain in place of the elderflower liqueur for a slightly richer floral note. | AA5: 0 | AB5: 1780270198088 | AC5: =IFERROR(XLOOKUP(SUBSTITUTE(A5,"-","_"),Recipes!$A:$A,Recipes!$AH:$AH,FALSE),FALSE) | AD5: [] | AH5: pack_000_import_20260603_2145 | AI5: imported_needs_review | AJ5: YES | AK5: Images intentionally blank for current app bulk import; use asset pipeline later.
A6: cold-fashioned | B6: Cold Fashioned | C6: Old Fashioned | D6: Core Old Fashioned | E6: Bourbon | F6: Rocks/Old Fashioned | G6: Party | H6: Summer | I6: Medium | J6: Frozen | K6: ["Boozy","Sweet","Bitter","Rich","Sour/Tart"] | L6: 7 | M6: 4 | N6: 3 | O6: 4 | P6: 2 | Q6: 0 | R6: 0 | S6: 1 | T6: 4 | U6: [{"name":"Bourbon","amount":"4","unit":"oz"},{"name":"Old Fashioned mix","amount":"2","unit":"oz"},{"name":"Citrus blend","amount":"6","unit":"oz"},{"name":"Xanthan gum (optional)","amount":"0.25","unit":"tsp"},{"name":"Pebble ice","amount":"350","unit":"g"}] | V6: Add all ingredients to a blender and blend until smooth. Serve in a rocks glass. Garnish with a brulee sugar crisp. For the Old Fashioned mix: combine 150ml black tea, 150g sugar, and 14 dashes aromatic bitters. Stir until sugar dissolves. For the citrus blend: combine 2 parts fresh lemon juice, 1 part fresh orange juice, 1 part fresh grapefruit juice. For the brulee sugar crisp: cut the end off an orange and place it upside down on a jigger. Spread 1 barspoon sugar over the center, add 8-10 drops aromatic bitters, then caramelize with a kitchen torch until fully browned and bubbling. Add a pinch of flaky sea salt as it cools. | W6: Xanthan gum is optional but recommended for texture — it prevents the blend from separating and gives the drink a smoother, more uniform consistency. A small amount goes a long way. Pre-made old fashioned mix and sour mix can substitute for the house-made versions but the scratch version is dramatically better. The brulee sugar crisp can be made ahead and stored briefly. | X6: A house cocktail from Still Austin Whiskey Co., the first whiskey distillery in Austin city limits since Prohibition. Still Austin is a grain-to-glass operation — milling, mashing, fermenting, distilling, barreling, and bottling entirely in-house — and The Musician bourbon, their flagship, is what the drink is built around. The Cold Fashioned is served at their distillery bar on the east side of Austin, alongside tours, live music, and a seafood food truck on the patio. The recipe was popularized online by Austin-based mixologist Reid Nelson (@reidbetweenthelimes), who recreated the Still Austin version at home with characteristic attention to technique and garnish detail. The brulee sugar crisp is the signature detail: sugar, aromatic bitters, and flaky sea salt caramelized on an orange slice with a kitchen torch. The xanthan gum note is worth heeding — a quarter teaspoon is the difference between a smooth frozen cocktail and a separated one. | Y6: Scale down to a single serving: 1.5oz bourbon, 0.75oz old fashioned mix, 2oz citrus blend, small pinch of xanthan gum, 4oz pebble ice. Substitute rye for a spicier result. | AA6: 0 | AB6: 1780269740325 | AC6: =IFERROR(XLOOKUP(SUBSTITUTE(A6,"-","_"),Recipes!$A:$A,Recipes!$AH:$AH,FALSE),FALSE) | AD6: ["old-fashioned-mix","citrus-blend","brulee-sugar-crisp"] | AH6: pack_000_import_20260603_2145 | AI6: imported_needs_review | AJ6: YES | AK6: Images intentionally blank for current app bulk import; use asset pipeline later.
A7: classic-margarita | B7: Classic Margarita | C7: Sour | D7: Daisy | E7: Tequila | F7: Other | G7: Party/Batch | H7: Summer | I7: Easy | J7: On the Rocks | K7: ["Sour/Tart","Fruity","Light/Refreshing","Sweet"] | L7: 6 | M7: 4 | N7: 8 | O7: 1 | P7: 3 | Q7: 1 | R7: 0 | S7: 0 | T7: 1 | U7: [{"name":"Tequila blanco","amount":"2","unit":"oz"},{"name":"Cointreau","amount":"0.5","unit":"oz"},{"name":"Fresh lime juice","amount":"1","unit":"oz"},{"name":"Agave syrup (1:1)","amount":"0.5","unit":"oz"},{"name":"Salt","amount":"1","unit":"whole"},{"name":"Lime wheel","amount":"1","unit":"whole"}] | V7: Prepare a margarita glass with a salted rim. Add tequila, Cointreau, lime juice, and agave syrup to a shaker tin. Add ice and shake hard for 15 seconds. Strain over fresh ice into the prepared glass. Garnish with a lime wheel. | W7: Use the best blanco tequila you can — it makes an enormous difference. Agave syrup at 1:1 (agave:water) keeps the sweetness clean and true to the spirit. | X7: The Margarita is technically a Daisy — a sour cocktail made with a base spirit, citrus, and an orange liqueur, served in a salt-rimmed glass. In fact, margarita is Spanish for daisy. It belongs to the same family as the Sidecar and Cosmopolitan, and is one of the most ordered cocktails in the world. Its precise origin is disputed, with several bartenders and socialites from the 1930s-50s claiming credit. | Y7: Tommy Margarita: agave nectar instead of triple sec, on the rocks. Mezcal Margarita: substitute mezcal for tequila for a smoky version. Spicy Margarita: add jalapeno-infused tequila or muddle fresh chile. | AA7: 0 | AB7: 1780198574911 | AC7: =IFERROR(XLOOKUP(SUBSTITUTE(A7,"-","_"),Recipes!$A:$A,Recipes!$AH:$AH,FALSE),FALSE) | AD7: [] | AH7: pack_000_import_20260603_2145 | AI7: imported_needs_review | AJ7: YES | AK7: Images intentionally blank for current app bulk import; use asset pipeline later.
A8: french-007 | B8: French 007 | C8: Sour | D8: Fizz | E8: Champagne/Prosecco | F8: Champagne Flute | G8: Aperitivo | H8: Year-Round | I8: Easy | J8: Up | K8: ["Fruity","Sparkling","Sweet","Light/Refreshing","Elegant"] | L8: 3 | M8: 5 | N8: 1 | O8: 0 | P8: 7 | Q8: 0 | R8: 0 | S8: 0 | T8: 2 | U8: [{"name":"Mathilde Poire Liqueur","amount":"0.5","unit":"oz"},{"name":"Pama Pomegranate Liqueur","amount":"0.5","unit":"oz"},{"name":"Dry champagne or sparkling wine","amount":"4","unit":"oz"}] | V8: Add the pear and pomegranate liqueurs to a chilled champagne flute. Top with dry champagne or sparkling wine. No stirring needed — the bubbles will do the work. | W8: The Mathilde Poire and Pama create a beautiful rose-gold color in the glass. Use a genuinely dry champagne or crémant to keep it from tipping too sweet. | X8: The French 007 is a champagne cocktail in the Kir Royale tradition — a style dating to post-war Burgundy, where Canon Félix Kir popularized the combination of crème de cassis and white wine. By substituting fruit liqueurs for cassis and using champagne, the format becomes endlessly riffable. The name nods to its Franco-elegant character — shaken, not stirred optional. | Y8: Substitute rye for bourbon for a spicier, drier result. Add a barspoon of honey syrup for a Gold Rush variation. | AA8: 0 | AB8: 1780198575011 | AC8: =IFERROR(XLOOKUP(SUBSTITUTE(A8,"-","_"),Recipes!$A:$A,Recipes!$AH:$AH,FALSE),FALSE) | AD8: [] | AH8: pack_000_import_20260603_2145 | AI8: imported_needs_review | AJ8: YES | AK8: Images intentionally blank for current app bulk import; use asset pipeline later.
A9: classic-martini | B9: Classic Martini | C9: Martini & Manhattan | D9: Martini Style | E9: Gin | F9: Martini | G9: Aperitivo | H9: Year-Round | I9: Medium | J9: Up | K9: ["Boozy","Herbal/Botanical","Elegant","Light/Refreshing"] | L9: 9 | M9: 1 | N9: 0 | O9: 2 | P9: 0 | Q9: 7 | R9: 0 | S9: 0 | T9: 1 | U9: [{"name":"London Dry gin","amount":"2.5","unit":"oz"},{"name":"Dry vermouth","amount":"0.5","unit":"oz"},{"name":"Orange bitters","amount":"1","unit":"dash"},{"name":"Lemon peel","amount":"1","unit":"whole"}] | V9: Stir gin, vermouth, and bitters with ice for 30-40 seconds until well chilled and properly diluted. Strain into a chilled martini or coupe glass. Express a lemon peel over the surface and either drop it in or perch it on the rim. | W9: The ratio is everything — 5:1 is bone dry, 3:1 is classic, 2:1 is a wet martini. Chill your glass in the freezer. Never shake unless specifically asked — it bruises the gin and clouds the drink. | X9: The Martini is arguably the most iconic cocktail in existence, its origins disputed between New York and San Francisco in the 1880s. It belongs to no family — it IS a family, the template from which the Manhattan, the Negroni, and countless others descend. Churchill famously chilled his gin by glancing at the vermouth bottle. James Bond's insistence on shaking it is, to purists, a cardinal sin. | Y9: Gibson: substitute a cocktail onion garnish for the olive. Dirty Martini: add a barspoon of olive brine. Vesper: add 0.5 oz Lillet Blanc and substitute vodka for half the gin. | AA9: 0 | AB9: 1780198574511 | AC9: =IFERROR(XLOOKUP(SUBSTITUTE(A9,"-","_"),Recipes!$A:$A,Recipes!$AH:$AH,FALSE),FALSE) | AD9: [] | AH9: pack_000_import_20260603_2145 | AI9: imported_needs_review | AJ9: YES | AK9: Images intentionally blank for current app bulk import; use asset pipeline later.
A10: classic-manhattan | B10: Manhattan | C10: Martini & Manhattan | D10: Manhattan Style | E10: Whiskey | F10: Coupe | G10: Nightcap | H10: Fall | I10: Easy | J10: Up | K10: ["Boozy","Bitter","Rich","Sweet","Elegant"] | L10: 9 | M10: 4 | N10: 0 | O10: 5 | P10: 2 | Q10: 3 | R10: 0 | S10: 2 | T10: 6 | U10: [{"name":"Rye whiskey","amount":"2","unit":"oz"},{"name":"Sweet vermouth","amount":"1","unit":"oz"},{"name":"Angostura Aromatic Bitters","amount":"2","unit":"dash"},{"name":"Cocktail cherry","amount":"1","unit":"whole"}] | V10: Combine whiskey, vermouth, and bitters in a mixing glass with ice. Stir for 30 seconds until well chilled. Strain into a chilled coupe or Nick & Nora glass. Garnish with a cocktail cherry. | W10: Rye gives a spicier, drier result; bourbon gives a softer, sweeter one. Use a quality sweet vermouth — Carpano Antica is the gold standard. The cherry matters — use a Luxardo, not a maraschino. | X10: The Manhattan was born in New York City in the 1870s, with the Manhattan Club claiming credit. It is the oldest known stirred whiskey cocktail and the direct ancestor of the Rob Roy (Scotch), the Black Manhattan (Averna), and the Toronto (Fernet). Along with the Old Fashioned and Martini it forms the holy trinity of classic American cocktails. | Y10: Rob Roy: substitute Scotch for rye. Black Manhattan: substitute Averna amaro for sweet vermouth. Perfect Manhattan: split sweet and dry vermouth equally. | AA10: 0 | AB10: 1780198574531 | AC10: =IFERROR(XLOOKUP(SUBSTITUTE(A10,"-","_"),Recipes!$A:$A,Recipes!$AH:$AH,FALSE),FALSE) | AD10: [] | AH10: pack_000_import_20260603_2145 | AI10: imported_needs_review | AJ10: YES | AK10: Images intentionally blank for current app bulk import; use asset pipeline later.
A11: classic-daiquiri | B11: Classic Daiquiri | C11: Sour | D11: Core Sour | E11: Rum | F11: Coupe | G11: Aperitivo | H11: Summer | I11: Easy | J11: Up | K11: ["Sour/Tart","Light/Refreshing","Sweet","Fruity"] | L11: 6 | M11: 4 | N11: 7 | O11: 0 | P11: 3 | Q11: 0 | R11: 0 | S11: 0 | T11: 1 | U11: [{"name":"White rum","amount":"2","unit":"oz"},{"name":"Fresh lime juice","amount":"1","unit":"oz"},{"name":"Simple syrup","amount":"0.75","unit":"oz"}] | V11: Combine all ingredients in a shaker with ice. Shake hard for 15 seconds. Double strain into a chilled coupe. | W11: The Daiquiri is a bartender's benchmark — deceptively simple, ruthlessly revealing of technique and ingredient quality. Use fresh lime juice only. The ratio of sweet to sour is the whole game — taste and adjust before shaking. | X11: The Daiquiri was born in the mining town of Daiquirí, Cuba around 1900, popularized by American engineer Jennings Cox. It belongs to the Sour family — spirit, citrus, sweetener — and is considered the purist's test of a bartender's skill. Hemingway famously drank them by the pitcher at El Floridita in Havana, though he requested his without sugar — the Papa Doble. | Y11: Hemingway Daiquiri: add grapefruit juice and maraschino, no sugar. Banana Daiquiri: add banana liqueur. Strawberry Daiquiri: blend with fresh strawberries. | AA11: 0 | AB11: 1780198574551 | AC11: =IFERROR(XLOOKUP(SUBSTITUTE(A11,"-","_"),Recipes!$A:$A,Recipes!$AH:$AH,FALSE),FALSE) | AD11: [] | AH11: pack_000_import_20260603_2145 | AI11: imported_needs_review | AJ11: YES | AK11: Images intentionally blank for current app bulk import; use asset pipeline later.
A12: classic-negroni | B12: Negroni | C12: Negroni | E12: Gin | F12: Rocks/Old Fashioned | G12: Aperitivo | H12: Year-Round | I12: Easy | J12: On the Rocks | K12: ["Bitter","Herbal/Botanical","Boozy","Sweet","Elegant"] | L12: 7 | M12: 4 | N12: 0 | O12: 8 | P12: 1 | Q12: 6 | R12: 0 | S12: 1 | T12: 3 | U12: [{"name":"London Dry gin","amount":"1","unit":"oz"},{"name":"Campari","amount":"1","unit":"oz"},{"name":"Sweet vermouth","amount":"1","unit":"oz"},{"name":"Orange peel","amount":"1","unit":"whole"}] | V12: Combine gin, Campari, and sweet vermouth in a mixing glass with ice. Stir for 30 seconds. Strain over a large ice cube in a rocks glass. Express an orange peel over the surface and drop it in. | W12: Equal parts is the rule — resist the urge to increase the gin. The Negroni rewards patience; stir it longer than you think necessary. Substituting bourbon for gin gives you a Boulevardier. | X12: The Negroni was born in Florence in 1919 when Count Camillo Negroni asked bartender Fosco Scarselli to strengthen his Americano by replacing the soda water with gin. It belongs to the equal-parts family and is the gateway drug to the world of bitter, amaro-driven cocktails. The Sbagliato (with prosecco), Boulevardier (with bourbon), and Mezcal Negroni are its most celebrated variations. | Y12: Boulevardier: substitute bourbon for gin. Mezcal Negroni: substitute mezcal for gin. Sbagliato: substitute Prosecco for gin. White Negroni: substitute Suze and Lillet Blanc. | AA12: 0 | AB12: 1780198574571 | AC12: =IFERROR(XLOOKUP(SUBSTITUTE(A12,"-","_"),Recipes!$A:$A,Recipes!$AH:$AH,FALSE),FALSE) | AD12: [] | AH12: pack_000_import_20260603_2145 | AI12: imported_needs_review | AJ12: YES | AK12: Images intentionally blank for current app bulk import; use asset pipeline later.
A13: classic-whiskey-sour | B13: Whiskey Sour | C13: Sour | D13: Egg White Sour | E13: Bourbon | F13: Rocks/Old Fashioned | G13: Anytime | H13: Year-Round | I13: Easy | J13: On the Rocks | K13: ["Sour/Tart","Sweet","Fruity","Creamy/Rich"] | L13: 6 | M13: 5 | N13: 7 | O13: 1 | P13: 2 | Q13: 0 | R13: 0 | S13: 1 | T13: 4 | U13: [{"name":"Bourbon","amount":"2","unit":"oz"},{"name":"Fresh lemon juice","amount":"0.75","unit":"oz"},{"name":"Simple syrup","amount":"0.75","unit":"oz"},{"name":"Egg white","amount":"1","unit":"whole"},{"name":"Angostura Aromatic Bitters","amount":"2","unit":"dash"}] | V13: Dry shake all ingredients without ice for 15 seconds to emulsify the egg white. Add ice and shake hard for another 15 seconds. Strain into a rocks glass over ice. Dash bitters on the foam and drag a toothpick through for a decorative pattern. | W13: The egg white is optional but transforms the texture — silky and luxurious. The dry shake first is essential to build the foam. For a Boston Sour, serve up in a coupe. | X13: The Whiskey Sour dates to at least 1862, appearing in Jerry Thomas's seminal bartending guide. It represents the entire Sour family — spirit, citrus, sweetener — which is the most important template in cocktail making. The addition of egg white elevates it to a Fizz or Boston Sour. Nearly every fruit-forward modern cocktail traces its lineage to this template. | Y13: New York Sour: float red wine on top. Boston Sour: add egg white. Add a dash of Angostura bitters for more structure. | AA13: 0 | AB13: 1780198574591 | AC13: =IFERROR(XLOOKUP(SUBSTITUTE(A13,"-","_"),Recipes!$A:$A,Recipes!$AH:$AH,FALSE),FALSE) | AD13: [] | AH13: pack_000_import_20260603_2145 | AI13: imported_needs_review | AJ13: YES | AK13: Images intentionally blank for current app bulk import; use asset pipeline later.
A14: moscow-mule | B14: Moscow Mule | C14: Highball | D14: Ginger Highball / Buck | E14: Vodka | F14: Copper Mug | G14: Party/Batch | H14: Summer | I14: Easy | J14: On the Rocks | K14: ["Light/Refreshing","Spicy","Sparkling"] | L14: 4 | M14: 2 | N14: 3 | O14: 0 | P14: 1 | Q14: 0 | R14: 0 | S14: 5 | T14: 0 | U14: [{"name":"Vodka","amount":"2","unit":"oz"},{"name":"Fresh lime juice","amount":"0.5","unit":"oz"},{"name":"Ginger beer","amount":"4","unit":"oz"},{"name":"Lime wheel","amount":"1","unit":"whole"}] | V14: Fill a copper mug with ice. Add vodka and lime juice. Top with ginger beer and gently stir to combine. Garnish with a lime wheel. | W14: The copper mug is traditional and does keep the drink colder longer. Use a spicy, full-flavored ginger beer — Fever-Tree or Bundaberg work well. Substituting dark rum gives you a Dark & Stormy. | X14: The Moscow Mule was invented in 1941 at the Cock 'n' Bull pub in Los Angeles as a marketing collaboration between Smirnoff vodka and a ginger beer company. Its signature copper mug was a stroke of branding genius. It represents the Highball family — spirit, mixer, ice — the simplest and most refreshing cocktail template, and the one responsible for popularizing vodka in America. | Y14: Dark and Stormy: substitute dark rum for vodka. Kentucky Mule: substitute bourbon. Mexican Mule: substitute tequila. | AA14: 0 | AB14: 1780198574611 | AC14: =IFERROR(XLOOKUP(SUBSTITUTE(A14,"-","_"),Recipes!$A:$A,Recipes!$AH:$AH,FALSE),FALSE) | AD14: [] | AH14: pack_000_import_20260603_2145 | AI14: imported_needs_review | AJ14: YES | AK14: Images intentionally blank for current app bulk import; use asset pipeline later.
A15: classic-cosmopolitan | B15: Cosmopolitan | C15: Sour | D15: Daisy | E15: Vodka | F15: Martini | G15: Party/Batch | H15: Year-Round | I15: Easy | J15: Up | K15: ["Fruity","Sour/Tart","Light/Refreshing","Elegant"] | L15: 5 | M15: 4 | N15: 6 | O15: 0 | P15: 7 | Q15: 0 | R15: 0 | S15: 0 | T15: 1 | U15: [{"name":"Vodka","amount":"1.5","unit":"oz"},{"name":"Cointreau","amount":"0.5","unit":"oz"},{"name":"Fresh lime juice","amount":"0.5","unit":"oz"},{"name":"Cranberry juice","amount":"0.5","unit":"oz"},{"name":"Orange peel","amount":"1","unit":"whole"}] | V15: Combine all ingredients in a shaker with ice. Shake hard for 15 seconds. Strain into a chilled martini glass. Garnish with an expressed orange peel. | W15: Use just enough cranberry juice to give the drink its signature blush — more than half an ounce and it tips too sweet. Citrus vodka is traditional but a clean neutral vodka works equally well. | X15: The Cosmopolitan was popularized by bartender Toby Cecchini at The Odeon in New York in 1988, though earlier versions existed in Florida and Provincetown. It became a cultural phenomenon through Sex and the City in the late 1990s, making it one of the most recognizable cocktails in the world. Technically a Daisy — spirit, citrus, orange liqueur — it shares its DNA with the Margarita and Sidecar. | Y15: Add a float of Cointreau for extra orange richness. Substitute blood orange juice for regular cranberry for a seasonal variation. | AA15: 0 | AB15: 1780198574631 | AC15: =IFERROR(XLOOKUP(SUBSTITUTE(A15,"-","_"),Recipes!$A:$A,Recipes!$AH:$AH,FALSE),FALSE) | AD15: [] | AH15: pack_000_import_20260603_2145 | AI15: imported_needs_review | AJ15: YES | AK15: Images intentionally blank for current app bulk import; use asset pipeline later.
A16: aperol-spritz | B16: Aperol Spritz | C16: Spritz & Aperitivo | D16: Classic Spritz | E16: Aperol | F16: Wine Glass | G16: Aperitivo | H16: Summer | I16: Easy | J16: On the Rocks | K16: ["Light/Refreshing","Sparkling","Bitter","Fruity","Elegant"] | L16: 2 | M16: 4 | N16: 1 | O16: 5 | P16: 4 | Q16: 2 | R16: 0 | S16: 0 | T16: 1 | U16: [{"name":"Aperol","amount":"2","unit":"oz"},{"name":"Prosecco","amount":"3","unit":"oz"},{"name":"Club soda","amount":"1","unit":"oz"},{"name":"Orange peel","amount":"1","unit":"whole"}] | V16: Build in a large wine glass over ice. Add Aperol first, then prosecco, then a splash of soda. Gently stir once. Garnish with a slice of orange or an expressed orange peel. | W16: The 3-2-1 ratio (prosecco-Aperol-soda) is the classic formula. Some prefer 2-2-1 for a boozier version. Always build in the glass — never shake or stir aggressively or you'll lose the bubbles. | X16: The Aperol Spritz follows the Venetian spritz tradition dating to the 19th century, when Austrian soldiers stationed in the Veneto diluted local wines with a spritz (splash) of water. Aperol itself was created in Padua in 1919. Though long popular in northern Italy, the drink became a global phenomenon after Campari Group's aggressive marketing campaign in the 2000s — making it the defining aperitivo of a generation. | Y16: Campari Spritz: substitute Campari for a more bitter, less sweet result. Hugo Spritz: substitute elderflower liqueur and add mint. | AA16: 0 | AB16: 1780198574651 | AC16: =IFERROR(XLOOKUP(SUBSTITUTE(A16,"-","_"),Recipes!$A:$A,Recipes!$AH:$AH,FALSE),FALSE) | AD16: [] | AH16: pack_000_import_20260603_2145 | AI16: imported_needs_review | AJ16: YES | AK16: Images intentionally blank for current app bulk import; use asset pipeline later.
A17: french-75 | B17: French 75 | C17: Sour | D17: Fizz | E17: Gin | F17: Champagne Flute | G17: Aperitivo | H17: Spring | I17: Easy | J17: Up | K17: ["Sparkling","Sour/Tart","Elegant","Light/Refreshing","Boozy"] | L17: 6 | M17: 3 | N17: 5 | O17: 0 | P17: 1 | Q17: 3 | R17: 0 | S17: 0 | T17: 1 | U17: [{"name":"London Dry gin","amount":"1.5","unit":"oz"},{"name":"Fresh lemon juice","amount":"0.75","unit":"oz"},{"name":"Simple syrup","amount":"0.5","unit":"oz"},{"name":"Dry champagne","amount":"2","unit":"oz"},{"name":"Lemon peel","amount":"1","unit":"whole"}] | V17: Combine gin, lemon juice, and simple syrup in a shaker with ice. Shake for 10 seconds. Strain into a chilled champagne flute. Top with champagne. Garnish with a lemon peel. | W17: Cognac is the traditional base in France; gin is the Anglo-American version. Either works beautifully. Use a genuinely dry champagne or crémant — the drink has enough sweetness already. | X17: The French 75 was created at Harry's New York Bar in Paris in 1915, named after the French 75mm field gun because its kick was said to feel like being shelled by one. It belongs to the Fizz family — spirit, citrus, sweetener, topped with bubbles — and is one of the few truly great champagne cocktails. It was famously featured in the film Casablanca. | Y17: Substitute rye for gin for a spicier, spirit-forward variation. Add a barspoon of St-Germain for a floral lift. | AA17: 0 | AB17: 1780198574671 | AC17: =IFERROR(XLOOKUP(SUBSTITUTE(A17,"-","_"),Recipes!$A:$A,Recipes!$AH:$AH,FALSE),FALSE) | AD17: [] | AH17: pack_000_import_20260603_2145 | AI17: imported_needs_review | AJ17: YES | AK17: Images intentionally blank for current app bulk import; use asset pipeline later.
A18: classic-sidecar | B18: Sidecar | C18: Sour | D18: Daisy | E18: Cognac | F18: Coupe | G18: After Dinner | H18: Fall | I18: Easy | J18: Up | K18: ["Sour/Tart","Boozy","Sweet","Elegant"] | L18: 7 | M18: 4 | N18: 6 | O18: 1 | P18: 2 | Q18: 0 | R18: 0 | S18: 0 | T18: 3 | U18: [{"name":"Cognac","amount":"2","unit":"oz"},{"name":"Cointreau","amount":"0.75","unit":"oz"},{"name":"Fresh lemon juice","amount":"0.75","unit":"oz"},{"name":"Sugar","amount":"1","unit":"whole"}] | V18: Sugar the rim of a coupe glass. Combine cognac, Cointreau, and lemon juice in a shaker with ice. Shake hard for 15 seconds. Double strain into the prepared glass. | W18: The sugared rim is traditional but optional — omit it if you prefer a drier drink. The ratio of spirit to orange liqueur to citrus (2:1:1 or 8:3:3) is the same template as the Margarita and Cosmopolitan. | X18: The Sidecar was born in Paris around World War I, with Harry's New York Bar and the Ritz both claiming credit. It is one of the great classic Daisies — the same family as the Margarita and Cosmopolitan — and essentially a Cognac sour with orange liqueur substituting for simple syrup. Its name supposedly comes from the motorcycle sidecar in which a regular patron arrived. | Y18: Brandy Crusta: add maraschino and bitters, add a sugar-rimmed crusta — the ancestor of this drink. Substitute Calvados for cognac for a French apple variation. | AA18: 0 | AB18: 1780198573511 | AC18: =IFERROR(XLOOKUP(SUBSTITUTE(A18,"-","_"),Recipes!$A:$A,Recipes!$AH:$AH,FALSE),FALSE) | AD18: [] | AH18: pack_000_import_20260603_2145 | AI18: imported_needs_review | AJ18: YES | AK18: Images intentionally blank for current app bulk import; use asset pipeline later.
A19: pisco-sour | B19: Pisco Sour | C19: Sour | D19: Egg White Sour | E19: Pisco | F19: Coupe | G19: Aperitivo | H19: Year-Round | I19: Medium | J19: Up | K19: ["Sour/Tart","Fruity","Creamy/Rich","Light/Refreshing"] | L19: 6 | M19: 4 | N19: 7 | O19: 2 | P19: 3 | Q19: 0 | R19: 0 | S19: 0 | T19: 4 | U19: [{"name":"Pisco","amount":"2","unit":"oz"},{"name":"Fresh lime juice","amount":"0.75","unit":"oz"},{"name":"Simple syrup","amount":"0.75","unit":"oz"},{"name":"Egg white","amount":"1","unit":"whole"},{"name":"Angostura Aromatic Bitters","amount":"3","unit":"dash"}] | V19: Combine pisco, lime juice, simple syrup, and egg white in a shaker without ice. Dry shake vigorously for 15 seconds. Add ice and shake hard for another 15 seconds. Strain into a chilled coupe. Dot bitters on the foam and drag a toothpick through to make a decorative pattern. | W19: The bitters pattern on the foam is traditional and visually striking — do not skip it. Peruvian pisco (Quebranta grape) gives a fuller, earthier result than Chilean pisco. | X19: The Pisco Sour is the national cocktail of both Peru and Chile, a rivalry that has sparked genuine diplomatic tension. The Peruvian version, created by American bartender Victor Vaughen Morris in Lima in the 1920s, uses Peruvian pisco and lime. The Chilean version uses lemon. Both nations consider the other's version a heresy. It belongs to the Sour family and is one of the few classics to feature bitters as a garnish rather than a flavor component. | Y19: Substitute gin for pisco for an egg white gin sour. Add a dash of Angostura bitters on top of the foam as aromatics. | AA19: 0 | AB19: 1780198573531 | AC19: =IFERROR(XLOOKUP(SUBSTITUTE(A19,"-","_"),Recipes!$A:$A,Recipes!$AH:$AH,FALSE),FALSE) | AD19: [] | AH19: pack_000_import_20260603_2145 | AI19: imported_needs_review | AJ19: YES | AK19: Images intentionally blank for current app bulk import; use asset pipeline later.
A20: bees-knees | B20: Bee's Knees | C20: Sour | D20: Core Sour | E20: Gin | F20: Coupe | G20: Aperitivo | H20: Spring | I20: Easy | J20: Up | K20: ["Sour/Tart","Herbal/Botanical","Sweet","Light/Refreshing","Elegant"] | L20: 6 | M20: 5 | N20: 6 | O20: 1 | P20: 1 | Q20: 5 | R20: 0 | S20: 0 | T20: 2 | U20: [{"name":"London Dry gin","amount":"2","unit":"oz"},{"name":"Fresh lemon juice","amount":"0.75","unit":"oz"},{"name":"Honey syrup","amount":"0.75","unit":"oz"},{"name":"Lemon peel","amount":"1","unit":"whole"}] | V20: Make honey syrup by combining equal parts honey and warm water and stirring until dissolved. Combine gin, lemon juice, and honey syrup in a shaker with ice. Shake hard for 15 seconds. Double strain into a chilled coupe. Garnish with a lemon peel. | W20: Make your honey syrup fresh — it keeps in the fridge for two weeks. The floral quality of honey pairs beautifully with botanical gins. Lavender honey gives a particularly lovely result. | X20: The Bee's Knees was born during Prohibition in the 1920s, when honey and lemon were used to mask the rough taste of bathtub gin. The name was 1920s slang for the best of something — like the cat's pajamas. It is a gin sour with honey substituting for simple syrup, and represents the broader category of honey-sweetened cocktails that includes the Gold Rush (bourbon) and the Brown Derby (grapefruit). | Y20: Substitute rye for gin for a spicier, more spirit-forward version. Add a barspoon of elderflower liqueur for a floral lift. | AA20: 0 | AB20: 1780198573551 | AC20: =IFERROR(XLOOKUP(SUBSTITUTE(A20,"-","_"),Recipes!$A:$A,Recipes!$AH:$AH,FALSE),FALSE) | AD20: [] | AH20: pack_000_import_20260603_2145 | AI20: imported_needs_review | AJ20: YES | AK20: Images intentionally blank for current app bulk import; use asset pipeline later.
A21: classic-gimlet | B21: Gimlet | C21: Sour | D21: Core Sour | E21: Gin | F21: Coupe | G21: Aperitivo | H21: Spring | I21: Easy | J21: Up | K21: ["Sour/Tart","Herbal/Botanical","Light/Refreshing","Sweet"] | L21: 6 | M21: 4 | N21: 7 | O21: 1 | P21: 2 | Q21: 5 | R21: 0 | S21: 0 | T21: 1 | U21: [{"name":"London Dry gin","amount":"2","unit":"oz"},{"name":"Fresh lime juice","amount":"0.75","unit":"oz"},{"name":"Simple syrup","amount":"0.75","unit":"oz"},{"name":"Lime wheel","amount":"1","unit":"whole"}] | V21: Combine gin, lime juice, and simple syrup in a shaker with ice. Shake hard for 15 seconds. Double strain into a chilled coupe or Nick & Nora glass. Garnish with a lime wheel or cucumber ribbon. | W21: The classic recipe calls for Rose's lime cordial, but fresh lime juice with simple syrup is vastly superior. A cucumber ribbon or sprig of dill adds a beautiful botanical lift. | X21: The Gimlet has Royal Navy origins, created in the 19th century when Surgeon General Sir Thomas Gimlette began mixing gin with lime juice to help sailors take their daily anti-scurvy ration. It appears in Raymond Chandler's The Long Goodbye, where Philip Marlowe declares that 'a real gimlet is half gin and half Rose's lime juice and nothing else.' Most modern bartenders respectfully disagree. | Y21: Rose Gimlet: add a barspoon of rose water. Mezcal Gimlet: substitute mezcal for gin for a smoky variation. | AA21: 0 | AB21: 1780198573571 | AC21: =IFERROR(XLOOKUP(SUBSTITUTE(A21,"-","_"),Recipes!$A:$A,Recipes!$AH:$AH,FALSE),FALSE) | AD21: [] | AH21: pack_000_import_20260603_2145 | AI21: imported_needs_review | AJ21: YES | AK21: Images intentionally blank for current app bulk import; use asset pipeline later.
A22: southside | B22: Southside | C22: Sour | D22: Core Sour | E22: Gin | F22: Coupe | G22: Aperitivo | H22: Summer | I22: Easy | J22: Up | K22: ["Sour/Tart","Herbal/Botanical","Light/Refreshing","Fruity"] | L22: 6 | M22: 4 | N22: 6 | O22: 1 | P22: 2 | Q22: 6 | R22: 0 | S22: 0 | T22: 1 | U22: [{"name":"London Dry gin","amount":"2","unit":"oz"},{"name":"Fresh lime juice","amount":"0.75","unit":"oz"},{"name":"Simple syrup","amount":"0.75","unit":"oz"},{"name":"Mint","amount":"8","unit":"whole"},{"name":"Lime wheel","amount":"1","unit":"whole"}] | V22: Gently muddle mint with simple syrup in the bottom of a shaker tin — press, do not tear. Add gin, lime juice, and ice. Shake hard for 15 seconds. Double strain through a fine mesh strainer into a chilled coupe. Garnish with a lime wheel and mint sprig. | W22: Double strain through a fine mesh sieve to remove all mint fragments. The key is bruising the mint gently — over-muddling releases bitter chlorophyll from the stems. | X22: The Southside is a gin sour with fresh mint — essentially a gin Mojito served up. Its origins are disputed between the 21 Club in New York and the South Side of Chicago during Prohibition, where bootleggers allegedly used mint and citrus to mask the taste of rough spirits. It remains a fixture of country club and yacht club culture, particularly in the American Northeast. | Y22: Southside Fizz: top with soda water and serve tall over ice. | AA22: 0 | AB22: 1780198573591 | AC22: =IFERROR(XLOOKUP(SUBSTITUTE(A22,"-","_"),Recipes!$A:$A,Recipes!$AH:$AH,FALSE),FALSE) | AD22: [] | AH22: pack_000_import_20260603_2145 | AI22: imported_needs_review | AJ22: YES | AK22: Images intentionally blank for current app bulk import; use asset pipeline later.
A23: clover-club | B23: Clover Club | C23: Sour | D23: Egg White Sour | E23: Gin | F23: Coupe | G23: Aperitivo | H23: Spring | I23: Medium | J23: Up | K23: ["Fruity","Sour/Tart","Creamy/Rich","Elegant","Floral"] | L23: 5 | M23: 4 | N23: 5 | O23: 1 | P23: 5 | Q23: 3 | R23: 0 | S23: 0 | T23: 4 | U23: [{"name":"Gin (Plymouth)","amount":"1.5","unit":"oz"},{"name":"Dry vermouth (Dolin)","amount":"0.5","unit":"oz"},{"name":"Fresh lemon juice","amount":"0.5","unit":"oz"},{"name":"Raspberry syrup","amount":"0.5","unit":"oz"},{"name":"Egg white","amount":"0.25","unit":"oz"}] | V23: Add all ingredients to a shaker with ice. Shake until well chilled and strain back into the empty tin. Shake again without ice — the reverse dry shake — until the foam builds. Pour into a chilled coupe. Garnish with 2-3 fresh raspberries on a skewer. For raspberry syrup: smash half cup fresh raspberries with 1 cup sugar and macerate for 30 minutes. Heat half cup water to warm (not hot) and pour over the fruit mixture. Stir until sugar dissolves. Strain through a chinois and fortify with half oz vodka to extend shelf life. The key is warm water not hot — hot water cooks the berries and produces a jam flavor rather than a bright fresh raspberry. | W23: The reverse dry shake — shaking with ice first, then straining and shaking again without ice — produces a notably frothier, more stable foam than the standard dry shake first method. Julie Reiner calls it optional but it is worth doing. The dry vermouth is the critical addition: it adds dryness and complexity and is in fact the historically accurate spec, confirmed by food historian David Wondrich who found the original 1890s recipe with vermouth intact. Plymouth gin is recommended for its softer, less juniper-forward botanical profile. | X23: Named for a Philadelphia men's literary club that met at the Bellevue-Stratford Hotel in the 1890s — the Clover Club cocktail predates Prohibition by two decades. The recipe that survived into the modern era had lost its dry vermouth somewhere along the way, making it sweeter and less complex than the original. Julie Reiner, who named her Brooklyn bar after the drink, restored the vermouth after historian David Wondrich found the original recipe in print. He apparently came running. The addition makes it more sophisticated and, it turns out, more historically accurate. Her bar has been making it this way since 2008. Even now, she notes with some amusement, you would think that more people would look to us for what the recipe should be. | Y23: The quick version: substitute half oz simple syrup for the raspberry syrup and muddle 3-4 fresh raspberries directly in the shaker. Less concentrated but faster. The Rattlesnake is a close cousin in the egg white sour family. | AA23: 0 | AB23: 1780198573611 | AC23: =IFERROR(XLOOKUP(SUBSTITUTE(A23,"-","_"),Recipes!$A:$A,Recipes!$AH:$AH,FALSE),FALSE) | AD23: [] | AH23: pack_000_import_20260603_2145 | AI23: imported_needs_review | AJ23: YES | AK23: Images intentionally blank for current app bulk import; use asset pipeline later.
A24: rob-roy | B24: Rob Roy | C24: Martini & Manhattan | D24: Manhattan Style | E24: Scotch | F24: Coupe | G24: Nightcap | H24: Winter | I24: Easy | J24: Up | K24: ["Boozy","Bitter","Rich","Sweet","Elegant","Smoky"] | L24: 9 | M24: 3 | N24: 0 | O24: 5 | P24: 1 | Q24: 2 | R24: 4 | S24: 2 | T24: 5 | U24: [{"name":"Scotch whisky","amount":"2","unit":"oz"},{"name":"Sweet vermouth","amount":"1","unit":"oz"},{"name":"Angostura Aromatic Bitters","amount":"2","unit":"dash"},{"name":"Cocktail cherry","amount":"1","unit":"whole"}] | V24: Combine Scotch, vermouth, and bitters in a mixing glass with ice. Stir for 30 seconds. Strain into a chilled coupe or Nick & Nora glass. Garnish with a cocktail cherry. | W24: The Scotch you choose defines the drink entirely. A blended Scotch gives a smooth, approachable result; an Islay single malt makes it smoky and dramatic. Dry vermouth instead of sweet gives you a Dry Rob Roy. | X24: The Rob Roy is simply a Manhattan made with Scotch whisky instead of rye or bourbon, created at the Waldorf Astoria in New York in 1894 to celebrate the opening of a Broadway operetta about the Scottish folk hero Rob Roy MacGregor. It demonstrates how the Manhattan template — whiskey, sweet vermouth, bitters — translates beautifully across different whisky styles. | Y24: Perfect Rob Roy: split sweet and dry vermouth equally. Dry Rob Roy: use dry vermouth only. | AA24: 0 | AB24: 1780198573631 | AC24: =IFERROR(XLOOKUP(SUBSTITUTE(A24,"-","_"),Recipes!$A:$A,Recipes!$AH:$AH,FALSE),FALSE) | AD24: [] | AH24: pack_000_import_20260603_2145 | AI24: imported_needs_review | AJ24: YES | AK24: Images intentionally blank for current app bulk import; use asset pipeline later.
... A43: dangerous-passion | B43: Dangerous Passion | C43: Sour | D43: Daisy | E43: Tequila | F43: Rocks/Old Fashioned | G43: Date Night | H43: Summer | I43: Medium | J43: On the Rocks | K43: ["Spicy","Fruity","Tropical","Boozy","Elegant"] | L43: 7 | M43: 4 | N43: 2 | O43: 1 | P43: 8 | Q43: 2 | R43: 1 | S43: 7 | T43: 3 | U43: [{"name":"Teremana Reposado Tequila","amount":"1.75","unit":"oz"},{"name":"Domaine de Canton Ginger Liqueur","amount":"0.875","unit":"oz"},{"name":"Ancho Reyes Chile Ancho Liqueur","amount":"1.75","unit":"oz"},{"name":"Fresh passion fruit juice","amount":"1.75","unit":"oz"},{"name":"Dehydrated lime slice","amount":"1","unit":"whole"},{"name":"Habanero pepper","amount":"0.5","unit":"whole"},{"name":"Cardamom seeds","amount":"1","unit":"pinch"}] | V43: Combine the tequila, ginger liqueur, Ancho Reyes, and passion fruit juice in a shaker over ice. Shake vigorously for 30 seconds. Strain into a rocks glass over fresh ice. To garnish, lightly torch or briefly flame the dehydrated lime slice, the halved habanero pepper, and a pinch of cardamom seeds to release their aromas. Place on the rim or float on top of the drink. | W43: The flamed garnish is essential to the experience — the scorched habanero and toasted cardamom transform the aromatic profile entirely. Fresh passion fruit juice is strongly preferred; bottled works but loses the floral brightness. Teremana Reposado brings a gentle oak and vanilla quality that bridges the fruit and heat beautifully. | X43: Created at a beachside bar in Aruba, the Dangerous Passion — El Azarosa Passionato in its original Spanish-Italian — is a masterclass in the seductive tension between tropical sweetness and slow-building heat. The passion fruit opens bright and floral, the ginger adds warmth, and the Ancho Reyes delivers a long, smoky chile finish. The flamed garnish is theatre as much as technique — the scorched habanero releases capsaicin aromatics that prime the palate before the first sip. A cocktail that lives up to its name. | Y43: Substitute gin for vodka for a more botanical version. Add a barspoon of grenadine for a deeper, richer color. | AA43: 0 | AB43: 1780198574011 | AC43: =IFERROR(XLOOKUP(SUBSTITUTE(A43,"-","_"),Recipes!$A:$A,Recipes!$AH:$AH,FALSE),FALSE) | AD43: [] | AH43: pack_000_import_20260603_2145 | AI43: imported_needs_review | AJ43: YES | AK43: Images intentionally blank for current app bulk import; use asset pipeline later.
A44: monte-cassino | B44: Monte Cassino | C44: Sour | D44: Core Sour | E44: Whiskey | F44: Coupe | G44: Nightcap | H44: Year-Round | I44: Easy | J44: Up | K44: ["Boozy","Sour/Tart","Herbal/Botanical","Elegant"] | L44: 6 | M44: 3 | N44: 5 | O44: 2 | P44: 0 | Q44: 7 | R44: 0 | S44: 1 | T44: 3 | U44: [{"name":"Rye whiskey","amount":"0.75","unit":"oz"},{"name":"Yellow Chartreuse","amount":"0.75","unit":"oz"},{"name":"Benedictine","amount":"0.75","unit":"oz"},{"name":"Lemon juice","amount":"0.75","unit":"oz"}] | W44: From Steve the Bartender's Top 10 list. | Y44: Substitute Yellow Chartreuse for Green for a softer, less assertive variation. | AA44: 0 | AB44: 1780198575311 | AC44: =IFERROR(XLOOKUP(SUBSTITUTE(A44,"-","_"),Recipes!$A:$A,Recipes!$AH:$AH,FALSE),FALSE) | AD44: [] | AH44: pack_000_import_20260603_2145 | AI44: imported_needs_review | AJ44: NO | AK44: Missing: instructions; Images intentionally blank for current app bulk import; use asset pipeline later.
A45: flor-de-jerez | B45: Flor de Jerez | C45: Sour | D45: Core Sour | E45: Vermouth | F45: Coupe | G45: Aperitivo | H45: Year-Round | I45: Medium | J45: Up | K45: ["Boozy","Sour/Tart","Fruity","Elegant"] | L45: 5 | M45: 3 | N45: 5 | O45: 2 | P45: 4 | Q45: 2 | R45: 0 | S45: 0 | T45: 2 | U45: [{"name":"Amontillado sherry","amount":"1.5","unit":"oz"},{"name":"Jamaican rum","amount":"0.5","unit":"oz"},{"name":"Apricot brandy liqueur, Marionette","amount":"0.25","unit":"oz"},{"name":"Lemon juice","amount":"0.75","unit":"oz"},{"name":"Cane syrup","amount":"0.5","unit":"oz"},{"name":"Angostura bitters","amount":"1","unit":"dash"}] | W45: From Steve the Bartender's Top 10 list. | Y45: Substitute fino sherry for manzanilla for a nuttier, more oxidized character. | AA45: 0 | AB45: 1780198575312 | AC45: =IFERROR(XLOOKUP(SUBSTITUTE(A45,"-","_"),Recipes!$A:$A,Recipes!$AH:$AH,FALSE),FALSE) | AD45: [] | AH45: pack_000_import_20260603_2145 | AI45: imported_needs_review | AJ45: NO | AK45: Missing: instructions; Images intentionally blank for current app bulk import; use asset pipeline later.
A46: bicycle-thief | B46: Bicycle Thief | C46: Sour | D46: Daisy | E46: Gin | F46: Highball | G46: Aperitivo | H46: Spring | I46: Easy | J46: On the Rocks | K46: ["Boozy","Sour/Tart","Bitter","Fruity","Light/Refreshing"] | L46: 5 | M46: 2 | N46: 5 | O46: 5 | P46: 4 | Q46: 2 | R46: 0 | S46: 0 | T46: 1 | U46: [{"name":"Dry gin","amount":"1","unit":"oz"},{"name":"Campari","amount":"1","unit":"oz"},{"name":"Grapefruit juice","amount":"1.5","unit":"oz"},{"name":"Lemon juice","amount":"0.5","unit":"oz"},{"name":"Simple syrup","amount":"0.5","unit":"oz"},{"name":"Soda water","amount":"1","unit":"oz"}] | W46: From Steve the Bartender's Top 10 list. | Y46: Add a barspoon of grenadine for a fruitier, deeper result. | AA46: 0 | AB46: 1780198575313 | AC46: =IFERROR(XLOOKUP(SUBSTITUTE(A46,"-","_"),Recipes!$A:$A,Recipes!$AH:$AH,FALSE),FALSE) | AD46: [] | AH46: pack_000_import_20260603_2145 | AI46: imported_needs_review | AJ46: NO | AK46: Missing: instructions; Images intentionally blank for current app bulk import; use asset pipeline later.
A47: kentucky-buck | B47: Kentucky Buck | C47: Highball | D47: Ginger Highball / Buck | E47: Bourbon | F47: Highball | G47: Party | H47: Summer | I47: Easy | J47: On the Rocks | K47: ["Boozy","Sour/Tart","Fruity","Spicy/Warming"] | L47: 6 | M47: 3 | N47: 4 | O47: 2 | P47: 3 | Q47: 0 | R47: 0 | S47: 3 | T47: 2 | U47: [{"name":"Bourbon whiskey","amount":"2","unit":"oz"},{"name":"Lemon juice","amount":"0.75","unit":"oz"},{"name":"Simple syrup","amount":"0.5","unit":"oz"},{"name":"Angostura bitters","amount":"2","unit":"dash"},{"name":"Ginger beer","amount":"1","unit":"oz"},{"name":"Strawberry, muddled","amount":"1","unit":"whole"}] | W47: By @BartenderAtLarge. From Steve the Bartender's Top 10 list. | Y47: Moscow Mule: substitute vodka for bourbon. Mexican Mule: substitute tequila. | AA47: 0 | AB47: 1780198575314 | AC47: =IFERROR(XLOOKUP(SUBSTITUTE(A47,"-","_"),Recipes!$A:$A,Recipes!$AH:$AH,FALSE),FALSE) | AD47: [] | AH47: pack_000_import_20260603_2145 | AI47: imported_needs_review | AJ47: NO | AK47: Missing: instructions; Images intentionally blank for current app bulk import; use asset pipeline later.
A48: bitter-giuseppe | B48: Bitter Giuseppe | C48: Old Fashioned | D48: Bittered Spirit | E48: Amaro | F48: Rocks/Old Fashioned | G48: Nightcap | H48: Fall | I48: Easy | J48: On the Rocks | K48: ["Boozy","Bitter","Herbal/Botanical","Elegant"] | L48: 6 | M48: 3 | N48: 1 | O48: 8 | P48: 0 | Q48: 6 | R48: 0 | S48: 1 | T48: 4 | U48: [{"name":"Cynar","amount":"2","unit":"oz"},{"name":"Sweet vermouth","amount":"1","unit":"oz"},{"name":"Orange bitters","amount":"2","unit":"dash"},{"name":"Lemon juice","amount":"12","unit":"drop"}] | W48: Original specs from Steve the Bartender's Top 10 list. | Y48: Add a barspoon of Fernet-Branca for an intensely bitter, digestif-style variation. | AA48: 0 | AB48: 1780198575315 | AC48: =IFERROR(XLOOKUP(SUBSTITUTE(A48,"-","_"),Recipes!$A:$A,Recipes!$AH:$AH,FALSE),FALSE) | AD48: [] | AH48: pack_000_import_20260603_2145 | AI48: imported_needs_review | AJ48: NO | AK48: Missing: instructions; Images intentionally blank for current app bulk import; use asset pipeline later.
A49: siesta | B49: Siesta | C49: Sour | D49: Daisy | E49: Tequila | F49: Coupe | G49: Aperitivo | H49: Summer | I49: Easy | J49: Up | K49: ["Boozy","Sour/Tart","Bitter","Fruity","Light/Refreshing"] | L49: 6 | M49: 2 | N49: 6 | O49: 4 | P49: 4 | Q49: 0 | R49: 0 | S49: 0 | T49: 1 | U49: [{"name":"Blanco tequila","amount":"2","unit":"oz"},{"name":"Campari","amount":"0.5","unit":"oz"},{"name":"Lime juice","amount":"0.5","unit":"oz"},{"name":"Grapefruit juice","amount":"0.5","unit":"oz"},{"name":"Simple syrup","amount":"0.5","unit":"oz"}] | W49: From Steve the Bartender's Top 10 list. | Y49: Substitute Aperol for Campari for a softer, less bitter result. | AA49: 0 | AB49: 1780198575316 | AC49: =IFERROR(XLOOKUP(SUBSTITUTE(A49,"-","_"),Recipes!$A:$A,Recipes!$AH:$AH,FALSE),FALSE) | AD49: [] | AH49: pack_000_import_20260603_2145 | AI49: imported_needs_review | AJ49: NO | AK49: Missing: instructions; Images intentionally blank for current app bulk import; use asset pipeline later.
A50: monella-sour | B50: Monella Sour | C50: Sour | D50: Core Sour | E50: Vodka | F50: Coupe | G50: Party | H50: Summer | I50: Easy | J50: Up | K50: ["Sour/Tart","Fruity","Light/Refreshing","Spicy/Warming"] | L50: 5 | M50: 3 | N50: 5 | O50: 0 | P50: 4 | Q50: 0 | R50: 0 | S50: 3 | T50: 1 | U50: [{"name":"Vodka","amount":"1.5","unit":"oz"},{"name":"Orange juice","amount":"1","unit":"oz"},{"name":"Cinnamon syrup, Liber & Co.","amount":"0.5","unit":"oz"},{"name":"Lime juice","amount":"0.5","unit":"oz"}] | W50: From Steve the Bartender's Top 10 list. | Y50: Substitute mezcal for the base spirit for a smoky variation. | AA50: 0 | AB50: 1780198575317 | AC50: =IFERROR(XLOOKUP(SUBSTITUTE(A50,"-","_"),Recipes!$A:$A,Recipes!$AH:$AH,FALSE),FALSE) | AD50: [] | AH50: pack_000_import_20260603_2145 | AI50: imported_needs_review | AJ50: NO | AK50: Missing: instructions; Images intentionally blank for current app bulk import; use asset pipeline later.
A51: shakedown-street | B51: Shakedown Street | C51: Sour | D51: Core Sour | E51: Tequila | F51: Coupe | G51: Aperitivo | H51: Summer | I51: Easy | J51: Up | K51: ["Boozy","Sour/Tart","Fruity","Light/Refreshing"] | L51: 6 | M51: 2 | N51: 5 | O51: 3 | P51: 3 | Q51: 0 | R51: 0 | S51: 0 | T51: 1 | U51: [{"name":"Blanco tequila","amount":"2","unit":"oz"},{"name":"Aperol","amount":"0.5","unit":"oz"},{"name":"Lemon juice","amount":"0.75","unit":"oz"},{"name":"Agave syrup","amount":"0.25","unit":"oz"},{"name":"Cucumber slice, muddled","amount":"1","unit":"whole"}] | W51: From Steve the Bartender's Top 10 list. | Y51: Substitute bourbon for rye for a sweeter, rounder result. | AA51: 0 | AB51: 1780198575318 | AC51: =IFERROR(XLOOKUP(SUBSTITUTE(A51,"-","_"),Recipes!$A:$A,Recipes!$AH:$AH,FALSE),FALSE) | AD51: [] | AH51: pack_000_import_20260603_2145 | AI51: imported_needs_review | AJ51: NO | AK51: Missing: instructions; Images intentionally blank for current app bulk import; use asset pipeline later.
A52: black-prince | B52: The Black Prince | C52: Old Fashioned | D52: Core Old Fashioned | E52: Rum | F52: Rocks/Old Fashioned | G52: Nightcap | H52: Fall | I52: Easy | J52: On the Rocks | K52: ["Boozy","Bitter","Rich","Herbal/Botanical","Elegant"] | L52: 7 | M52: 3 | N52: 0 | O52: 7 | P52: 1 | Q52: 5 | R52: 1 | S52: 1 | T52: 6 | U52: [{"name":"Aged rum","amount":"2","unit":"oz"},{"name":"Punt e Mes","amount":"0.75","unit":"oz"},{"name":"Amaro Averna","amount":"0.5","unit":"oz"},{"name":"Orange bitters, Steve the Bartender","amount":"1","unit":"dash"}] | W52: From Steve the Bartender's Top 10 list. | Y52: Add a barspoon of blackberry liqueur for a fruitier, deeper result. | AA52: 0 | AB52: 1780198575319 | AC52: =IFERROR(XLOOKUP(SUBSTITUTE(A52,"-","_"),Recipes!$A:$A,Recipes!$AH:$AH,FALSE),FALSE) | AD52: [] | AH52: pack_000_import_20260603_2145 | AI52: imported_needs_review | AJ52: NO | AK52: Missing: instructions; Images intentionally blank for current app bulk import; use asset pipeline later.
A53: muddled-mission | B53: Muddled Mission | C53: Sour | D53: Smash | E53: Gin | F53: Coupe | G53: Party | H53: Spring | I53: Easy | J53: Up | K53: ["Boozy","Sour/Tart","Fruity","Herbal/Botanical","Floral"] | L53: 6 | M53: 4 | N53: 5 | O53: 0 | P53: 4 | Q53: 5 | R53: 0 | S53: 0 | T53: 2 | U53: [{"name":"Dry gin","amount":"1.5","unit":"oz"},{"name":"St-Germain elderflower liqueur","amount":"1","unit":"oz"},{"name":"Yellow Chartreuse","amount":"0.25","unit":"oz"},{"name":"Lemon juice","amount":"0.75","unit":"oz"},{"name":"Strawberry, muddled","amount":"1","unit":"whole"}] | W53: From Steve the Bartender's Top 10 list. | Y53: Substitute gin for vodka for a more botanical variation. | AA53: 0 | AB53: 1780198575320 | AC53: =IFERROR(XLOOKUP(SUBSTITUTE(A53,"-","_"),Recipes!$A:$A,Recipes!$AH:$AH,FALSE),FALSE) | AD53: [] | AH53: pack_000_import_20260603_2145 | AI53: imported_needs_review | AJ53: NO | AK53: Missing: instructions; Images intentionally blank for current app bulk import; use asset pipeline later.
A54: bad-birdy-sangria | B54: Bad Birdy's Sangria | C54: Spritz & Aperitivo | D54: Wine Spritz | E54: Wine | F54: Highball | G54: Party | H54: Summer | I54: Easy | J54: On the Rocks | K54: ["Fruity","Light/Refreshing","Sparkling","Elegant"] | L54: 4 | M54: 4 | N54: 4 | O54: 2 | P54: 6 | Q54: 1 | R54: 0 | S54: 2 | T54: 3 | U54: [{"name":"Angostura bitters","amount":"2","unit":"dash"},{"name":"Lime juice","amount":"0.5","unit":"oz"},{"name":"Lemon juice","amount":"0.5","unit":"oz"},{"name":"Cinnamon syrup","amount":"0.5","unit":"oz"},{"name":"Pineapple juice","amount":"0.75","unit":"oz"},{"name":"Brandy","amount":"0.75","unit":"oz"},{"name":"Red wine, medium bodied","amount":"2","unit":"oz"},{"name":"Coca-Cola","amount":"1","unit":"splash"}] | W54: Created by mixologist Bad Birdy. Garnish with a mint sprig and lime wheel. | X54: Created by mixologist Bad Birdy, this elevated Sangria riff layers citrus, warm spice, and tropical fruit over a medium-bodied red wine base, with brandy adding depth and a splash of Coke lifting the whole thing with a whisper of sweetness and fizz. It drinks like a party in a glass. | Y54: Adjust the fruit selection seasonally — stone fruit in summer, citrus in winter. | AA54: 0 | AB54: 1780198575321 | AC54: =IFERROR(XLOOKUP(SUBSTITUTE(A54,"-","_"),Recipes!$A:$A,Recipes!$AH:$AH,FALSE),FALSE) | AD54: [] | AH54: pack_000_import_20260603_2145 | AI54: imported_needs_review | AJ54: NO | AK54: Missing: instructions; Images intentionally blank for current app bulk import; use asset pipeline later.
A55: rattlesnake | B55: Rattlesnake | C55: Sour | D55: Egg White Sour | E55: Rye | F55: Coupe | G55: Nightcap | H55: Year-Round | I55: Medium | J55: Up | K55: ["Boozy","Sour/Tart","Herbal/Botanical","Elegant","Frothy"] | L55: 7 | M55: 3 | N55: 5 | O55: 2 | P55: 0 | Q55: 4 | R55: 0 | S55: 0 | T55: 3 | U55: [{"name":"Rye whiskey","amount":"2","unit":"oz"},{"name":"Lemon juice","amount":"0.75","unit":"oz"},{"name":"Simple syrup","amount":"0.75","unit":"oz"},{"name":"Absinthe","amount":"2","unit":"dash"},{"name":"Egg white","amount":"1","unit":"whole"}] | V55: Add all ingredients to a shaker and dry shake without ice. Add ice and shake again until chilled. Fine strain into a coupe glass. Garnish with an Angostura bitters swirl. | W55: Garnish: Angostura bitters swirl. | X55: Created by Natasha David in New York City. David herself admits she is not a huge fan of egg whites or absinthe — yet finds the Rattlesnake unexpectedly balanced. As she puts it: ingredients in the right proportions create harmony, even if they are not always up your alley. A frothy, absinthe-spiked Whiskey Sour that earns its name. | Y55: Omit the absinthe rinse for a more straightforward whiskey sour. The Corpse Reviver No. 2 shares the absinthe rinse technique. | AA55: 0 | AB55: 1780198575323 | AC55: =IFERROR(XLOOKUP(SUBSTITUTE(A55,"-","_"),Recipes!$A:$A,Recipes!$AH:$AH,FALSE),FALSE) | AD55: [] | AH55: pack_000_import_20260603_2145 | AI55: imported_needs_review | AJ55: YES | AK55: Images intentionally blank for current app bulk import; use asset pipeline later.
A56: fresh-fruit-citronade | B56: Fresh Fruit Citronade | C56: Sour | D56: Smash | E56: Vodka | F56: Highball | G56: Party | H56: Summer | I56: Easy | J56: On the Rocks | K56: ["Fruity","Light/Refreshing","Herbal/Botanical","Spicy/Warming"] | L56: 4 | M56: 3 | N56: 5 | O56: 0 | P56: 6 | Q56: 3 | R56: 0 | S56: 2 | T56: 1 | U56: [{"name":"Vodka (Effen or similar)","amount":"1.5","unit":"oz"},{"name":"Solerno blood orange liqueur","amount":"0.25","unit":"oz"},{"name":"Fresh lemon juice","amount":"0.75","unit":"oz"},{"name":"Simple syrup","amount":"0.25","unit":"oz"},{"name":"Fresh strawberries, sliced","amount":"2","unit":"whole"},{"name":"Fresh basil leaves","amount":"3-4","unit":"whole"},{"name":"Freshly cracked black pepper","amount":"2","unit":"crack"},{"name":"Soda water","amount":"1","unit":"splash"}] | V56: Muddle the strawberries, basil, simple syrup, and black pepper in a shaker until the berries are smashed and the basil is fragrant. Add the vodka, Solerno, lemon juice, and ice and shake vigorously for 10 seconds. Dirty pour the entire contents directly into a tall Collins glass. Top with a splash of soda water and garnish with a strawberry slice or fresh basil sprig. | W56: The dirty pour keeps the muddled fruit in the glass, creating layered flavor as you drink. The black pepper is the secret — do not skip it. Solerno bridges the citrus and strawberry beautifully; Cointreau works as a substitute. | X56: Started life as an Applebee's menu item — proof that chain restaurants occasionally stumble onto something worth stealing. Re-specced for Alchemy with fresh lemon, Solerno, and an extra crack of pepper. A dirty pour keeps the muddled fruit and broken ice in the glass, layering the flavor from first sip to last. Sorry, Applebee's. | Y56: The original Applebee's spec that started this: 1.5 oz citron vodka, 2 fresh strawberries, 3 basil leaves, pinch of black pepper, good quality lemonade, seltzer. Build in glass — muddle strawberries, pepper, and basil gently, add vodka and ice and stir, top with lemonade and seltzer, then gently lift and stir to combine. The current Alchemy spec is a proper cocktail rebuild of that same spirit. | AA56: 0 | AB56: 1780198575324 | AC56: =IFERROR(XLOOKUP(SUBSTITUTE(A56,"-","_"),Recipes!$A:$A,Recipes!$AH:$AH,FALSE),FALSE) | AD56: [] | AH56: pack_000_import_20260603_2145 | AI56: imported_needs_review | AJ56: YES | AK56: Images intentionally blank for current app bulk import; use asset pipeline later.
A57: berry-gin-fizz | B57: Berry Gin Fizz | C57: Sour | D57: Fizz | E57: Gin | F57: Highball | G57: Party | H57: Summer | I57: Easy | J57: On the Rocks | K57: ["Fruity","Light/Refreshing","Sour/Tart","Sparkling"] | L57: 4 | M57: 3 | N57: 4 | O57: 1 | P57: 6 | Q57: 2 | R57: 0 | S57: 0 | T57: 1 | U57: [{"name":"Gin","amount":"1.75","unit":"oz"},{"name":"Lemon juice","amount":"0.75","unit":"oz"},{"name":"Simple syrup","amount":"0.33","unit":"oz"},{"name":"Raspberries or blueberries","amount":"1","unit":"handful"},{"name":"Soda water","amount":"2","unit":"oz"}] | V57: Lightly muddle the berries in the glass. Add gin, lemon juice, simple syrup, and ice. Stir gently to combine. Top with soda water. Garnish with a mint sprig for extra freshness. | W57: The recipe calls for The Great Eight Gin, an Austrian craft dry gin from the Peter Affenzeller distillery in Upper Austria, named for its eight botanicals. Any quality dry gin works beautifully. Use raspberries for tartness, blueberries for a deeper, earthier note, or a mix of both. | X57: Discovered on a German cocktail website, this is a modern riff on the classic Gin Fizz — one of the most enduring cocktail families of the 1920s. The addition of fresh berries gives it a playful, summery character that feels entirely contemporary. The Fizz family template — spirit, citrus, sweetener, soda — is one of the most riff-able in the cocktail canon. | AA57: 0 | AB57: 1780198575325 | AC57: =IFERROR(XLOOKUP(SUBSTITUTE(A57,"-","_"),Recipes!$A:$A,Recipes!$AH:$AH,FALSE),FALSE) | AD57: [] | AH57: pack_000_import_20260603_2145 | AI57: imported_needs_review | AJ57: YES | AK57: Images intentionally blank for current app bulk import; use asset pipeline later.
A58: rosemary-gin-smash | B58: Rosemary Gin Smash | C58: Sour | D58: Smash | E58: Gin | F58: Rocks/Old Fashioned | G58: Aperitivo | H58: Summer | I58: Easy | J58: On the Rocks | K58: ["Herbal/Botanical","Light/Refreshing","Sour/Tart","Elegant"] | L58: 5 | M58: 3 | N58: 4 | O58: 1 | P58: 0 | Q58: 7 | R58: 0 | S58: 1 | T58: 1 | U58: [{"name":"Gin","amount":"1.75","unit":"oz"},{"name":"Lemon juice","amount":"0.75","unit":"oz"},{"name":"Simple syrup","amount":"0.5","unit":"oz"},{"name":"Fresh rosemary","amount":"1","unit":"sprig"}] | V58: Muddle the rosemary sprig in the glass to release its oils — press gently, do not strip the leaves. Add gin, lemon juice, and simple syrup. Fill with ice and stir to combine. Garnish with a lemon slice and a fresh rosemary sprig. | W58: Built in the glass with no shaking — try it as written first for comparison, then try shaking for more dilution and a colder result. The Great Eight Gin is an Austrian craft dry gin from the Peter Affenzeller distillery in Upper Austria. Any quality dry gin with botanical character works well here. | X58: The Smash is one of cocktailing oldest templates — spirit, herb, sugar, and seasonal fruit, dating to at least 1862. The modern gin-and-herb interpretation was pioneered by German bartender Jorg Meyer, whose Gin Basil Smash (created in 2008 at Le Lion in Hamburg) inspired a generation of herb-forward riffs. This rosemary version follows that lineage: clean, aromatic, and deeply refreshing. Found on a German cocktail website featuring The Great Eight Gin, an Austrian craft dry gin from the Peter Affenzeller distillery. | Y58: The direct ancestor of this drink is the Gin Basil Smash, created by German bartender Jorg Meyer at Le Lion in Hamburg in 2008 — same template, basil instead of rosemary. Worth making both back to back. | AA58: 0 | AB58: 1780198575326 | AC58: =IFERROR(XLOOKUP(SUBSTITUTE(A58,"-","_"),Recipes!$A:$A,Recipes!$AH:$AH,FALSE),FALSE) | AD58: [] | AH58: pack_000_import_20260603_2145 | AI58: imported_needs_review | AJ58: YES | AK58: Images intentionally blank for current app bulk import; use asset pipeline later.
A59: morgenthaler-amaretto-sour | B59: Amaretto Sour | C59: Sour | D59: Egg White Sour | E59: Liqueur | F59: Rocks/Old Fashioned | G59: Nightcap | H59: Year-Round | I59: Medium | J59: On the Rocks | K59: ["Sour/Tart","Rich/Creamy","Fruity","Elegant","Frothy"] | L59: 5 | M59: 5 | N59: 5 | O59: 1 | P59: 4 | Q59: 0 | R59: 0 | S59: 0 | T59: 4 | U59: [{"name":"Amaretto","amount":"1.5","unit":"oz"},{"name":"Overproof bourbon","amount":"0.75","unit":"oz"},{"name":"Fresh lemon juice","amount":"1","unit":"oz"},{"name":"Simple syrup","amount":"1","unit":"tsp"},{"name":"Egg white","amount":"1","unit":"whole"}] | V59: Combine all ingredients in a shaker and dry shake without ice to build the foam. Add ice and shake again until well chilled. Fine strain into a rocks glass over fresh ice. Garnish with a lemon twist and a brandied cherry. | W59: The overproof bourbon is non-negotiable — it provides the backbone that makes this drink work. Without it, the amaretto overwhelms. Overproof means 100 proof (50% ABV) or higher; the higher the better. Morgenthaler recommends Bookers (typically 120-130 proof, uncut and unfiltered straight from the barrel), and he also recommends Old Grand-Dad 114 as an excellent, more accessible option. Any cask-strength bourbon in the 110-130 proof range will work beautifully. Dry shake first to build the foam, then shake with ice. Fine strain to keep it clean. Luxardo amaretto is also recommended. | X59: In 2012, Jeffrey Morgenthaler published a post titled I Make the Best Amaretto Sour in the World. The craft cocktail world had spent a decade treating the Amaretto Sour as a punchline. Morgenthaler disagreed. His revamped version adds overproof bourbon for backbone and egg white for texture, transforming a drink everyone had written off into something genuinely elegant. It is now considered a modern classic and a defining moment of the cocktail revival — proof that rehabilitation is possible. Search Morgenthaler to find all three of his recipes in the collection. | AA59: 0 | AB59: 1780198575327 | AC59: =IFERROR(XLOOKUP(SUBSTITUTE(A59,"-","_"),Recipes!$A:$A,Recipes!$AH:$AH,FALSE),FALSE) | AD59: [] | AH59: pack_000_import_20260603_2145 | AI59: imported_needs_review | AJ59: YES | AK59: Images intentionally blank for current app bulk import; use asset pipeline later.
A60: tia-mia | B60: Tia Mia | C60: Tiki & Tropical | D60: Mai Tai Style | E60: Mezcal | F60: Rocks/Old Fashioned | G60: Party | H60: Summer | I60: Medium | J60: On the Rocks | K60: ["Smoky","Fruity","Herbal/Botanical","Tiki/Tropical","Boozy"] | L60: 7 | M60: 4 | N60: 4 | O60: 1 | P60: 3 | Q60: 3 | R60: 5 | S60: 0 | T60: 2 | U60: [{"name":"Mezcal","amount":"1","unit":"oz"},{"name":"Jamaican rum","amount":"1","unit":"oz"},{"name":"Fresh lime juice","amount":"0.75","unit":"oz"},{"name":"Orgeat","amount":"0.5","unit":"oz"},{"name":"Simple syrup","amount":"0.5","unit":"oz"},{"name":"Orange curacao","amount":"0.25","unit":"oz"}] | V60: Combine all ingredients and shake with ice. Strain into a double rocks glass filled with crushed ice. Garnish with a lime wheel, mint sprig, and an orchid if you have one. | W60: The name is a play on Mai Tai — swap the letters. Tia Mia is also Spanish for my aunt, the name Mix gave to a regular she knew in Guatemala. Use a smoky, expressive mezcal — Del Maguey Vida is the classic choice. Jamaican rum brings funk and depth; any full-bodied aged Jamaican rum works. Crushed ice is part of the identity. | X60: In the mid-2000s, Ivy Mix had a habit of floating a splash of mezcal on cocktails she liked — including the Mai Tai. Around 2010, working at Lani Kai in New York, she committed to a full ounce and the Tia Mia was born. A mezcal-and-Jamaican-rum riff on Trader Vic 1944 original, it quickly earned a following among New York bartenders and drinkers and is now considered a modern tropical classic. Mix went on to co-found Leyenda in Brooklyn, a pan-Latin cocktail bar ranked among the world best, and to write Spirits of Latin America — a book that treats Latin spirits as cultural history, travel, and place, not just bottles on a backbar. | Search Ivy Mix to find more of her recipes. | Y60: The Mai Tai is the direct ancestor — substitute curacao for orgeat and lime for the base. | AA60: 0 | AB60: 1780198575329 | AC60: =IFERROR(XLOOKUP(SUBSTITUTE(A60,"-","_"),Recipes!$A:$A,Recipes!$AH:$AH,FALSE),FALSE) | AD60: [] | AH60: pack_000_import_20260603_2145 | AI60: imported_needs_review | AJ60: YES | AK60: Images intentionally blank for current app bulk import; use asset pipeline later.
A61: negroni-sbagliato | B61: Negroni Sbagliato | C61: Negroni | D61: Sbagliato Style | E61: Campari | F61: Rocks/Old Fashioned | G61: Aperitivo | H61: Year-Round | I61: Easy | J61: On the Rocks | K61: ["Bitter","Fruity","Elegant","Sparkling","Light/Refreshing"] | L61: 3 | M61: 4 | N61: 1 | O61: 5 | P61: 2 | Q61: 3 | R61: 0 | S61: 0 | T61: 2 | U61: [{"name":"Campari","amount":"1","unit":"oz"},{"name":"Sweet vermouth","amount":"1","unit":"oz"},{"name":"Prosecco","amount":"1","unit":"oz"}] | V61: Build in a rocks glass over ice. Add Campari and sweet vermouth first, then top with Prosecco. Stir gently once — just enough to combine without losing the bubbles. Garnish with an orange slice. | W61: Do not shake. Do not over-stir. The Prosecco is delicate and the bubbles are part of the drink. Use a good Prosecco — it is a third of the cocktail. Cava works beautifully as a slightly drier alternative. | X61: Sbagliato means mistaken in Italian. At Bar Basso in Milan sometime in the 1970s, bartender Mirko Stocchetto was making a Negroni during a busy service and accidentally reached for a bottle of Prosecco instead of gin. Rather than discard it, he served it. The guest loved it. It became a house specialty and eventually a global classic. In 2022 a viral TikTok interview with House of the Dragon actress Olivia Cooke — in which she ordered a Negroni Sbagliato with Prosecco in a particular tone of voice — made it briefly the most Googled cocktail in the world. The happy accident has never looked back. | Y61: The classic Negroni: substitute gin for Prosecco. Large-Batch version: equal bottles of each ingredient in a punch bowl. | AA61: 0 | AB61: 1780198575331 | AC61: =IFERROR(XLOOKUP(SUBSTITUTE(A61,"-","_"),Recipes!$A:$A,Recipes!$AH:$AH,FALSE),FALSE) | AD61: [] | AH61: pack_000_import_20260603_2145 | AI61: imported_needs_review | AJ61: YES | AK61: Images intentionally blank for current app bulk import; use asset pipeline later.
A62: americano-cocktail | B62: Americano | C62: Negroni | D62: Americano Style | E62: Campari | F62: Rocks/Old Fashioned | G62: Aperitivo | H62: Summer | I62: Easy | J62: On the Rocks | K62: ["Bitter","Light/Refreshing","Herbal/Botanical","Sparkling"] | L62: 2 | M62: 3 | N62: 1 | O62: 5 | P62: 1 | Q62: 3 | R62: 0 | S62: 0 | T62: 1 | U62: [{"name":"Campari","amount":"1.5","unit":"oz"},{"name":"Sweet vermouth","amount":"1.5","unit":"oz"},{"name":"Soda water","amount":"2","unit":"oz"}] | V62: Build in a rocks glass over ice. Add Campari and sweet vermouth, then top with soda water. Stir gently. Garnish with an orange slice or lemon twist. | W62: The Americano is the ancestor of the Negroni — substitute gin for the soda water and you have one. Lower-ABV, endlessly refreshing, and the perfect introduction to the bitter aperitivo style. James Bond orders one in the first chapter of Casino Royale — his very first drink in the entire canon. | X62: The Americano traces directly to the Milano Torino — equal parts Campari and sweet vermouth — which had been popular in Italy since the 1860s. When American soldiers arrived in Italy during World War I, many found the Mi-To too bitter and too strong. Italian bartenders began adding soda water to lengthen and lighten it for their American guests. The name stuck. It is one of the oldest drinks in the Campari lineage and the direct precursor to the Negroni — Count Camillo Negroni simply asked his bartender to replace the soda with gin. | Y62: Negroni: add gin. Sbagliato: substitute Prosecco for soda. | AA62: 0 | AB62: 1780198575332 | AC62: =IFERROR(XLOOKUP(SUBSTITUTE(A62,"-","_"),Recipes!$A:$A,Recipes!$AH:$AH,FALSE),FALSE) | AD62: [] | AH62: pack_000_import_20260603_2145 | AI62: imported_needs_review | AJ62: YES | AK62: Images intentionally blank for current app bulk import; use asset pipeline later.
A63: french-blonde | B63: French Blonde | C63: Sour | D63: Daisy | E63: Gin | F63: Coupe | G63: Aperitivo | H63: Spring | I63: Easy | J63: Up | K63: ["Floral","Fruity","Light/Refreshing","Elegant","Sour/Tart"] | L63: 4 | M63: 4 | N63: 4 | O63: 1 | P63: 5 | Q63: 3 | R63: 0 | S63: 0 | T63: 1 | U63: [{"name":"Gin","amount":"1","unit":"oz"},{"name":"Lillet Blanc","amount":"1.5","unit":"oz"},{"name":"Fresh grapefruit juice","amount":"2","unit":"oz"},{"name":"St-Germain elderflower liqueur","amount":"0.5","unit":"oz"},{"name":"Lemon bitters","amount":"1","unit":"dash"}] | V63: Combine all ingredients in a shaker with ice. Shake vigorously for 30 seconds. Double strain into a chilled coupe or Nick and Nora glass. Garnish with a grapefruit twist. | W63: Use fresh grapefruit juice — not bottled. Oro Blanco (white grapefruit) gives the palest, most elegant color. Pink grapefruit works just as well and adds a peachy hue. A London dry gin is traditional but a citrus-forward gin elevates the floral notes beautifully. | X63: The French Blonde is gin, Lillet Blanc, fresh grapefruit, and St-Germain elderflower — a drink that sits somewhere between a Greyhound and a White Negroni, floral and citrus-bright and unmistakably French in character. It came to widespread attention when US Weekly reported it as Taylor Swift favorite cocktail during the Eras Tour era — and if the Eras Tour can boost the global economy, a Swift endorsement was always going to move bottles of Lillet. Bartenders everywhere had better know how to make it. The good news: it deserves the attention entirely on its own merits. | AA63: 0 | AB63: 1780198575333 | AC63: =IFERROR(XLOOKUP(SUBSTITUTE(A63,"-","_"),Recipes!$A:$A,Recipes!$AH:$AH,FALSE),FALSE) | AD63: [] | AH63: pack_000_import_20260603_2145 | AI63: imported_needs_review | AJ63: YES | AK63: Images intentionally blank for current app bulk import; use asset pipeline later.
A64: caipirinha | B64: Caipirinha | C64: Sour | D64: Smash | E64: Cachaca | F64: Rocks/Old Fashioned | G64: Party | H64: Summer | I64: Easy | J64: On the Rocks | K64: ["Sour/Tart","Fruity","Light/Refreshing","Boozy"] | L64: 6 | M64: 3 | N64: 5 | O64: 0 | P64: 3 | Q64: 1 | R64: 0 | S64: 0 | T64: 1 | U64: [{"name":"Cachaca","amount":"2","unit":"oz"},{"name":"Fresh lime, cut into wedges","amount":"0.5","unit":"whole"},{"name":"White sugar","amount":"2","unit":"tsp"}] | V64: Cut off the top and tail of the lime half and remove the white pith from the center. Cut into 4 wedges and add to a sturdy rocks glass with the sugar. Muddle firmly, pressing on the flesh rather than the skin to avoid bitterness. Add cachaca and fill with ice. Stir until well chilled, about 20 seconds. No garnish needed — the lime is already in the glass. | W64: The white pith is the enemy — remove it before muddling or it will add bitterness. Press on the flesh, not the skin. Brazilian tradition says stirred, never shaken. Use 2 teaspoons of sugar as a starting point and adjust to your lime and preference. Leblon and Novo Fogo are excellent cachacas for the Caipirinha. | X64: The national cocktail of Brazil and one of the great three-ingredient drinks in the world. Cachaca, lime, sugar — that is all. The name means little country girl in Portuguese, and the drink most likely originated in Sao Paulo, though its precise history is contested. One persistent theory holds that an early version was created as a folk remedy during the Spanish Flu pandemic of 1918 — cachaca, lime, honey, and garlic — and that the garlic was eventually dropped as the drink moved from medicine cabinet to bar. In 2003 the Brazilian government officially declared it the national cocktail. In 2024 it ranked third in the world on TasteAtlas. Cachaca is not rum — both come from sugarcane, but cachaca is distilled from fresh-pressed cane juice while rum is made from molasses. That difference is everything. | Y64: Strawberry Caipirinha: muddle 3-4 hulled strawberries with the lime and sugar before adding cachaca. Passionfruit Caipirinha: add 1 oz fresh passionfruit pulp. Caipiroska: substitute vodka for cachaca. Caipirissima: substitute white rum for cachaca. | AA64: 0 | AB64: 1780198575334 | AC64: =IFERROR(XLOOKUP(SUBSTITUTE(A64,"-","_"),Recipes!$A:$A,Recipes!$AH:$AH,FALSE),FALSE) | AD64: [] | AH64: pack_000_import_20260603_2145 | AI64: imported_needs_review | AJ64: YES | AK64: Images intentionally blank for current app bulk import; use asset pipeline later.
A65: strawberry-caipirinha | B65: Strawberry Caipirinha | C65: Sour | D65: Smash | E65: Cachaca | F65: Rocks/Old Fashioned | G65: Party | H65: Summer | I65: Easy | J65: On the Rocks | K65: ["Fruity","Sour/Tart","Light/Refreshing","Sweet"] | L65: 5 | M65: 4 | N65: 4 | O65: 0 | P65: 6 | Q65: 0 | R65: 0 | S65: 0 | T65: 1 | U65: [{"name":"Cachaca","amount":"2","unit":"oz"},{"name":"Fresh strawberries, hulled","amount":"4","unit":"whole"},{"name":"Fresh lime, cut into wedges","amount":"0.5","unit":"whole"},{"name":"White sugar","amount":"2","unit":"tsp"}] | V65: Remove the white pith from the lime half and cut into 4 wedges. Add to a rocks glass with the strawberries and sugar. Muddle firmly until the strawberries are fully broken down and the lime has released its juice. Add cachaca and fill with crushed or regular ice. Stir well. Garnish with a fresh strawberry on the rim. | W65: Use ripe, in-season strawberries — underripe strawberries are mostly water and will produce a flat, pink drink rather than a vibrant one. Taste before adding more sugar as ripe strawberries bring their own sweetness. Crushed ice gives a better result than cubed here. | X65: The Strawberry Caipirinha is the most popular variation of Brazil national cocktail — and the one most likely to convert someone who thinks they do not like cachaca. The fruit softens the spirit forward edge of the classic while the lime keeps the brightness. It follows the same logic as the classic: muddle, spirit, ice. The template is unchanged. Only the fruit has moved. | Y65: Add a few fresh basil leaves to the muddle for an herbal variation. A splash of fresh orange juice adds brightness. For a sparkling version, top with a splash of soda water. | AA65: 0 | AB65: 1780198575335 | AC65: =IFERROR(XLOOKUP(SUBSTITUTE(A65,"-","_"),Recipes!$A:$A,Recipes!$AH:$AH,FALSE),FALSE) | AD65: [] | AH65: pack_000_import_20260603_2145 | AI65: imported_needs_review | AJ65: YES | AK65: Images intentionally blank for current app bulk import; use asset pipeline later.
A66: white-lady | B66: White Lady | C66: Sour | D66: Daisy | E66: Gin | F66: Coupe | G66: Aperitivo | H66: Year-Round | I66: Easy | J66: Up | K66: ["Elegant","Sour/Tart","Fruity","Floral","Frothy"] | L66: 6 | M66: 3 | N66: 4 | O66: 0 | P66: 2 | Q66: 3 | R66: 0 | S66: 0 | T66: 2 | U66: [{"name":"Gin","amount":"1.5","unit":"oz"},{"name":"Cointreau","amount":"0.75","unit":"oz"},{"name":"Fresh lemon juice","amount":"0.75","unit":"oz"},{"name":"Egg white","amount":"1","unit":"whole"}] | V66: Dry shake all ingredients without ice to build the foam. Add ice and shake again until well chilled. Fine strain into a chilled coupe. No garnish, or a thin lemon twist if you must. | W66: The egg white is optional but highly recommended — it gives the drink a silky texture and a beautiful white foam that explains the name. Dry shake first, then shake with ice. Cointreau specifically, not generic triple sec — the quality of the orange liqueur matters here. A good London dry gin is the right choice. | X66: Harry Craddock created the White Lady at the American Bar at the Savoy in London in 1930, publishing it in The Savoy Cocktail Book the same year — one of the most important bartending reference books ever written. It is a Daisy in its purest form: gin, orange liqueur, citrus, served up. The egg white was Craddock addition, lifting a clean three-ingredient Sour into something more refined. The Savoy Cocktail Book codified an entire era of classic cocktail making during Prohibition, when American bartenders fled to London and brought their craft with them. The White Lady is one of its finest results. | Y66: Omit the egg white for a sharper, more citrus-forward version. Add a dash of orange bitters for depth. Some bartenders add a barspoon of simple syrup for a rounder finish. | AA66: 0 | AB66: 1780198575336 | AC66: =IFERROR(XLOOKUP(SUBSTITUTE(A66,"-","_"),Recipes!$A:$A,Recipes!$AH:$AH,FALSE),FALSE) | AD66: [] | AH66: pack_000_import_20260603_2145 | AI66: imported_needs_review | AJ66: YES | AK66: Images intentionally blank for current app bulk import; use asset pipeline later.
